Workbook
Name UPDATE: 'Data Sheet >'!$E$1

Sheet Teaser
B2: ='Data Sheet >'!B1&" - One Page Profile" -> INFOSYS LTD - One Page Profile
C4: ='Input Sheet'!C3 -> With over four decades of experience in managing the systems and workings of global enterprises, we expertly steer clients, in 59 countries, as they navigate their digital transformation powered by cloud and AI. We enable them with an AI-first core, empower the business with agile digital at scale and drive continuous improvement with always-on learning through the transfer of digital skills, expertise, and ideas from our innovation ecosystem.
B5: INR (Crs)
B6: Key Financial Metrics | C6: ='Data Sheet >'!G16 -> 44651 | D6: ='Data Sheet >'!H16 -> 45016 | E6: ='Data Sheet >'!I16 -> 45382 | F6: ='Data Sheet >'!J16 -> 45747 | G6: ='Data Sheet >'!K16 -> 46112 | I6: Share Price - 5 Year
B8: Total Sales | C8: ='Data Sheet >'!G17 -> 121641 | D8: ='Data Sheet >'!H17 -> 146767 | E8: ='Data Sheet >'!I17 -> 153670 | F8: ='Data Sheet >'!J17 -> 162990 | G8: ='Data Sheet >'!K17 -> 178650
B9: Sales Growth (y-o-y) | C9: ='Data Sheet >'!G17/'Data Sheet >'!F17-1 -> 0.21069552 | D9: ='Data Sheet >'!H17/'Data Sheet >'!G17-1 -> 0.20655864 | E9: ='Data Sheet >'!I17/'Data Sheet >'!H17-1 -> 0.047033734 | F9: ='Data Sheet >'!J17/'Data Sheet >'!I17-1 -> 0.060649444 | G9: ='Data Sheet >'!K17/'Data Sheet >'!J17-1 -> 0.096079514
B10: Gross Profit Margins (%) | C10: ='Income Statement '!C12 -> 0.82882416 | D10: ='Income Statement '!D12 -> 0.81940082 | E10: ='Income Statement '!E12 -> 0.82173489 | F10: ='Income Statement '!F12 -> 0.81215412 | G10: ='Income Statement '!G12 -> 0.81446963
B11: EBITDA Margins (%) | C11: ='Income Statement '!C18 -> 0.25888475 | D11: ='Income Statement '!D18 -> 0.23935898 | E11: ='Income Statement '!E18 -> 0.2370339 | F11: ='Income Statement '!F18 -> 0.24072642 | G11: ='Income Statement '!G18 -> 0.23666387
B12: EBIT Margins (%) | C12: ='Income Statement '!C24 -> 0.23030886 | D12: ='Income Statement '!D24 -> 0.21057186 | E12: ='Income Statement '!E24 -> 0.20659205 | F12: ='Income Statement '!F24 -> 0.21120314 | G12: ='Income Statement '!G24 -> 0.20922474
B13: Net Profit Margins (%) | C13: ='Income Statement '!C36 -> 0.16319333 | D13: ='Income Statement '!D36 -> 0.14585704 | E13: ='Income Statement '!E36 -> 0.14015097 | F13: ='Income Statement '!F36 -> 0.14203325 | G13: ='Income Statement '!G36 -> 0.14800448
B14: Earning Per Share (In Rs) | C14: ='Income Statement '!C40 -> 47.189008 | D14: ='Income Statement '!D40 -> 51.60054 | E14: ='Income Statement '!E40 -> 51.885133 | F14: ='Income Statement '!F40 -> 55.73881 | G14: ='Income Statement '!G40 -> 65.196272
B15: EPS Growth (y-o-y) | C15: ='Profit & Loss'!G13/'Profit & Loss'!F13-1 -> 0.15724348 | D15: ='Profit & Loss'!H13/'Profit & Loss'!G13-1 -> 0.10504043 | E15: ='Profit & Loss'!I13/'Profit & Loss'!H13-1 -> 0.088128839 | F15: ='Profit & Loss'!J13/'Profit & Loss'!I13-1 -> 0.017709137 | G15: ='Profit & Loss'!K13/'Profit & Loss'!J13-1 -> 0.12863452
B16: Dividend Per Share (In Rs) | C16: ='Income Statement '!C43 -> 30.92115 | D16: ='Income Statement '!D43 -> 33.913127 | E16: ='Income Statement '!E43 -> 45.901371 | F16: ='Income Statement '!F43 -> 42.924422 | G16: ='Income Statement '!G43 -> 47.91005
B17: DSP Growth (y-o-y) | C17: ='Profit & Loss'!G29 -> 0.14865158 | D17: ='Profit & Loss'!H29 -> 0.096761529 | E17: ='Profit & Loss'!I29 -> 0.35349861 | F17: ='Profit & Loss'!J29 -> -0.064855345 | G17: ='Profit & Loss'!K29 -> 0.116149
B19: Key Financial Ratios | C19: =C6 -> 44651 | D19: =D6 -> 45016 | E19: =E6 -> 45382 | F19: =F6 -> 45747 | G19: =G6 -> 46112 | I19: Volume - 5 Year
B21: Price to Earning | C21: ='Profit & Loss'!G14 -> 36.280171 | D21: ='Profit & Loss'!H14 -> 24.585986 | E21: ='Profit & Loss'!I14 -> 23.703944 | F21: ='Profit & Loss'!J14 -> 24.420247 | G21: ='Profit & Loss'!K14 -> 17.228035
B22: EV/EBITDA | C22: ='Profit & Loss'!G35 -> 25.091505 | D22: ='Profit & Loss'!H35 -> 16.752785 | E22: ='Profit & Loss'!I35 -> 16.894951 | F22: ='Profit & Loss'!J35 -> 16.212409 | G22: ='Profit & Loss'!K35 -> 11.687993
B23: EV/Sales | C23: ='Profit & Loss'!G36 -> 6.4958081 | D23: ='Profit & Loss'!H36 -> 4.0099296 | E23: ='Profit & Loss'!I36 -> 4.0046761 | F23: ='Profit & Loss'!J36 -> 3.9027552 | G23: ='Profit & Loss'!K36 -> 2.7661256
B24: Price to Book Value | C24: ='Profit & Loss'!G37 -> 10.645715 | D24: ='Profit & Loss'!H37 -> 7.8560258 | E24: ='Profit & Loss'!I37 -> 7.0568974 | F24: ='Profit & Loss'!J37 -> 6.8080952 | G24: ='Profit & Loss'!K37 -> 5.4623846
B25: Return on Equity (%) | C25: ='His Balance Sheet'!G23 -> 0.29343066 | D25: ='His Balance Sheet'!H23 -> 0.31953267 | E25: ='His Balance Sheet'!I23 -> 0.29770984 | F25: ='His Balance Sheet'!J23 -> 0.27878895 | G25: ='His Balance Sheet'!K23 -> 0.31706371
B26: Return oc Capital Employed | C26: ='His Balance Sheet'!G24 -> 0.37304615 | D26: ='His Balance Sheet'!H24 -> 0.40850909 | E26: ='His Balance Sheet'!I24 -> 0.40468196 | F26: ='His Balance Sheet'!J24 -> 0.37925394 | G26: ='His Balance Sheet'!K24 -> 0.39220082
B28: ='Input Sheet'!B11 -> Shareholder's name | C28: ='Input Sheet'!C11 -> No. of Share (in crs) | D28: ='Input Sheet'!D11 -> Shareholding (%) | E28: ='Input Sheet'!E11 -> Market Value (in crs) | G28: Shareholding Pattern
B30: ='Input Sheet'!B12 -> LIFE INSURANCE CORPORATION OF INDIA - ULIF00220091 | C30: ='Input Sheet'!C12 -> 43.859487 | D30: ='Input Sheet'!D12 -> 0.118 | E30: ='Input Sheet'!E12 -> 50613.848
B31: ='Input Sheet'!B13 -> SBI MUTUAL FUND | C31: ='Input Sheet'!C13 -> 16.748512 | D31: ='Input Sheet'!D13 -> 0.0451 | E31: ='Input Sheet'!E13 -> 19327.783
B32: ='Input Sheet'!B14 -> ICICI PRUDENTIAL MUTUAL FUND | C32: ='Input Sheet'!C14 -> 14.669216 | D32: ='Input Sheet'!D14 -> 0.0395 | E32: ='Input Sheet'!E14 -> 16928.275
B33: ='Input Sheet'!B15 -> National Pension System Trust | C33: ='Input Sheet'!C15 -> 12.570505 | D33: ='Input Sheet'!D15 -> 0.0338 | E33: ='Input Sheet'!E15 -> 14506.362
B34: ='Input Sheet'!B16 -> NIPPON LIFE INDIA TRUSTEE | C34: ='Input Sheet'!C16 -> 9.8562135 | D34: ='Input Sheet'!D16 -> 0.0265 | E34: ='Input Sheet'!E16 -> 11374.07
B35: ='Input Sheet'!B17 -> SUDHA GOPALAKRISHNAN | C35: ='Input Sheet'!C17 -> 9.5357 | D35: ='Input Sheet'!D17 -> 0.0257 | E35: ='Input Sheet'!E17 -> 11004.198
B36: ='Input Sheet'!B18 -> UTI MUTUAL FUND | C36: ='Input Sheet'!C18 -> 7.188733 | D36: ='Input Sheet'!D18 -> 0.0193 | E36: ='Input Sheet'!E18 -> 8295.7979
B37: ='Input Sheet'!B19 -> HDFC MUTUAL FUND | C37: ='Input Sheet'!C19 -> 6.3538616 | D37: ='Input Sheet'!D19 -> 0.0171 | E37: ='Input Sheet'!E19 -> 7332.3563
B38: ='Input Sheet'!B20 -> ROHAN MURTY | C38: ='Input Sheet'!C20 -> 6.0812892 | D38: ='Input Sheet'!D20 -> 0.0164 | E38: ='Input Sheet'!E20 -> 7017.8077
B39: ='Input Sheet'!B21 -> VANGUARD TOTAL INTERNATIONAL STOCK INDEX FUND | C39: ='Input Sheet'!C21 -> 5.2268865 | D39: ='Input Sheet'!D21 -> 0.0141 | E39: ='Input Sheet'!E21 -> 6031.827
B41: Managerial Remuneration | C41: Designation | E41: % Change | F41: X of Median Salary | I41: Capital Structure
B43: Nandan M. Nilekani | C43: Chairman | E43: - | F43: - | I43: Share Price | K43: ='Data Sheet >'!B8 -> 1013.85
B44: Salil Parekh | C44: CEO & MD | E44: 22 | F44: 752:1 | I44: Number of Shares o/s | K44: ='Data Sheet >'!B6 -> 406.22571
B45: Jayesh Sanghrajka | C45: CFO | E45: - | F45: 85:1 | I45: Market Capitalization | K45: =K43*K44 -> 411851.94
B46: A.G.S. Manikantha | C46: Company Secretary | E46: -4 | F46: 13:1 | I46: Less: Cash & Equivalents | K46: =-'Data Sheet >'!K69 -> -22201
I47: Add: Total Debt | K47: ='Data Sheet >'!K59 -> 9176
I48: Add: Minority Interest | K48: 466
I49: Enterprise Value | K49: =SUM(K45:K48) -> 399292.94
B51: Investment Outlook & Valuation

Sheet Input Sheet
B3: Assumption Drivers | C3: With over four decades of experience in managing the systems and workings of global enterprises, we expertly steer clients, in 59 countries, as they navigate their digital transformation powered by cloud and AI. We enable them with an AI-first core, empower the business with agile digital at scale and drive continuous improvement with always-on learning through the transfer of digital skills, expertise, and ideas from our innovation ecosystem. | M3: Date | N3: Adj Close | O3: Volume
M4: Oct 22, 2026 | N4: 13.12 | O4: 22668585
M5: Oct 21, 2026 | N5: 12.75 | O5: 22042900
M6: Oct 20, 2026 | N6: 12.66 | O6: 22799200
M7: Oct 19, 2026 | N7: 12.2 | O7: 20804200
M8: Oct 16, 2026 | N8: 12.24 | O8: 17932300
M9: Oct 15, 2026 | N9: 12.13 | O9: 29560200
C10: 100 | M10: Oct 14, 2026 | N10: 11.48 | O10: 14209400
B11: Shareholder's name | C11: No. of Share (in crs) | D11: Shareholding (%) | E11: Market Value (in crs) | M11: Oct 13, 2026 | N11: 11.4 | O11: 25564500
B12: LIFE INSURANCE CORPORATION OF INDIA - ULIF00220091 | C12: 43.859487 | D12: 0.118 | E12: =1154*C12 -> 50613.848 | M12: Oct 12, 2026 | N12: 10.83 | O12: 13025600
B13: SBI MUTUAL FUND | C13: 16.748512 | D13: 0.0451 | E13: =1154*C13 -> 19327.783 | M13: Oct 09, 2026 | N13: 10.73 | O13: 12902100
B14: ICICI PRUDENTIAL MUTUAL FUND | C14: 14.669216 | D14: 0.0395 | E14: =1154*C14 -> 16928.275 | M14: Oct 08, 2026 | N14: 10.7 | O14: 31359300
B15: National Pension System Trust | C15: 12.570505 | D15: 0.0338 | E15: =1154*C15 -> 14506.362 | M15: Oct 07, 2026 | N15: 10.55 | O15: 28397400
B16: NIPPON LIFE INDIA TRUSTEE | C16: 9.8562135 | D16: 0.0265 | E16: =1154*C16 -> 11374.07 | M16: Oct 06, 2026 | N16: 10.55 | O16: 20107800
B17: SUDHA GOPALAKRISHNAN | C17: 9.5357 | D17: 0.0257 | E17: =1154*C17 -> 11004.198 | M17: Oct 05, 2026 | N17: 10.76 | O17: 17223000
B18: UTI MUTUAL FUND | C18: 7.188733 | D18: 0.0193 | E18: =1154*C18 -> 8295.7979 | M18: Oct 02, 2026 | N18: 11.04 | O18: 19592500
B19: HDFC MUTUAL FUND | C19: 6.3538616 | D19: 0.0171 | E19: =1154*C19 -> 7332.3563 | M19: Oct 01, 2026 | N19: 11.35 | O19: 38330500
B20: ROHAN MURTY | C20: 6.0812892 | D20: 0.0164 | E20: =1154*C20 -> 7017.8077 | M20: Sep 30, 2026 | N20: 10.76 | O20: 20322700
B21: VANGUARD TOTAL INTERNATIONAL STOCK INDEX FUND | C21: 5.2268865 | D21: 0.0141 | E21: =1154*C21 -> 6031.827 | M21: Sep 29, 2026 | N21: 10.64 | O21: 14285700
M22: Sep 28, 2026 | N22: 10.52 | O22: 13014600
M23: Sep 25, 2026 | N23: 10.5 | O23: 17570900
B24: Promoters | C24: 0.139 | M24: Sep 24, 2026 | N24: 10.5 | O24: 14511200
B25: FIIs | C25: 0.2744 | M25: Sep 23, 2026 | N25: 10.75 | O25: 17357500
B26: DIIs | C26: 0.4266 | M26: Sep 22, 2026 | N26: 10.76 | O26: 17671200
B27: Public | C27: 0.1559 | M27: Sep 21, 2026 | N27: 10.89 | O27: 9680900
B28: Government | C28: 0.0021 | M28: Sep 18, 2026 | N28: 10.82 | O28: 17157100
M29: Sep 17, 2026 | N29: 11.07 | O29: 9199200
M30: Sep 16, 2026 | N30: 11.08 | O30: 11497600
M31: Sep 15, 2026 | N31: 11.32 | O31: 17333900
M32: Sep 14, 2026 | N32: 11.6 | O32: 24835300
M33: Sep 11, 2026 | N33: 11.07 | O33: 16797600
M34: Sep 10, 2026 | N34: 10.91 | O34: 14030500
M35: Sep 09, 2026 | N35: 10.93 | O35: 17975200
M36: Sep 08, 2026 | N36: 11.13 | O36: 20180800
M37: Sep 04, 2026 | N37: 11.7 | O37: 19837900
M38: Sep 03, 2026 | N38: 12.09 | O38: 11957100
M39: Sep 02, 2026 | N39: 11.97 | O39: 11007700
M40: Sep 01, 2026 | N40: 12 | O40: 16393700
... M1257: Oct 25, 2021 | N1257: 19.96 | O1257: 10860000

Sheet Dupont Analysis
B3: ='Data Sheet >'!A1 -> INFOSYS LTD
B4: =CONCATENATE(" ","(",VLOOKUP(B3,'List of Stocks'!B2:E5442,3,1)," | ","BSE Code: ",VLOOKUP(B3,'List of Stocks'!B2:E5442,2,1),")") -> (INFY | BSE Code: 500209)
B5: =CONCATENATE(" ","INR "&'Data Sheet >'!B8) -> INR 1013.85
B6: 52 Week (High - INR 1728.00 & Low - 980.40)
B8: About the Company
B9: Infosys Limited is an Indian multinational IT services and consulting company founded in 1981. Its headquarters is located in Bengaluru, Karnataka, India. The company provides services such as software development, IT consulting, cloud computing, artificial intelligence, data analytics, and digital transformation. Infosys serves clients across various industries, including banking, financial services, insurance, retail, manufacturing, and healthcare. It operates in numerous countries and generates revenue by providing technology solutions and business services to organisations worldwide. Infosys is listed on the National Stock Exchange (NSE) and Bombay Stock Exchange (BSE) in India, as well as the New York Stock Exchange (NYSE) in the United States. It is recognised as one of India's leading IT companies and plays a significant role in the global technology industry.
B18: Financial Summary
B76: Return on Equity (ROE)
D77: ='Data Sheet >'!G16 -> 44651 | E77: ='Data Sheet >'!H16 -> 45016 | F77: ='Data Sheet >'!I16 -> 45382 | G77: ='Data Sheet >'!J16 -> 45747 | H77: ='Data Sheet >'!K16 -> 46112
B78: Net Profit | D78: ='Data Sheet >'!G30 -> 22110 | E78: ='Data Sheet >'!H30 -> 24095 | F78: ='Data Sheet >'!I30 -> 26233 | G78: ='Data Sheet >'!J30 -> 26713 | H78: ='Data Sheet >'!K30 -> 29440
B79: Average Shareholder Equity | D79: =(('Data Sheet >'!G57+'Data Sheet >'!G58)+('Data Sheet >'!F57+'Data Sheet >'!F58))/2 -> 75850.5 | E79: =(('Data Sheet >'!H57+'Data Sheet >'!H58)+('Data Sheet >'!G57+'Data Sheet >'!G58))/2 -> 75378.5 | F79: =(('Data Sheet >'!I57+'Data Sheet >'!I58)+('Data Sheet >'!H57+'Data Sheet >'!H58))/2 -> 81761.5 | G79: =(('Data Sheet >'!J57+'Data Sheet >'!J58)+('Data Sheet >'!I57+'Data Sheet >'!I58))/2 -> 91967 | H79: =(('Data Sheet >'!K57+'Data Sheet >'!K58)+('Data Sheet >'!J57+'Data Sheet >'!J58))/2 -> 94335
B80: Return on Equity (ROE) | D80: =D78/D79 -> 0.29149445 | E80: =E78/E79 -> 0.31965348 | F80: =F78/F79 -> 0.32084783 | G80: =G78/G79 -> 0.29046288 | H80: =H78/H79 -> 0.31207929
B82: ROE - Dupont Equation
D83: =D77 -> 44651 | E83: =E77 -> 45016 | F83: =F77 -> 45382 | G83: =G77 -> 45747 | H83: =H77 -> 46112
B84: =B78 -> Net Profit | D84: =D78 -> 22110 | E84: =E78 -> 24095 | F84: =F78 -> 26233 | G84: =G78 -> 26713 | H84: =H78 -> 29440
B85: Revenue | D85: ='Data Sheet >'!G17 -> 121641 | E85: ='Data Sheet >'!H17 -> 146767 | F85: ='Data Sheet >'!I17 -> 153670 | G85: ='Data Sheet >'!J17 -> 162990 | H85: ='Data Sheet >'!K17 -> 178650
B86: Net Profit Margin (A) | D86: =D84/D85 -> 0.18176437 | E86: =E84/E85 -> 0.16417178 | F86: =F84/F85 -> 0.17070996 | G86: =G84/G85 -> 0.16389349 | H86: =H84/H85 -> 0.16479149
B88: Revenue | D88: =D85 -> 121641 | E88: =E85 -> 146767 | F88: =F85 -> 153670 | G88: =G85 -> 162990 | H88: =H85 -> 178650
B89: Average Total Assets | D89: =('Data Sheet >'!G66+'Data Sheet >'!F66)/2 -> 112120 | E89: =('Data Sheet >'!H66+'Data Sheet >'!G66)/2 -> 120662.5 | F89: =('Data Sheet >'!I66+'Data Sheet >'!H66)/2 -> 130308 | G89: =('Data Sheet >'!J66+'Data Sheet >'!I66)/2 -> 141907.5 | H89: =('Data Sheet >'!K66+'Data Sheet >'!J66)/2 -> 151041.5
B90: Assets Turnover Ratio (B) | D90: =D88/D89 -> 1.0849179 | E90: =E88/E89 -> 1.2163431 | F90: =F88/F89 -> 1.1792829 | G90: =G88/G89 -> 1.1485651 | H90: =H88/H89 -> 1.1827875
B92: =B89 -> Average Total Assets | D92: =D89 -> 112120 | E92: =E89 -> 120662.5 | F92: =F89 -> 130308 | G92: =G89 -> 141907.5 | H92: =H89 -> 151041.5
B93: =B79 -> Average Shareholder Equity | D93: =D79 -> 75850.5 | E93: =E79 -> 75378.5 | F93: =F79 -> 81761.5 | G93: =G79 -> 91967 | H93: =H79 -> 94335
B94: Equity Multiplier (C) | D94: =D92/D93 -> 1.4781709 | E94: =E92/E93 -> 1.6007549 | F94: =F92/F93 -> 1.5937575 | G94: =G92/G93 -> 1.5430263 | H94: =H92/H93 -> 1.6011184
B96: Return on Equity (A*B*C) | D96: =D94*D90*D86 -> 0.29149445 | E96: =E94*E90*E86 -> 0.31965348 | F96: =F94*F90*F86 -> 0.32084783 | G96: =G94*G90*G86 -> 0.29046288 | H96: =H94*H90*H86 -> 0.31207929
B98: Return on Equity Assets
D99: =D77 -> 44651 | E99: =E77 -> 45016 | F99: =F77 -> 45382 | G99: =G77 -> 45747 | H99: =H77 -> 46112
B100: Net Profit | D100: =D78 -> 22110 | E100: =E78 -> 24095 | F100: =F78 -> 26233 | G100: =G78 -> 26713 | H100: =H78 -> 29440
B101: =B92 -> Average Total Assets | D101: =D89 -> 112120 | E101: =E89 -> 120662.5 | F101: =F89 -> 130308 | G101: =G89 -> 141907.5 | H101: =H89 -> 151041.5
B102: Return on Assets (ROA) | D102: =D100/D101 -> 0.19719943 | E102: =E100/E101 -> 0.19968922 | F102: =F100/F101 -> 0.20131535 | G102: =G100/G101 -> 0.18824234 | H102: =H100/H101 -> 0.19491332
B104: ROA - Dupont Equation
D105: =D99 -> 44651 | E105: =E99 -> 45016 | F105: =F99 -> 45382 | G105: =G99 -> 45747 | H105: =H99 -> 46112
B106: =B100 -> Net Profit | D106: =D100 -> 22110 | E106: =E100 -> 24095 | F106: =F100 -> 26233 | G106: =G100 -> 26713 | H106: =H100 -> 29440
B107: Revenue | D107: =D85 -> 121641 | E107: =E85 -> 146767 | F107: =F85 -> 153670 | G107: =G85 -> 162990 | H107: =H85 -> 178650
B108: Net Profit Margin (A) | D108: =D106/D107 -> 0.18176437 | E108: =E106/E107 -> 0.16417178 | F108: =F106/F107 -> 0.17070996 | G108: =G106/G107 -> 0.16389349 | H108: =H106/H107 -> 0.16479149
B110: Revenue | D110: =D107 -> 121641 | E110: =E107 -> 146767 | F110: =F107 -> 153670 | G110: =G107 -> 162990 | H110: =H107 -> 178650
B111: Average Total Assets | D111: =D101 -> 112120 | E111: =E101 -> 120662.5 | F111: =F101 -> 130308 | G111: =G101 -> 141907.5 | H111: =H101 -> 151041.5
B112: Assets Turnover Ratio (B) | D112: =D110/D111 -> 1.0849179 | E112: =E110/E111 -> 1.2163431 | F112: =F110/F111 -> 1.1792829 | G112: =G110/G111 -> 1.1485651 | H112: =H110/H111 -> 1.1827875
B114: Return on Assets (A*B) | D114: =D112*D108 -> 0.19719943 | E114: =E112*E108 -> 0.19968922 | F114: =F112*F108 -> 0.20131535 | G114: =G112*G108 -> 0.18824234 | H114: =H112*H108 -> 0.19491332

Sheet List of Stocks
B2: COMPANY_NAME | C2: BSE | D2: NSE | E2: Industry
B3: 20 MICRONS LTD | C3: 533022 | D3: 20MICRONS | E3: Mining
B4: 21ST CENTURY MANAGEMENT SERVICES LTD | C4: 526921 | D4: 21STCENMGM | E4: Other Financial Services
B5: 3I INFOTECH LTD | C5: 532628 | D5: 3IINFOTECH | E5: IT Consulting & Software
B6: 3M (INDIA) LTD | C6: 523395 | D6: 3M(INDIA) | E6: Diversified
B7: 3M INDIA LTD | C7: 523395 | D7: 3MINDIA | E7: Diversified
B8: 3P LAND HOLDINGS LTD | C8: 516092 | D8: 3PLAND | E8: Paper & Paper Products
B9: 5PAISA CAPITAL LTD | C9: 540776 | D9: 5PAISA | E9: Other Financial Services
B10: 63 MOONS TECHNOLOGIES LTD | C10: 526881 | D10: 63MOONS | E10: IT Consulting & Software
B11: 7NR RETAIL LTD | C11: 540615 | D11: Not Listed | E11: Specialty Retail
B12: 7SEAS ENTERTAINMENT LTD | C12: 540874 | D12: Not Listed | E12: Movies & Entertainment
B13: 8K MILES SOFTWARE SERVICES LTD | C13: 512161 | D13: 8KMILES | E13: Internet Software & Services
B14: A & M FEBCON LTD | C14: 540697 | D14: Not Listed | E14: Industrial Machinery
B15: A AND M JUMBO BAGS LTD | C15: Not Listed | D15: AMJUMBO | E15: SME
B16: A INFRASTRUCTURE LTD | C16: 539620 | D16: Not Listed | E16: Cement & Cement Products
B17: A K SPINTEX LTD | C17: 539300 | D17: Not Listed | E17: Textiles
B18: A K CAPITAL SERVICES LTD | C18: 530499 | D18: Not Listed | E18: Finance (including NBFCs)
B19: A.F. Enterprises Ltd | C19: 538351 | D19: AFEL | E19: Investment Companies
B20: A-1 ACID LTD | C20: 542012 | D20: Not Listed | E20: Comm.Trading & Distribution
B21: A2Z INFRA ENGINEERING LTD | C21: 533292 | D21: A2ZINFRA | E21: Utilities:Non-Elec.
B22: AADHAAR VENTURES (INDIA) LTD | C22: 531611 | D22: Not Listed | E22: Finance (including NBFCs)
B23: AADHAAR VENTURES INDIA LTD | C23: 531611 | D23: Not Listed | E23: Finance (including NBFCs)
B24: AAKASH EXPLORATION SERVICES LTD | C24: Not Listed | D24: AAKASH | E24: SME
B25: AANANDA LAKSHMI SPINNING MILLS LTD | C25: 539096 | D25: Not Listed | E25: Textiles
B26: AANCHAL ISPAT LTD | C26: 538812 | D26: Not Listed | E26: Iron & Steel/Interm.Products
B27: AAR COMMERCIAL COMPANY LTD | C27: 539632 | D27: Not Listed | E27: Distributors
B28: Aar Shyam India Investment Company Ltd | C28: 542377 | D28: AARSHYAM | E28: Finance (including NBFCs)
B29: AAREY DRUGS & PHARMACEUTICALS LTD | C29: 524412 | D29: Not Listed | E29: Pharmaceuticals
B30: AARON INDUSTRIES LTD | C30: Not Listed | D30: AARON | E30: SME
B31: Aartech Solonics Ltd | C31: 542580 | D31: AARTECH | E31: Heavy Electrical Equipment
B32: AARTI DRUGS LTD | C32: 524348 | D32: AARTIDRUGS | E32: Pharmaceuticals
B33: AARTI INDUSTRIES LTD | C33: 524208 | D33: AARTIIND | E33: Commodity Chemicals
B34: AARV INFRATEL LTD | C34: 526488 | D34: Not Listed | E34: Textiles
B35: AARVEE DENIMS & EXPORTS LTD | C35: 514274 | D35: AARVEEDEN | E35: Textiles
B36: AARVI ENCON LTD | C36: Not Listed | D36: AARVI | E36: SME
B37: AASHEE INFOTECH LTD | C37: 519319 | D37: Not Listed | E37: Internet Software & Services
B38: AASWA TRADING & EXPORTS LTD | C38: 512038 | D38: Not Listed | E38: Comm.Trading & Distribution
B39: AAVAS FINANCIERS LTD | C39: 541988 | D39: AAVAS | E39: Housing Finance
B40: AAYUSH FOOD AND HERBS LTD | C40: 539528 | D40: Not Listed | E40: Packaged Foods
B41: ABAN OFFSHORE LTD | C41: 523204 | D41: ABAN | E41: Exploration & Production
B42: ABANS ENTERPRISES LTD | C42: 512165 | D42: Not Listed | E42: Comm.Trading & Distribution
B43: ABB INDIA LTD | C43: 500002 | D43: ABB | E43: Heavy Electrical Equipment
B44: ABBOTT (INDIA) LTD | C44: 500488 | D44: ABBOT(INDIA) | E44: Pharmaceuticals
B45: ABBOTT INDIA LTD | C45: 500488 | D45: ABBOTINDIA | E45: Pharmaceuticals
B46: ABC (INDIA) LTD | C46: 520123 | D46: Not Listed | E46: Surface Transportation
B47: ABC GAS INTERNATIONAL LTD | C47: 513119 | D47: Not Listed | E47: Copper
B48: ABC INDIA LTD | C48: 520123 | D48: Not Listed | E48: Surface Transportation
... B56: ABIRAMI FINANCIAL SERVICES INDIA LTD | C56: 511756 | D56: Not Listed | E56: Finance (including NBFCs)
B57: ABM INTERNATIONAL LTD | C57: Not Listed | D57: ABMINTLTD | E57: Others
B58: ABM KNOWLEDGEWARE LTD | C58: 531161 | D58: Not Listed | E58: IT Software Products
B59: ACC LTD | C59: 500410 | D59: ACC | E59: Cement & Cement Products
B60: ACCEL LTD | C60: 517494 | D60: Not Listed | E60: Storage Media & Peripherals
B61: ACCELYA KALE SOLUTIONS LTD | C61: 532268 | D61: ACCELYA | E61: IT Consulting & Software
B62: ACCORD SYNERGY LTD | C62: Not Listed | D62: ACCORD | E62: SME
B63: ACCURACY SHIPPING LTD | C63: Not Listed | D63: ACCURACY | E63: SME
B64: ACE EDUTREND LTD | C64: 530093 | D64: Not Listed | E64: Education
B65: ACE INTEGRATED SOLUTIONS LTD | C65: Not Listed | D65: ACEINTEG | E65: SME
B66: ACE MEN ENGG WORKS LTD | C66: 539661 | D66: Not Listed | E66: Distributors
B67: ACE SOFTWARE EXPORTS LTD | C67: 531525 | D67: Not Listed | E67: IT Software Products
B68: Achal Investments Ltd | C68: 538570 | D68: ACHAL | E68: Other Financial Services
B69: ACI INFOCOM LTD | C69: 517356 | D69: Not Listed | E69: Storage Media & Peripherals
B70: ACKNIT INDUSTRIES LTD | C70: 530043 | D70: Not Listed | E70: Other Apparels & Accessories
B71: ACME RESOURCES LTD | C71: 539391 | D71: Not Listed | E71: Finance (including NBFCs)
B72: ACROW INDIA LTD. | C72: 513149 | D72: ACROW | E72: Iron &amp; Steel Products
B73: ACRYSIL LTD | C73: 524091 | D73: Not Listed | E73: Plastic Products
B74: ACTION CONSTRUCTION EQUIPMENT LTD | C74: 532762 | D74: ACE | E74: Transport Related Services
B75: ACTION FINANCIAL SERVICES (INDIA) LTD | C75: 511706 | D75: Not Listed | E75: Other Financial Services
B76: ACTION FINANCIAL SERVICES INDIA LTD | C76: 511706 | D76: Not Listed | E76: Other Financial Services
B77: ACTIVE CLOTHING CO LTD | C77: 541144 | D77: Not Listed | E77: Other Apparels & Accessories
... B135: AGRI-TECH INDIA LTD | C135: 537292 | D135: AGRITECH | E135: Other Agricultural Products
B136: AGRO PHOS (INDIA) LTD | C136: Not Listed | D136: AGROPHOS | E136: SME
B137: AGRO PHOS INDIA LTD | C137: Not Listed | D137: AGROPHOS | E137: SME
B138: AGRO TECH FOODS LTD | C138: 500215 | D138: ATFL | E138: Other Agricultural Products
B139: AHIMSA INDUSTRIES LTD | C139: Not Listed | D139: AHIMSA | E139: SME
B140: AHLADA ENGINEERS LTD | C140: Not Listed | D140: AHLADA | E140: SME
B141: AHLUWALIA CONTRACTS (INDIA) LTD | C141: 532811 | D141: AHLUCONT | E141: Realty
B142: AHLUWALIA CONTRACTS INDIA LTD | C142: 532811 | D142: AHLUCONT | E142: Realty
B143: AHMEDABAD STEELCRAFT LTD | C143: 522273 | D143: Not Listed | E143: Iron & Steel/Interm.Products
B144: AI CHAMPDANY INDUSTRIES LTD | C144: 532806 | D144: Not Listed | E144: Jute & Jute Products
B145: AIA ENGINEERING LTD | C145: 532683 | D145: AIAENG | E145: Other Industrial Goods
B146: AIMCO PESTICIDES LTD | C146: 524288 | D146: Not Listed | E146: Agrochemicals
B147: AIRAN LTD | C147: Not Listed | D147: AIRAN | E147: SME
B148: AIRO LAM LTD | C148: Not Listed | D148: AIROLAM | E148: SME
B149: AISHWARYA TELECOM LTD | C149: 532975 | D149: Not Listed | E149: Telecom Equipment
B150: AJANTA PHARMA LTD | C150: 532331 | D150: AJANTPHARM | E150: Pharmaceuticals
B151: AJANTA SOYA LTD | C151: 519216 | D151: Not Listed | E151: Edible Oils
B152: AJCON GLOBAL SERVICES LTD | C152: 511692 | D152: Not Listed | E152: Other Financial Services
B153: AJEL LTD | C153: 530713 | D153: Not Listed | E153: IT Consulting & Software
B154: AJMERA REALTY & INFRA (INDIA) LTD | C154: 513349 | D154: AJMERA | E154: Realty
B155: AJMERA REALTY & INFRA INDIA LTD | C155: 513349 | D155: AJMERA | E155: Realty
B156: AJOONI BIOTECH LTD | C156: Not Listed | D156: AJOONI | E156: SME
B157: AJWA FUN WORLD & RESORT LTD | C157: 526628 | D157: Not Listed | E157: Other Leisure Facilities
B158: AKAR AUTO INDUSTRIES LTD | C158: 530621 | D158: Not Listed | E158: Industrial Machinery
B159: AKASH INFRA PROJECTS LTD | C159: Not Listed | D159: AKASH | E159: SME
B160: AKASHDEEP METAL INDUSTRIES LTD | C160: 538778 | D160: Not Listed | E160: Finance (including NBFCs)
B161: AKG EXIM LTD | C161: Not Listed | D161: AKG | E161: SME
B162: AKI (INDIA) LTD | C162: 542020 | D162: Not Listed | E162: Other Apparels & Accessories
B163: AKI INDIA LTD | C163: 542020 | D163: Not Listed | E163: Other Apparels & Accessories
B164: AKM LACE AND EMBROTEX LTD | C164: 540718 | D164: Not Listed | E164: Textiles
B165: AKME STAR HOUSING FINANCE LTD | C165: 539017 | D165: Not Listed | E165: Housing Finance
...

Sheet Football Field
B2: Football Field Analysis - Data
C4: OpenLow | D4: Low | E4: OpenHigh | F4: High
B5: Comps | C5: =D5 -> 967.52777 | D5: ='Comparable Company Valuation'!N28 -> 967.52777 | E5: =F5 -> 1129.0637 | F5: ='Comparable Company Valuation'!P28 -> 1129.0637
B6: DCF Bear | C6: =D6 -> 899.4567 | D6: =DCF!G46 -> 899.4567 | E6: =F6 -> 1293.4127 | F6: =DCF!G50 -> 1293.4127
B7: DCF Base | C7: =D7 -> 988.72502 | D7: =DCF!E46 -> 988.72502 | E7: =F7 -> 1724.5585 | F7: =DCF!E50 -> 1724.5585
B8: DCF Bull | C8: =D8 -> 1142.1556 | D8: =DCF!C46 -> 1142.1556 | E8: =F8 -> 4362.7092 | F8: =DCF!C50 -> 4362.7092
B9: 52 W H/L | C9: =D9 -> 980.4 | D9: 980.4 | E9: =F9 -> 1728 | F9: 1728

Sheet Comparable Company Valuation
B2: Comparable Company Valuation
C4: Market Data | J4: Financials | N4: Valuation
B5: Company | C5: Share Price | D5: Shares Outstanding | E5: Equity Value | F5: Net Debt | G5: Enterprise Value | J5: Revenue | K5: EBITDA | L5: Net Income | N5: EV/Revenue | O5: EV/EBITDA | P5: P/E
B7: Infosys | C7: 1023.4 | D7: ='Income Statement '!H38 -> 405.56 | E7: =C7*D7 -> 415050.1 | F7: ='Balance Sheet'!G7 -> 9176 | G7: 402416.02 | J7: ='Income Statement '!F5 -> 162990 | K7: ='Income Statement '!G17 -> 42280 | L7: ='Income Statement '!G35 -> 26441 | N7: =G7/J7 -> 2.4689614 | O7: =G7/K7 -> 9.5178813 | P7: =E7/L7 -> 15.697217
B8: TCS | C8: 2156 | D8: 363.81 | E8: =C8*D8 -> 784374.36 | F8: 11808 | G8: 777809.67 | J8: 283248 | K8: 18815 | L8: 51858 | N8: =G8/J8 -> 2.7460376 | O8: =G8/K8 -> 41.339871 | P8: =E8/L8 -> 15.125426
B9: HCL Technologies | C9: 1216.7 | D9: 271.37 | E9: =C9*D9 -> 330175.88 | F9: 5215 | G9: 311961.63 | J9: 134374 | K9: 26752 | L9: 17434 | N9: =G9/J9 -> 2.3215922 | O9: =G9/K9 -> 11.661245 | P9: =E9/L9 -> 18.938619
B10: Wipro | C10: 162.57 | D10: 990.53 | E10: =C10*D10 -> 161030.46 | F10: 20291 | G10: 170766.66 | J10: 94968 | K10: 5612.2 | L10: 13285.3 | N10: =G10/J10 -> 1.7981495 | O10: =G10/K10 -> 30.427757 | P10: =E10/L10 -> 12.12095
B11: Tech Mahindra | C11: 1514.1 | D11: 88.63 | E11: =C11*D11 -> 134194.68 | F11: 2186 | G11: 145486.69 | J11: 59176.1 | K11: 2636.1 | L11: 5163 | N11: =G11/J11 -> 2.458538 | O11: =G11/K11 -> 55.190126 | P11: =E11/L11 -> 25.99161
B12: LTM | C12: 4070 | D12: 29.65 | E12: =C12*D12 -> 120675.5 | F12: 2310 | G12: 120222.48 | J12: 44075 | K12: 8649.6 | L12: 5196.7 | N12: =G12/J12 -> 2.7276796 | O12: =G12/K12 -> 13.899195 | P12: =E12/L12 -> 23.221564
B14: High | N14: =MAX(N7:N12) -> 2.7460376 | O14: =MAX(O7:O12) -> 55.190126 | P14: =MAX(P7:P12) -> 25.99161
B15: 75th Percentile | N15: =_xlfn.QUARTILE.EXC(N7:N12,3) -> 2.7322691 | O15: =_xlfn.QUARTILE.EXC(O7:O12,3) -> 44.802435 | P15: =_xlfn.QUARTILE.EXC(P7:P12,3) -> 23.914075
B16: Average | N16: =AVERAGE(N7:N12) -> 2.4201597 | O16: =AVERAGE(O7:O12) -> 27.006013 | P16: =AVERAGE(P7:P12) -> 18.515898
B17: Median | N17: =MEDIAN(N7:N12) -> 2.4637497 | O17: =MEDIAN(O7:O12) -> 22.163476 | P17: =MEDIAN(P7:P12) -> 17.317918
B18: 25th Percentile | N18: =_xlfn.QUARTILE.EXC(N7:N12,1) -> 2.1907315 | O18: =_xlfn.QUARTILE.EXC(O7:O12,1) -> 11.125404 | P18: =_xlfn.QUARTILE.EXC(P7:P12,1) -> 14.374307
B19: Low | N19: =MIN(N7:N12) -> 1.7981495 | O19: =MIN(O7:O12) -> 9.5178813 | P19: =MIN(P7:P12) -> 12.12095
B21: Infosys Comparable Valuation | N21: EV/Revenue | O21: EV/EBITDA | P21: P/E
B23: Implied Enterprise Value | N23: =J7*N17 -> 401566.56 | O23: =K7*O17 -> 937071.78 | P23: =P24+P25 -> 467079.06
B24: Net Debt | N24: =F7 -> 9176 | O24: =N24 -> 9176 | P24: =O24 -> 9176
B25: Implied Market Value | N25: =N23-N24 -> 392390.56 | O25: =O23-O24 -> 927895.78 | P25: =L7*P17 -> 457903.06
B26: Shares Outstanding | N26: =D7 -> 405.56 | O26: =N26 -> 405.56 | P26: =O26 -> 405.56
B28: Implied Value per Share | N28: =N25/N26 -> 967.52777 | O28: =O25/O26 -> 2287.9371 | P28: =P25/P26 -> 1129.0637

Sheet DCF
B2: Discounted Cash Flow
B3: Period | C3: ='Income Statement '!H3 -> 46477 | D3: ='Income Statement '!I3 -> 46842 | E3: ='Income Statement '!J3 -> 47207 | F3: ='Income Statement '!K3 -> 47572 | G3: ='Income Statement '!L3 -> 47937
B5: Free Cash Flows
B7: EBIT | C7: ='Income Statement '!H23 -> 41621.863 | D7: ='Income Statement '!I23 -> 45620.872 | E7: ='Income Statement '!J23 -> 50004.103 | F7: ='Income Statement '!K23 -> 54808.473 | G7: ='Income Statement '!L23 -> 60074.444
B8: Tax | C8: =-'Income Statement '!H23*'Income Statement '!H33 -> -12507.848 | D8: =-'Income Statement '!I23*'Income Statement '!I33 -> -13709.596 | E8: =-'Income Statement '!J23*'Income Statement '!J33 -> -15026.807 | F8: =-'Income Statement '!K23*'Income Statement '!K33 -> -16470.575 | G8: =-'Income Statement '!L23*'Income Statement '!L33 -> -18053.06
B9: D&A | C9: ='Income Statement '!H20 -> 5669.5097 | D9: ='Income Statement '!I20 -> 6214.2334 | E9: ='Income Statement '!J20 -> 6811.2939 | F9: ='Income Statement '!K20 -> 7465.7197 | G9: ='Income Statement '!L20 -> 8183.0225
B10: CapEx | C10: =-'Dep Capex'!H10 -> -13525.907 | D10: =-'Dep Capex'!I10 -> -12566.12 | E10: =-'Dep Capex'!J10 -> -11674.44 | F10: =-'Dep Capex'!K10 -> -10846.032 | G10: =-'Dep Capex'!L10 -> -10076.408
B11: Non-cash Work. Capital (inc) / dec | C11: =-(('Balance Sheet'!H18-'Balance Sheet'!H17-'Balance Sheet'!H8)-('Balance Sheet'!G18-'Balance Sheet'!G17-'Balance Sheet'!G8)) -> 494.28165 | D11: =-(('Balance Sheet'!I18-'Balance Sheet'!I17-'Balance Sheet'!I8)-('Balance Sheet'!H18-'Balance Sheet'!H17-'Balance Sheet'!H8)) -> 1683.3401 | E11: =-(('Balance Sheet'!J18-'Balance Sheet'!J17-'Balance Sheet'!J8)-('Balance Sheet'!I18-'Balance Sheet'!I17-'Balance Sheet'!I8)) -> 1845.0747 | F11: =-(('Balance Sheet'!K18-'Balance Sheet'!K17-'Balance Sheet'!K8)-('Balance Sheet'!J18-'Balance Sheet'!J17-'Balance Sheet'!J8)) -> 2022.3485 | G11: =-(('Balance Sheet'!L18-'Balance Sheet'!L17-'Balance Sheet'!L8)-('Balance Sheet'!K18-'Balance Sheet'!K17-'Balance Sheet'!K8)) -> 2216.6548
B12: FCF | C12: =SUM(C7:C11) -> 21751.901 | D12: =SUM(D7:D11) -> 27242.729 | E12: =SUM(E7:E11) -> 31959.225 | F12: =SUM(F7:F11) -> 36979.934 | G12: =SUM(G7:G11) -> 42344.654
B14: WACC
B16: WACC | C16: =WACC!C21 -> 0.13260882
B18: Terminal Value
B20: Growth rate | G20: 0.04
B21: EBITDA | G21: ='Income Statement '!L17 -> 68257.467
B22: EV/EBITDA Multiple | G22: 8.41
B23: Perpertuity Growth TV | G23: =G12*(1+G20)/(C16-G20) -> 475531.83
B24: EV/ EBITDA TV | G24: =G21*G22 -> 574045.3
B25: Average | G25: =AVERAGE(G23:G24) -> 524788.56
B27: Mid Year Convention | C27: 0.5 | D27: =C27+1 -> 1.5 | E27: =D27+1 -> 2.5 | F27: =E27+1 -> 3.5 | G27: =F27+1 -> 4.5
B29: Discounting Factor | C29: =1/(1+$C$16)^C27 -> 0.93963683 | D29: =1/(1+$C$16)^D27 -> 0.82962168 | E29: =1/(1+$C$16)^E27 -> 0.73248739 | F29: =1/(1+$C$16)^F27 -> 0.64672584 | G29: =1/(1+$C$16)^G27 -> 0.57100548
B30: PV of FCF | C30: =C12*C29 -> 20438.887 | D30: =D12*D29 -> 22601.159 | E30: =E12*E29 -> 23409.729 | F30: =F12*F29 -> 23915.879 | G30: =G12*G29 -> 24179.03
B31: PV of TV | G31: =G25*G29 -> 299657.15
B32: Enterprise Value | C32: =SUM(C30:G31) -> 414201.83
B34: Enterprise Value to Equity Value
B36: Cash | C36: ='Balance Sheet'!G17 -> 22201
B37: Marketable Securities | C37: 0
B38: Debt | C38: ='Balance Sheet'!G7 -> 9176
B39: Equity Value | C39: =C32+C36+C37-C38 -> 427226.83
B41: Shares Outstanding | C41: ='Income Statement '!G38 -> 405.56
B42: Implied Share Price | C42: =C39/C41 -> 1053.4245
B44: Sensitivity Analysis
B45: =C42 -> 1053.4245 | C45: 0.11 | D45: 0.12 | E45: 0.1326 | F45: 0.14 | G45: 0.15
B46: 0.02 | C46: 1142.1556 | D46: 1067.6111 | E46: 988.72502 | F46: 948.3945 | G46: 899.4567
B47: 0.04 | C47: 1257.1753 | D47: 1155.39 | E47: 1053.4879 | F47: 1003.3986 | G47: 944.22443
B48: 0.06 | C48: 1464.2109 | D48: 1301.6883 | E48: 1153.9328 | F48: 1085.9048 | G48: 1008.8889
B49: 0.08 | C49: 1947.294 | D49: 1594.2848 | E49: 1330.7617 | F49: 1223.4151 | G49: 1110.5045
B50: 0.1 | C50: 4362.7092 | D50: 2472.0744 | E50: 1724.5585 | F50: 1498.4357 | G50: 1293.4127

Sheet WACC
B2: Weighted Average Cost of Capital
B4: Name of the Comp | C4: Total Debt | D4: Total Equity | E4: Tax Rate | F4: Risk Free Rate | G4: Beta | H4: Market Return
B6: Infosys | C6: ='Balance Sheet'!H7 -> 9176 | D6: =SUM('Balance Sheet'!H5:H6) -> 102284.51 | E6: ='Income Statement '!G33 -> 0.28464369 | F6: 0.0648 | G6: ='Beta - Regression'!K12 -> 0.77032835 | H6: =RM!F7 -> 0.16449231
B10: Cost of Debt | E10: Cost of Equity
B12: Pre-Tax Cost of Debt | C12: ='Income Statement '!G26/'Balance Sheet'!G7 -> 0.045335658 | E12: Risk Free Rate | H12: =F6 -> 0.0648
B13: Tax Rate | C13: =E6 -> 0.28464369 | E13: Equity Risk Premium | H13: =RM!F7 -> 0.16449231
B14: Post Tax Cost of Debt | C14: =C12*(1-C13) -> 0.032431149 | E14: Levered Beta | H14: =G6 -> 0.77032835
E15: Cost of Equity | H15: =H12+H14*(H13-H12) -> 0.14159581
B17: Weighted Average Cost of Capital
B19: E / D +E | C19: =D6/(D6+C6) -> 0.91767488
B20: D / D+E | C20: =C6/(D6+C6) -> 0.082325118
B21: WACC | C21: =(C19*H15)+(C20*C14) -> 0.13260882

Sheet Beta - Regression
B2: Beta - Regression
B4: Nifty Weekly Returns | F4: Infosys Weekly Returns | I4: Beta Drifting | M4: Beta | N4: =N23 -> 0.69377113
B6: Date | C6: Adj Close | D6: Returns | F6: Adj Close | G6: Returns | I6: Levered Raw Beta | K6: =N4 -> 0.69377113 | M6: SUMMARY OUTPUT
B7: Oct 07, 2024 | C7: 24964.25 | F7: 21.56 | I7: Raw Beta Weight | K7: 0.75
B8: Oct 14, 2024 | C8: 24854.05 | D8: =C8/C7-1 -> -0.0044143125 | F8: 21.16 | G8: =F8/F7-1 -> -0.018552876 | M8: Regression Statistics
B9: Oct 21, 2024 | C9: 24180.8 | D9: =C9/C8-1 -> -0.027088141 | F9: 20.58 | G9: =F9/F8-1 -> -0.027410208 | I9: Market Weight | K9: 1 | M9: Multiple R | N9: 0.28648156
B10: Oct 28, 2024 | C10: 24304.35 | D10: =C10/C9-1 -> 0.0051094257 | F10: 19.74 | G10: =F10/F9-1 -> -0.040816327 | I10: Market Beta Weight | K10: 0.25 | M10: R Square | N10: 0.082071683
B11: Nov 04, 2024 | C11: 24148.2 | D11: =C11/C10-1 -> -0.0064247758 | F11: 20.68 | G11: =F11/F10-1 -> 0.047619048 | M11: Adjusted R Square | N11: 0.073072386
B12: Nov 11, 2024 | C12: 23532.7 | D12: =C12/C11-1 -> -0.025488442 | F12: 20.47 | G12: =F12/F11-1 -> -0.010154739 | I12: Adjusted Beta | K12: =(K6*K7)+(K9*K10) -> 0.77032835 | M12: Standard Error | N12: 0.04219873
B13: Nov 18, 2024 | C13: 23907.25 | D13: =C13/C12-1 -> 0.015916151 | F13: 21.67 | G13: =F13/F12-1 -> 0.058622374 | M13: Observations | N13: 104
B14: Nov 25, 2024 | C14: 24131.1 | D14: =C14/C13-1 -> 0.0093632685 | F14: 20.99 | G14: =F14/F13-1 -> -0.031379788
B15: Dec 02, 2024 | C15: 24677.8 | D15: =C15/C14-1 -> 0.022655411 | F15: 21.74 | G15: =F15/F14-1 -> 0.035731301 | M15: ANOVA
B16: Dec 09, 2024 | C16: 24768.3 | D16: =C16/C15-1 -> 0.0036672637 | F16: 22.25 | G16: =F16/F15-1 -> 0.023459062 | N16: df | O16: SS | P16: MS | Q16: F | R16: Significance F
B17: Dec 16, 2024 | C17: 23587.5 | D17: =C17/C16-1 -> -0.047673841 | F17: 21.61 | G17: =F17/F16-1 -> -0.028764045 | M17: Regression | N17: 1 | O17: 0.016239906 | P17: 0.016239906 | Q17: 9.1197881 | R17: 0.003195286
B18: Dec 23, 2024 | C18: 23813.4 | D18: =C18/C17-1 -> 0.0095771065 | F18: 21.38 | G18: =F18/F17-1 -> -0.010643221 | M18: Residual | N18: 102 | O18: 0.18163475 | P18: 0.0017807328
B19: Dec 30, 2024 | C19: 24004.75 | D19: =C19/C18-1 -> 0.0080353918 | F19: 21.52 | G19: =F19/F18-1 -> 0.0065481759 | M19: Total | N19: 103 | O19: 0.19787465
B20: Jan 06, 2025 | C20: 23431.5 | D20: =C20/C19-1 -> -0.02388069 | F20: 21.59 | G20: =F20/F19-1 -> 0.0032527881
B21: Jan 13, 2025 | C21: 23203.2 | D21: =C21/C20-1 -> -0.0097432943 | F21: 20.15 | G21: =F21/F20-1 -> -0.066697545 | N21: Coefficients | O21: Standard Error | P21: t Stat | Q21: P-value | R21: Lower 95% | S21: Upper 95% | T21: Lower 95.0% | U21: Upper 95.0%
B22: Jan 20, 2025 | C22: 23092.2 | D22: =C22/C21-1 -> -0.0047838229 | F22: 20.62 | G22: =F22/F21-1 -> 0.023325062 | M22: Intercept | N22: -0.0050968877 | O22: 0.0041422965 | P22: -1.2304498 | Q22: 0.22135882 | R22: -0.013313113 | S22: 0.0031193376 | T22: -0.013313113 | U22: 0.0031193376
B23: Jan 27, 2025 | C23: 23482.15 | D23: =C23/C22-1 -> 0.016886654 | F23: 20.87 | G23: =F23/F22-1 -> 0.012124151 | M23: X Variable 1 | N23: 0.69377113 | O23: 0.22973325 | P23: 3.0198987 | Q23: 0.003195286 | R23: 0.23809632 | S23: 1.1494459 | T23: 0.23809632 | U23: 1.1494459
B24: Feb 03, 2025 | C24: 23559.95 | D24: =C24/C23-1 -> 0.0033131549 | F24: 20.76 | G24: =F24/F23-1 -> -0.0052707235
B25: Feb 10, 2025 | C25: 22929.25 | D25: =C25/C24-1 -> -0.026770006 | F25: 20.51 | G25: =F25/F24-1 -> -0.012042389
B26: Feb 17, 2025 | C26: 22795.9 | D26: =C26/C25-1 -> -0.0058157157 | F26: 20.13 | G26: =F26/F25-1 -> -0.018527548
B27: Feb 24, 2025 | C27: 22124.7 | D27: =C27/C26-1 -> -0.029443891 | F27: 19.11 | G27: =F27/F26-1 -> -0.050670641
B28: Mar 03, 2025 | C28: 22552.5 | D28: =C28/C27-1 -> 0.019335855 | F28: 18.89 | G28: =F28/F27-1 -> -0.011512297
B29: Mar 10, 2025 | C29: 22397.2 | D29: =C29/C28-1 -> -0.0068861545 | F29: 17.5 | G29: =F29/F28-1 -> -0.073583907
B30: Mar 17, 2025 | C30: 23350.4 | D30: =C30/C29-1 -> 0.042558891 | F30: 17.42 | G30: =F30/F29-1 -> -0.0045714286
B31: Mar 24, 2025 | C31: 23519.35 | D31: =C31/C30-1 -> 0.0072354221 | F31: 17.28 | G31: =F31/F30-1 -> -0.0080367394
B32: Mar 31, 2025 | C32: 22904.45 | D32: =C32/C31-1 -> -0.02614443 | F32: 15.77 | G32: =F32/F31-1 -> -0.087384259
B33: Apr 07, 2025 | C33: 22828.55 | D33: =C33/C32-1 -> -0.0033137665 | F33: 16.05 | G33: =F33/F32-1 -> 0.017755231
B34: Apr 14, 2025 | C34: 23851.65 | D34: =C34/C33-1 -> 0.044816688 | F34: 15.35 | G34: =F34/F33-1 -> -0.043613707
B35: Apr 21, 2025 | C35: 24039.35 | D35: =C35/C34-1 -> 0.0078694765 | F35: 16.55 | G35: =F35/F34-1 -> 0.078175896
... B111: Oct 05, 2026 | C111: 22520.45 | D111: =C111/C110-1 -> 0.0043930167 | F111: 10.8 | G111: =F111/F110-1 -> -0.02173913

Sheet RM
B2: Returns on Market
B4: Year | C4: Annual
B5: 2000 | C5: -0.1465 | E5: Average Returns | F5: =AVERAGE(C5:C30) -> 0.15149231
B6: 2001 | C6: -0.1618 | E6: Dividend Yield | F6: 0.013
B7: 2002 | C7: 0.0325 | E7: Total Market Returns | F7: =SUM(F5:F6) -> 0.16449231
B8: 2003 | C8: 0.719
B9: 2004 | C9: 0.1068
B10: 2005 | C10: 0.3634
B11: 2006 | C11: 0.3983
B12: 2007 | C12: 0.5477
B13: 2008 | C13: -0.5179
B14: 2009 | C14: 0.7576
B15: 2010 | C15: 0.1795
B16: 2011 | C16: -0.2462
B17: 2012 | C17: 0.277
B18: 2013 | C18: 0.0676
B19: 2014 | C19: 0.3139
... B30: 2025 | C30: 0.1051

Sheet Common Size Statement
B2: ="Common Size Statement-"&'Data Sheet >'!B1 -> Common Size Statement-INFOSYS LTD
B4: Particulers | C4: ='Cash Flow '!C3 -> 44651 | D4: ='Cash Flow '!D3 -> 45016 | E4: ='Cash Flow '!E3 -> 45382 | F4: ='Cash Flow '!F3 -> 45747 | G4: ='Cash Flow '!G3 -> 46112 | H4: ='Cash Flow '!H3 -> 46477 | I4: ='Cash Flow '!I3 -> 46842 | J4: ='Cash Flow '!J3 -> 47207 | ... L4: ='Cash Flow '!L3 -> 47937
B6: ='Income Statement '!B5 -> Sales | C6: ='Income Statement '!C5/'Income Statement '!C5 -> 1 | D6: ='Income Statement '!D5/'Income Statement '!D5 -> 1 | E6: ='Income Statement '!E5/'Income Statement '!E5 -> 1 | F6: ='Income Statement '!F5/'Income Statement '!F5 -> 1 | G6: ='Income Statement '!G5/'Income Statement '!G5 -> 1 | H6: ='Income Statement '!H5/'Income Statement '!H5 -> 1 | I6: ='Income Statement '!I5/'Income Statement '!I5 -> 1 | J6: ='Income Statement '!J5/'Income Statement '!J5 -> 1 | ... L6: ='Income Statement '!L5/'Income Statement '!L5 -> 1
B7: ='Income Statement '!B8 -> COGS | C7: ='Income Statement '!C8/'Income Statement '!C5 -> 0.17117584 | D7: ='Income Statement '!D8/'Income Statement '!D5 -> 0.18059918 | E7: ='Income Statement '!E8/'Income Statement '!E5 -> 0.17826511 | F7: ='Income Statement '!F8/'Income Statement '!F5 -> 0.18784588 | G7: ='Income Statement '!G8/'Income Statement '!G5 -> 0.18553037 | H7: ='Income Statement '!H8/'Income Statement '!H5 -> 0.18068328 | I7: ='Income Statement '!I8/'Income Statement '!I5 -> 0.18068328 | J7: ='Income Statement '!J8/'Income Statement '!J5 -> 0.18068328 | ... L7: ='Income Statement '!L8/'Income Statement '!L5 -> 0.18068328
B8: ='Income Statement '!B14 -> Selling & Other Expenses | C8: ='Income Statement '!C14/'Income Statement '!C5 -> 0.56993941 | D8: ='Income Statement '!D14/'Income Statement '!D5 -> 0.58004184 | E8: ='Income Statement '!E14/'Income Statement '!E5 -> 0.58470098 | F8: ='Income Statement '!F14/'Income Statement '!F5 -> 0.57142769 | G8: ='Income Statement '!G14/'Income Statement '!G5 -> 0.57780577 | H8: ='Income Statement '!H14/'Income Statement '!H5 -> 0.57780577 | I8: ='Income Statement '!I14/'Income Statement '!I5 -> 0.57780577 | J8: ='Income Statement '!J14/'Income Statement '!J5 -> 0.57780577 | ... L8: ='Income Statement '!L14/'Income Statement '!L5 -> 0.57780577
B9: ='Income Statement '!B17 -> EBITDA | C9: ='Income Statement '!C17/'Income Statement '!C5 -> 0.25888475 | D9: ='Income Statement '!D17/'Income Statement '!D5 -> 0.23935898 | E9: ='Income Statement '!E17/'Income Statement '!E5 -> 0.2370339 | F9: ='Income Statement '!F17/'Income Statement '!F5 -> 0.24072642 | G9: ='Income Statement '!G17/'Income Statement '!G5 -> 0.23666387 | H9: ='Income Statement '!H17/'Income Statement '!H5 -> 0.24151096 | I9: ='Income Statement '!I17/'Income Statement '!I5 -> 0.24151096 | J9: ='Income Statement '!J17/'Income Statement '!J5 -> 0.24151096 | ... L9: ='Income Statement '!L17/'Income Statement '!L5 -> 0.24151096
B10: ='Income Statement '!B20 -> Depreciation | C10: ='Income Statement '!C20/'Income Statement '!C5 -> 0.028575891 | D10: ='Income Statement '!D20/'Income Statement '!D5 -> 0.028787125 | E10: ='Income Statement '!E20/'Income Statement '!E5 -> 0.030441856 | F10: ='Income Statement '!F20/'Income Statement '!F5 -> 0.029523284 | G10: ='Income Statement '!G20/'Income Statement '!G5 -> 0.027439127 | H10: ='Income Statement '!H20/'Income Statement '!H5 -> 0.028953457 | I10: ='Income Statement '!I20/'Income Statement '!I5 -> 0.028953457 | J10: ='Income Statement '!J20/'Income Statement '!J5 -> 0.028953457 | ... L10: ='Income Statement '!L20/'Income Statement '!L5 -> 0.028953457
B11: ='Income Statement '!B23 -> EBIT | C11: ='Income Statement '!C23/'Income Statement '!C5 -> 0.23030886 | D11: ='Income Statement '!D23/'Income Statement '!D5 -> 0.21057186 | E11: ='Income Statement '!E23/'Income Statement '!E5 -> 0.20659205 | F11: ='Income Statement '!F23/'Income Statement '!F5 -> 0.21120314 | G11: ='Income Statement '!G23/'Income Statement '!G5 -> 0.20922474 | H11: ='Income Statement '!H23/'Income Statement '!H5 -> 0.2125575 | I11: ='Income Statement '!I23/'Income Statement '!I5 -> 0.2125575 | J11: ='Income Statement '!J23/'Income Statement '!J5 -> 0.2125575 | ... L11: ='Income Statement '!L23/'Income Statement '!L5 -> 0.2125575
B12: ='Income Statement '!B26 -> Interest | C12: ='Income Statement '!C26/'Income Statement '!C5 -> 0.0016441825 | D12: ='Income Statement '!D26/'Income Statement '!D5 -> 0.0019350399 | E12: ='Income Statement '!E26/'Income Statement '!E5 -> 0.003058502 | F12: ='Income Statement '!F26/'Income Statement '!F5 -> 0.0025523038 | G12: ='Income Statement '!G26/'Income Statement '!G5 -> 0.0023285754 | H12: ='Income Statement '!H26/'Income Statement '!H5 -> 0.0018332534 | I12: ='Income Statement '!I26/'Income Statement '!I5 -> 0.0016725552 | J12: ='Income Statement '!J26/'Income Statement '!J5 -> 0.0015259433 | ... L12: ='Income Statement '!L26/'Income Statement '!L5 -> 0.0012701478
B13: ='Income Statement '!B29 -> EBT | C13: ='Income Statement '!C29/'Income Statement '!C5 -> 0.22866468 | D13: ='Income Statement '!D29/'Income Statement '!D5 -> 0.20863682 | E13: ='Income Statement '!E29/'Income Statement '!E5 -> 0.20353355 | F13: ='Income Statement '!F29/'Income Statement '!F5 -> 0.20865084 | G13: ='Income Statement '!G29/'Income Statement '!G5 -> 0.20689617 | H13: ='Income Statement '!H29/'Income Statement '!H5 -> 0.21072425 | I13: ='Income Statement '!I29/'Income Statement '!I5 -> 0.21088495 | J13: ='Income Statement '!J29/'Income Statement '!J5 -> 0.21103156 | ... L13: ='Income Statement '!L29/'Income Statement '!L5 -> 0.21128735
B14: ='Income Statement '!B32 -> Tax | C14: ='Income Statement '!C32/'Income Statement '!C5 -> 0.065471346 | D14: ='Income Statement '!D32/'Income Statement '!D5 -> 0.06277978 | E14: ='Income Statement '!E32/'Income Statement '!E5 -> 0.063382573 | F14: ='Income Statement '!F32/'Income Statement '!F5 -> 0.066617584 | G14: ='Income Statement '!G32/'Income Statement '!G5 -> 0.058891688 | H14: ='Income Statement '!H32/'Income Statement '!H5 -> 0.063325055 | I14: ='Income Statement '!I32/'Income Statement '!I5 -> 0.063373347 | J14: ='Income Statement '!J32/'Income Statement '!J5 -> 0.063417405 | ... L14: ='Income Statement '!L32/'Income Statement '!L5 -> 0.063494275
B15: ='Income Statement '!B35 -> Net Profit | C15: ='Income Statement '!C35/'Income Statement '!C5 -> 0.16319333 | D15: ='Income Statement '!D35/'Income Statement '!D5 -> 0.14585704 | E15: ='Income Statement '!E35/'Income Statement '!E5 -> 0.14015097 | F15: ='Income Statement '!F35/'Income Statement '!F5 -> 0.14203325 | G15: ='Income Statement '!G35/'Income Statement '!G5 -> 0.14800448 | H15: ='Income Statement '!H35/'Income Statement '!H5 -> 0.14739919 | I15: ='Income Statement '!I35/'Income Statement '!I5 -> 0.1475116 | J15: ='Income Statement '!J35/'Income Statement '!J5 -> 0.14761415 | ... L15: ='Income Statement '!L35/'Income Statement '!L5 -> 0.14779308
B17: ="Common Size Statement-"&'Data Sheet >'!B16 -> Common Size Statement-42825
B19: Particulers | C19: =C4 -> 44651 | D19: =D4 -> 45016 | E19: =E4 -> 45382 | F19: =F4 -> 45747 | G19: =G4 -> 46112 | H19: =H4 -> 46477 | I19: =I4 -> 46842 | J19: =J4 -> 47207 | ... L19: =L4 -> 47937
B21: ='Balance Sheet'!B9 -> Total Liabilitis | C21: ='Balance Sheet'!C9/'Balance Sheet'!C9 -> 1 | D21: ='Balance Sheet'!D9/'Balance Sheet'!D9 -> 1 | E21: ='Balance Sheet'!E9/'Balance Sheet'!E9 -> 1 | F21: ='Balance Sheet'!F9/'Balance Sheet'!F9 -> 1 | G21: ='Balance Sheet'!G9/'Balance Sheet'!G9 -> 1 | H21: ='Balance Sheet'!H9/'Balance Sheet'!H9 -> 1 | I21: ='Balance Sheet'!I9/'Balance Sheet'!I9 -> 1 | J21: ='Balance Sheet'!J9/'Balance Sheet'!J9 -> 1 | ... L21: ='Balance Sheet'!L9/'Balance Sheet'!L9 -> 1
B22: ='Balance Sheet'!B5 -> Equity Share Capital | C22: ='Balance Sheet'!C5/'Balance Sheet'!C9 -> 0.017973254 | D22: ='Balance Sheet'!D5/'Balance Sheet'!D9 -> 0.01660567 | E22: ='Balance Sheet'!E5/'Balance Sheet'!E9 -> 0.015225702 | F22: ='Balance Sheet'!F5/'Balance Sheet'!F9 -> 0.014026185 | G22: ='Balance Sheet'!G5/'Balance Sheet'!G9 -> 0.013118324 | H22: ='Balance Sheet'!H5/'Balance Sheet'!H9 -> 0.012194406 | I22: ='Balance Sheet'!I5/'Balance Sheet'!I9 -> 0.011033249 | J22: ='Balance Sheet'!J5/'Balance Sheet'!J9 -> 0.0098981545 | ... L22: ='Balance Sheet'!L5/'Balance Sheet'!L9 -> 0.0078246657
B23: ='Balance Sheet'!B6 -> Reserves | C23: ='Balance Sheet'!C6/'Balance Sheet'!C9 -> 0.627539 | D23: ='Balance Sheet'!D6/'Balance Sheet'!D9 -> 0.58860638 | E23: ='Balance Sheet'!E6/'Balance Sheet'!E9 -> 0.6325908 | F23: ='Balance Sheet'!F6/'Balance Sheet'!F9 -> 0.63429074 | G23: ='Balance Sheet'!G6/'Balance Sheet'!G9 -> 0.58869128 | H23: ='Balance Sheet'!H6/'Balance Sheet'!H9 -> 0.60405997 | I23: ='Balance Sheet'!I6/'Balance Sheet'!I9 -> 0.61320818 | J23: ='Balance Sheet'!J6/'Balance Sheet'!J9 -> 0.62492412 | ... L23: ='Balance Sheet'!L6/'Balance Sheet'!L9 -> 0.65250276
B24: ='Balance Sheet'!B7 -> Borrowings | C24: ='Balance Sheet'!C7/'Balance Sheet'!C9 -> 0.046894945 | D24: ='Balance Sheet'!D7/'Balance Sheet'!D9 -> 0.066607275 | E24: ='Balance Sheet'!E7/'Balance Sheet'!E9 -> 0.061454198 | F24: ='Balance Sheet'!F7/'Balance Sheet'!F9 -> 0.055664941 | G24: ='Balance Sheet'!G7/'Balance Sheet'!G9 -> 0.059473193 | H24: ='Balance Sheet'!H7/'Balance Sheet'!H9 -> 0.055284519 | I24: ='Balance Sheet'!I7/'Balance Sheet'!I9 -> 0.050020302 | J24: ='Balance Sheet'!J7/'Balance Sheet'!J9 -> 0.044874242 | ... L24: ='Balance Sheet'!L7/'Balance Sheet'!L9 -> 0.03547388
B25: ='Balance Sheet'!B8 -> Other Liabilities | C25: ='Balance Sheet'!C8/'Balance Sheet'!C9 -> 0.3075928 | D25: ='Balance Sheet'!D8/'Balance Sheet'!D9 -> 0.32818068 | E25: ='Balance Sheet'!E8/'Balance Sheet'!E9 -> 0.2907293 | F25: ='Balance Sheet'!F8/'Balance Sheet'!F9 -> 0.29601813 | G25: ='Balance Sheet'!G8/'Balance Sheet'!G9 -> 0.3387172 | H25: ='Balance Sheet'!H8/'Balance Sheet'!H9 -> 0.3284611 | I25: ='Balance Sheet'!I8/'Balance Sheet'!I9 -> 0.32573827 | J25: ='Balance Sheet'!J8/'Balance Sheet'!J9 -> 0.32030348 | ... L25: ='Balance Sheet'!L8/'Balance Sheet'!L9 -> 0.3041987
B27: ='Balance Sheet'!B20 -> Total Assets | C27: ='Balance Sheet'!C20/'Balance Sheet'!C20 -> 1 | D27: ='Balance Sheet'!D20/'Balance Sheet'!D20 -> 1 | E27: ='Balance Sheet'!E20/'Balance Sheet'!E20 -> 1 | F27: ='Balance Sheet'!F20/'Balance Sheet'!F20 -> 1 | G27: ='Balance Sheet'!G20/'Balance Sheet'!G20 -> 1 | H27: ='Balance Sheet'!H20/'Balance Sheet'!H20 -> 1 | I27: ='Balance Sheet'!I20/'Balance Sheet'!I20 -> 1 | J27: ='Balance Sheet'!J20/'Balance Sheet'!J20 -> 1 | ... L27: ='Balance Sheet'!L20/'Balance Sheet'!L20 -> 1
B28: ='Balance Sheet'!B10 -> Net Block | C28: ='Balance Sheet'!C10/'Balance Sheet'!C20 -> 0.22102477 | D28: ='Balance Sheet'!D10/'Balance Sheet'!D20 -> 0.23455809 | E28: ='Balance Sheet'!E10/'Balance Sheet'!E20 -> 0.20307308 | F28: ='Balance Sheet'!F10/'Balance Sheet'!F20 -> 0.20948611 | G28: ='Balance Sheet'!G10/'Balance Sheet'!G20 -> 0.21887639 | H28: ='Balance Sheet'!H10/'Balance Sheet'!H20 -> 0.25079504 | I28: ='Balance Sheet'!I10/'Balance Sheet'!I20 -> 0.26153969 | J28: ='Balance Sheet'!J10/'Balance Sheet'!J20 -> 0.25841533 | ... L28: ='Balance Sheet'!L10/'Balance Sheet'!L20 -> 0.22466968
B29: ='Balance Sheet'!B11 -> Capital Work in Progress | C29: ='Balance Sheet'!C11/'Balance Sheet'!C20 -> 0.0035638102 | D29: ='Balance Sheet'!D11/'Balance Sheet'!D20 -> 0.0023114707 | E29: ='Balance Sheet'!E11/'Balance Sheet'!E20 -> 0.002154095 | F29: ='Balance Sheet'!F11/'Balance Sheet'!F20 -> 0.0055076288 | G29: ='Balance Sheet'!G11/'Balance Sheet'!G20 -> 0.0034092088 | H29: ='Balance Sheet'!H11/'Balance Sheet'!H20 -> 0.003592937 | I29: ='Balance Sheet'!I11/'Balance Sheet'!I20 -> 0.0035631528 | J29: ='Balance Sheet'!J11/'Balance Sheet'!J20 -> 0.0035037033 | ... L29: ='Balance Sheet'!L11/'Balance Sheet'!L20 -> 0.0033275379
B30: ='Balance Sheet'!B12 -> Investments | C30: ='Balance Sheet'!C12/'Balance Sheet'!C20 -> 0.17411269 | D30: ='Balance Sheet'!D12/'Balance Sheet'!D20 -> 0.15632926 | E30: ='Balance Sheet'!E12/'Balance Sheet'!E20 -> 0.18102485 | F30: ='Balance Sheet'!F12/'Balance Sheet'!F20 -> 0.15928144 | G30: ='Balance Sheet'!G12/'Balance Sheet'!G20 -> 0.14181271 | H30: ='Balance Sheet'!H12/'Balance Sheet'!H20 -> 0.17152234 | I30: ='Balance Sheet'!I12/'Balance Sheet'!I20 -> 0.17010047 | J30: ='Balance Sheet'!J12/'Balance Sheet'!J20 -> 0.16726243 | ... L30: ='Balance Sheet'!L12/'Balance Sheet'!L20 -> 0.15885251
B31: ='Balance Sheet'!B13 -> Other Assets | C31: ='Balance Sheet'!C13/'Balance Sheet'!C20 -> 0.25716831 | D31: ='Balance Sheet'!D13/'Balance Sheet'!D20 -> 0.30504992 | E31: ='Balance Sheet'!E13/'Balance Sheet'!E20 -> 0.28306867 | F31: ='Balance Sheet'!F13/'Balance Sheet'!F20 -> 0.2494401 | G31: ='Balance Sheet'!G13/'Balance Sheet'!G20 -> 0.26364332 | H31: ='Balance Sheet'!H13/'Balance Sheet'!H20 -> 0.28554657 | I31: ='Balance Sheet'!I13/'Balance Sheet'!I20 -> 0.28317948 | J31: ='Balance Sheet'!J13/'Balance Sheet'!J20 -> 0.27845477 | ... L31: ='Balance Sheet'!L13/'Balance Sheet'!L20 -> 0.26445412
B32: ='Balance Sheet'!B15 -> Receivables | C32: ='Balance Sheet'!C15/'Balance Sheet'!C20 -> 0.19445039 | D32: ='Balance Sheet'!D15/'Balance Sheet'!D20 -> 0.20405149 | E32: ='Balance Sheet'!E15/'Balance Sheet'!E20 -> 0.22197471 | F32: ='Balance Sheet'!F15/'Balance Sheet'!F20 -> 0.21081904 | G32: ='Balance Sheet'!G15/'Balance Sheet'!G20 -> 0.22836514 | H32: ='Balance Sheet'!H15/'Balance Sheet'!H20 -> 0.22290309 | I32: ='Balance Sheet'!I15/'Balance Sheet'!I20 -> 0.2210553 | J32: ='Balance Sheet'!J15/'Balance Sheet'!J20 -> 0.2173671 | ... L32: ='Balance Sheet'!L15/'Balance Sheet'!L20 -> 0.20643793
B33: ='Balance Sheet'!B16 -> Inventory | C33: =IFERROR('Balance Sheet'!C16/'Balance Sheet'!C20,0) -> 0 | D33: =IFERROR('Balance Sheet'!D16/'Balance Sheet'!D20,0) -> 0 | E33: =IFERROR('Balance Sheet'!E16/'Balance Sheet'!E20,0) -> 0 | F33: =IFERROR('Balance Sheet'!F16/'Balance Sheet'!F20,0) -> 0 | G33: =IFERROR('Balance Sheet'!G16/'Balance Sheet'!G20,0) -> 0 | H33: =IFERROR('Balance Sheet'!H16/'Balance Sheet'!H20,0) -> 0 | I33: =IFERROR('Balance Sheet'!I16/'Balance Sheet'!I20,0) -> 0 | J33: =IFERROR('Balance Sheet'!J16/'Balance Sheet'!J20,0) -> 0 | ... L33: =IFERROR('Balance Sheet'!L16/'Balance Sheet'!L20,0) -> 0
B34: ='Balance Sheet'!B17 -> Cash & Bank | C34: ='Balance Sheet'!C17/'Balance Sheet'!C20 -> 0.14968003 | D34: ='Balance Sheet'!D17/'Balance Sheet'!D20 -> 0.097699766 | E34: ='Balance Sheet'!E17/'Balance Sheet'!E20 -> 0.1087046 | F34: ='Balance Sheet'!F17/'Balance Sheet'!F20 -> 0.16546568 | G34: ='Balance Sheet'!G17/'Balance Sheet'!G20 -> 0.14389324 | H34: ='Balance Sheet'!H17/'Balance Sheet'!H20 -> 0.065640028 | I34: ='Balance Sheet'!I17/'Balance Sheet'!I20 -> 0.060561905 | J34: ='Balance Sheet'!J17/'Balance Sheet'!J20 -> 0.074996671 | ... L34: ='Balance Sheet'!L17/'Balance Sheet'!L20 -> 0.14225822

Sheet Ratio Analysis
B2: ="Ratio Analysis-"&'Data Sheet >'!B1 -> Ratio Analysis-INFOSYS LTD
B3: Year | C3: ='Data Sheet >'!G16 -> 44651 | D3: ='Data Sheet >'!H16 -> 45016 | E3: ='Data Sheet >'!I16 -> 45382 | F3: ='Data Sheet >'!J16 -> 45747 | G3: ='Data Sheet >'!K16 -> 46112 | H3: =G3+365 -> 46477 | I3: =H3+365 -> 46842 | J3: =I3+365 -> 47207 | K3: =J3+365 -> 47572 | L3: =K3+365 -> 47937 | M3: Trend | N3: Mean | O3: Median
B5: Sales Growth | D5: ='Income Statement '!D5/'Income Statement '!C5-1 -> 0.20655864 | E5: ='Income Statement '!E5/'Income Statement '!D5-1 -> 0.047033734 | F5: ='Income Statement '!F5/'Income Statement '!E5-1 -> 0.060649444 | G5: ='Income Statement '!G5/'Income Statement '!F5-1 -> 0.096079514 | H5: ='Income Statement '!H5/'Income Statement '!G5-1 -> 0.096079514 | I5: ='Income Statement '!I5/'Income Statement '!H5-1 -> 0.096079514 | J5: ='Income Statement '!J5/'Income Statement '!I5-1 -> 0.096079514 | K5: ='Income Statement '!K5/'Income Statement '!J5-1 -> 0.096079514 | L5: ='Income Statement '!L5/'Income Statement '!K5-1 -> 0.096079514 | N5: =AVERAGE(D5:L5) -> 0.098968767 | O5: =MEDIAN(D5:L5) -> 0.096079514
B6: EBITDA Growth | D6: ='Income Statement '!D17/'Income Statement '!C17-1 -> 0.11555683 | E6: ='Income Statement '!E17/'Income Statement '!D17-1 -> 0.03686308 | F6: ='Income Statement '!F17/'Income Statement '!E17-1 -> 0.077172272 | G6: ='Income Statement '!G17/'Income Statement '!F17-1 -> 0.077581813 | H6: ='Income Statement '!H17/'Income Statement '!G17-1 -> 0.11852822 | I6: ='Income Statement '!I17/'Income Statement '!H17-1 -> 0.096079514 | J6: ='Income Statement '!J17/'Income Statement '!I17-1 -> 0.096079514 | K6: ='Income Statement '!K17/'Income Statement '!J17-1 -> 0.096079514 | L6: ='Income Statement '!L17/'Income Statement '!K17-1 -> 0.096079514 | N6: =AVERAGE(D6:L6) -> 0.090002252 | O6: =MEDIAN(D6:L6) -> 0.096079514
B7: EBIT Growth | D7: ='Income Statement '!D23/'Income Statement '!C23-1 -> 0.10315902 | E7: ='Income Statement '!E23/'Income Statement '!D23-1 -> 0.027244782 | F7: ='Income Statement '!F23/'Income Statement '!E23-1 -> 0.084322928 | G7: ='Income Statement '!G23/'Income Statement '!F23-1 -> 0.085812224 | H7: ='Income Statement '!H23/'Income Statement '!G23-1 -> 0.11353907 | I7: ='Income Statement '!I23/'Income Statement '!H23-1 -> 0.096079514 | J7: ='Income Statement '!J23/'Income Statement '!I23-1 -> 0.096079514 | K7: ='Income Statement '!K23/'Income Statement '!J23-1 -> 0.096079514 | L7: ='Income Statement '!L23/'Income Statement '!K23-1 -> 0.096079514 | N7: =AVERAGE(D7:L7) -> 0.088710676 | O7: =MEDIAN(D7:L7) -> 0.096079514
B8: Net Profit Growth | D8: ='Income Statement '!D35/'Income Statement '!C35-1 -> 0.078383961 | E8: ='Income Statement '!E35/'Income Statement '!D35-1 -> 0.0060727799 | F8: ='Income Statement '!F35/'Income Statement '!E35-1 -> 0.074894368 | G8: ='Income Statement '!G35/'Income Statement '!F35-1 -> 0.14215983 | H8: ='Income Statement '!H35/'Income Statement '!G35-1 -> 0.091596948 | I8: ='Income Statement '!I35/'Income Statement '!H35-1 -> 0.096915384 | J8: ='Income Statement '!J35/'Income Statement '!I35-1 -> 0.096841533 | K8: ='Income Statement '!K35/'Income Statement '!J35-1 -> 0.096774253 | L8: ='Income Statement '!L35/'Income Statement '!K35-1 -> 0.096712953 | N8: =AVERAGE(D8:L8) -> 0.086705778 | O8: =MEDIAN(D8:L8) -> 0.096712953
B9: Dividend Growth | D9: ='Income Statement '!D43/'Income Statement '!C43-1 -> 0.096761529 | E9: ='Income Statement '!E43/'Income Statement '!D43-1 -> 0.35349861 | F9: ='Income Statement '!F43/'Income Statement '!E43-1 -> -0.064855345 | G9: ='Income Statement '!G43/'Income Statement '!F43-1 -> 0.116149 | H9: ='Income Statement '!H43/'Income Statement '!G43-1 -> 0 | I9: ='Income Statement '!I43/'Income Statement '!H43-1 -> 0 | J9: ='Income Statement '!J43/'Income Statement '!I43-1 -> 0 | K9: ='Income Statement '!K43/'Income Statement '!J43-1 -> 0 | L9: ='Income Statement '!L43/'Income Statement '!K43-1 -> 0 | N9: =AVERAGE(D9:L9) -> 0.0557282 | O9: =MEDIAN(D9:L9) -> 0
B11: Gross Margin | C11: ='Income Statement '!C12 -> 0.82882416 | D11: ='Income Statement '!D12 -> 0.81940082 | E11: ='Income Statement '!E12 -> 0.82173489 | F11: ='Income Statement '!F12 -> 0.81215412 | G11: ='Income Statement '!G12 -> 0.81446963 | H11: ='Income Statement '!H12 -> 0.81931672 | I11: ='Income Statement '!I12 -> 0.81931672 | J11: ='Income Statement '!J12 -> 0.81931672 | ... L11: ='Income Statement '!L12 -> 0.81931672 | N11: =AVERAGE(C11:L11) -> 0.81931672 | O11: =MEDIAN(C11:L11) -> 0.81931672
B12: EBITDA Margin | C12: ='Income Statement '!C18 -> 0.25888475 | D12: ='Income Statement '!D18 -> 0.23935898 | E12: ='Income Statement '!E18 -> 0.2370339 | F12: ='Income Statement '!F18 -> 0.24072642 | G12: ='Income Statement '!G18 -> 0.23666387 | H12: ='Income Statement '!H18 -> 0.24151096 | I12: ='Income Statement '!I18 -> 0.24151096 | J12: ='Income Statement '!J18 -> 0.24151096 | ... L12: ='Income Statement '!L18 -> 0.24151096 | N12: =AVERAGE(C12:L12) -> 0.24202227 | O12: =MEDIAN(C12:L12) -> 0.24151096
B13: EBIT Margin | C13: ='Income Statement '!C24 -> 0.23030886 | D13: ='Income Statement '!D24 -> 0.21057186 | E13: ='Income Statement '!E24 -> 0.20659205 | F13: ='Income Statement '!F24 -> 0.21120314 | G13: ='Income Statement '!G24 -> 0.20922474 | H13: ='Income Statement '!H24 -> 0.2125575 | I13: ='Income Statement '!I24 -> 0.2125575 | J13: ='Income Statement '!J24 -> 0.2125575 | ... L13: ='Income Statement '!L24 -> 0.2125575 | N13: =AVERAGE(C13:L13) -> 0.21306882 | O13: =MEDIAN(C13:L13) -> 0.2125575
B14: EBT Margin | C14: ='Income Statement '!C30 -> 0.22866468 | D14: ='Income Statement '!D30 -> 0.20863682 | E14: ='Income Statement '!E30 -> 0.20353355 | F14: ='Income Statement '!F30 -> 0.20865084 | G14: ='Income Statement '!G30 -> 0.20689617 | H14: ='Income Statement '!H30 -> 0.21072425 | I14: ='Income Statement '!I30 -> 0.21088495 | J14: ='Income Statement '!J30 -> 0.21103156 | ... L14: ='Income Statement '!L30 -> 0.21128735 | N14: =AVERAGE(C14:L14) -> 0.21114755 | O14: =MEDIAN(C14:L14) -> 0.2108046
B15: Net Profit Margin | C15: ='Income Statement '!C36 -> 0.16319333 | D15: ='Income Statement '!D36 -> 0.14585704 | E15: ='Income Statement '!E36 -> 0.14015097 | F15: ='Income Statement '!F36 -> 0.14203325 | G15: ='Income Statement '!G36 -> 0.14800448 | H15: ='Income Statement '!H36 -> 0.14739919 | I15: ='Income Statement '!I36 -> 0.1475116 | J15: ='Income Statement '!J36 -> 0.14761415 | ... L15: ='Income Statement '!L36 -> 0.14779308 | N15: =AVERAGE(C15:L15) -> 0.14772648 | O15: =MEDIAN(C15:L15) -> 0.14756288
B17: Sales Expenses%Sales | C17: ='Income Statement '!C15 -> 0.56993941 | D17: ='Income Statement '!D15 -> 0.58004184 | E17: ='Income Statement '!E15 -> 0.58470098 | F17: ='Income Statement '!F15 -> 0.57142769 | G17: ='Income Statement '!G15 -> 0.57780577 | H17: ='Income Statement '!H15 -> 0.57780577 | I17: ='Income Statement '!I15 -> 0.57780577 | J17: ='Income Statement '!J15 -> 0.57780577 | ... L17: ='Income Statement '!L15 -> 0.57780577 | N17: =AVERAGE(C17:L17) -> 0.57729445 | O17: =MEDIAN(C17:L17) -> 0.57780577
B18: Depreciation%Sales | C18: ='Income Statement '!C21 -> 0.028575891 | D18: ='Income Statement '!D21 -> 0.028787125 | E18: ='Income Statement '!E21 -> 0.030441856 | F18: ='Income Statement '!F21 -> 0.029523284 | G18: ='Income Statement '!G21 -> 0.027439127 | H18: ='Income Statement '!H21 -> 0.028953457 | I18: ='Income Statement '!I21 -> 0.028953457 | J18: ='Income Statement '!J21 -> 0.028953457 | ... L18: ='Income Statement '!L21 -> 0.028953457 | N18: =AVERAGE(C18:L18) -> 0.028953457 | O18: =MEDIAN(C18:L18) -> 0.028953457
B19: OperatingIncome%Sales | C19: =C13 -> 0.23030886 | D19: =D13 -> 0.21057186 | E19: =E13 -> 0.20659205 | F19: =F13 -> 0.21120314 | G19: =G13 -> 0.20922474 | H19: =H13 -> 0.2125575 | I19: =I13 -> 0.2125575 | J19: =J13 -> 0.2125575 | ... L19: =L13 -> 0.2125575 | N19: =AVERAGE(C19:L19) -> 0.21306882 | O19: =MEDIAN(C19:L19) -> 0.2125575
B21: Return on Capital Employed | C21: ='Income Statement '!C23/SUM('Balance Sheet'!C5:C7) -> 0.34661734 | D21: ='Income Statement '!D23/SUM('Balance Sheet'!D5:D7) -> 0.3692089 | E21: ='Income Statement '!E23/SUM('Balance Sheet'!E5:E7) -> 0.32906971 | F21: ='Income Statement '!F23/SUM('Balance Sheet'!F5:F7) -> 0.33085684 | G21: ='Income Statement '!G23/SUM('Balance Sheet'!G5:G7) -> 0.36635041 | H21: ='Income Statement '!H23/SUM('Balance Sheet'!H5:H7) -> 0.37342249 | I21: ='Income Statement '!I23/SUM('Balance Sheet'!I5:I7) -> 0.36883147 | J21: ='Income Statement '!J23/SUM('Balance Sheet'!J5:J7) -> 0.35977776 | ... L21: ='Income Statement '!L23/SUM('Balance Sheet'!L5:L7) -> 0.33377961 | N21: =AVERAGE(C21:L21) -> 0.35255903 | O21: =MEDIAN(C21:L21) -> 0.35372677
B22: Retained Earning% | C22: ='Income Statement '!C46 -> 16.267858 | D22: ='Income Statement '!D46 -> 17.687413 | E22: ='Income Statement '!E46 -> 5.9837626 | F22: ='Income Statement '!F46 -> 12.814389 | G22: ='Income Statement '!G46 -> 17.286222 | H22: ='Income Statement '!H46 -> 23.258001 | I22: ='Income Statement '!I46 -> 30.15528 | J22: ='Income Statement '!J46 -> 37.715246 | ... L22: ='Income Statement '!L46 -> 55.084041 | N22: =AVERAGE(C22:L22) -> 26.225378 | O22: =MEDIAN(C22:L22) -> 20.472707
B23: Return on Equity% | C23: ='Income Statement '!C35/SUM('Balance Sheet'!C5:C6) -> 0.26345056 | D23: ='Income Statement '!D35/SUM('Balance Sheet'!D5:D6) -> 0.28388611 | E23: ='Income Statement '!E35/SUM('Balance Sheet'!E5:E6) -> 0.24441645 | F23: ='Income Statement '!F35/SUM('Balance Sheet'!F5:F6) -> 0.24160387 | G23: ='Income Statement '!G35/SUM('Balance Sheet'!G5:G6) -> 0.284765 | H23: ='Income Statement '!H35/SUM('Balance Sheet'!H5:H6) -> 0.28218264 | I23: ='Income Statement '!I35/SUM('Balance Sheet'!I5:I6) -> 0.27647358 | J23: ='Income Statement '!J35/SUM('Balance Sheet'!J5:J6) -> 0.26751539 | ... L23: ='Income Statement '!L35/SUM('Balance Sheet'!L5:L6) -> 0.24454758 | N23: =AVERAGE(C23:L23) -> 0.26453758 | O23: =MEDIAN(C23:L23) -> 0.26548298
B24: Self Sustained Growth Rate | C24: =C22*C23 -> 4.2857765 | D24: =D22*D23 -> 5.0212108 | E24: =E22*E23 -> 1.46253 | F24: =F22*F23 -> 3.0960059 | G24: =G22*G23 -> 4.9225109 | H24: =H22*H23 -> 6.5630042 | I24: =I22*I23 -> 8.3371381 | J24: =J22*J23 -> 10.089409 | ... L24: =L22*L23 -> 13.470669 | N24: =AVERAGE(C24:L24) -> 6.9049251 | O24: =MEDIAN(C24:L24) -> 5.7921075
B25: Interest Coverage Ratio | C25: ='Income Statement '!C23/'Income Statement '!C26 -> 140.075 | D25: ='Income Statement '!D23/'Income Statement '!D26 -> 108.82042 | E25: ='Income Statement '!E23/'Income Statement '!E26 -> 67.546809 | F25: ='Income Statement '!F23/'Income Statement '!F26 -> 82.75 | G25: ='Income Statement '!G23/'Income Statement '!G26 -> 89.850962 | H25: ='Income Statement '!H23/'Income Statement '!H26 -> 115.94551 | I25: ='Income Statement '!I23/'Income Statement '!I26 -> 127.0855 | J25: ='Income Statement '!J23/'Income Statement '!J26 -> 139.29581 | ... L25: ='Income Statement '!L23/'Income Statement '!L26 -> 167.34863 | N25: =AVERAGE(C25:L25) -> 119.13979 | O25: =MEDIAN(C25:L25) -> 121.5155
B27: Debtor Turnover Ratio | C27: ='Income Statement '!C5/'Balance Sheet'!C15 -> 5.3591065 | D27: ='Income Statement '!D5/'Balance Sheet'!D15 -> 5.7727738 | E27: ='Income Statement '!E5/'Balance Sheet'!E15 -> 5.0895903 | F27: ='Income Statement '!F5/'Balance Sheet'!F15 -> 5.2310803 | G27: ='Income Statement '!G5/'Balance Sheet'!G15 -> 5.0703866 | H27: ='Income Statement '!H5/'Balance Sheet'!H15 -> 5.2927224 | I27: ='Income Statement '!I5/'Balance Sheet'!I15 -> 5.2927224 | J27: ='Income Statement '!J5/'Balance Sheet'!J15 -> 5.2927224 | ... L27: ='Income Statement '!L5/'Balance Sheet'!L15 -> 5.2927224 | N27: =AVERAGE(C27:L27) -> 5.298655 | O27: =MEDIAN(C27:L27) -> 5.2927224
B28: Creditor Turnover Ratio | C28: 0 | D28: 0 | E28: 0 | F28: 0 | G28: 0 | H28: 0 | I28: 0 | J28: 0 | K28: 0 | L28: 0 | N28: =AVERAGE(C28:L28) -> 0 | O28: =MEDIAN(C28:L28) -> 0
B29: Inventory Turnover | C29: =IFERROR('Income Statement '!C5/'Balance Sheet'!C16,0) -> 0 | D29: =IFERROR('Income Statement '!D5/'Balance Sheet'!D16,0) -> 0 | E29: =IFERROR('Income Statement '!E5/'Balance Sheet'!E16,0) -> 0 | F29: =IFERROR('Income Statement '!F5/'Balance Sheet'!F16,0) -> 0 | G29: =IFERROR('Income Statement '!G5/'Balance Sheet'!G16,0) -> 0 | H29: =IFERROR('Income Statement '!H5/'Balance Sheet'!H16,0) -> 0 | I29: =IFERROR('Income Statement '!I5/'Balance Sheet'!I16,0) -> 0 | J29: =IFERROR('Income Statement '!J5/'Balance Sheet'!J16,0) -> 0 | ... L29: =IFERROR('Income Statement '!L5/'Balance Sheet'!L16,0) -> 0 | N29: =AVERAGE(C29:L29) -> 0 | O29: =MEDIAN(C29:L29) -> 0
B30: Fixed Asset Turnover | C30: ='Income Statement '!C5/'Balance Sheet'!C10 -> 4.7147674 | D30: ='Income Statement '!D5/'Balance Sheet'!D10 -> 5.0219675 | E30: ='Income Statement '!E5/'Balance Sheet'!E10 -> 5.5633191 | F30: ='Income Statement '!F5/'Balance Sheet'!F10 -> 5.2643648 | G30: ='Income Statement '!G5/'Balance Sheet'!G10 -> 5.2901984 | H30: ='Income Statement '!H5/'Balance Sheet'!H10 -> 4.7040969 | I30: ='Income Statement '!I5/'Balance Sheet'!I10 -> 4.4734484 | J30: ='Income Statement '!J5/'Balance Sheet'!J10 -> 4.4519947 | ... L30: ='Income Statement '!L5/'Balance Sheet'!L10 -> 4.8632224 | N30: =AVERAGE(C30:L30) -> 4.8933727 | O30: =MEDIAN(C30:L30) -> 4.7889949
B31: Capital Turnover Ratio | C31: ='Income Statement '!C5/SUM('Balance Sheet'!C5:C6) -> 1.6143464 | D31: ='Income Statement '!D5/SUM('Balance Sheet'!D5:D6) -> 1.9463312 | E31: ='Income Statement '!E5/SUM('Balance Sheet'!E5:E6) -> 1.7439512 | F31: ='Income Statement '!F5/SUM('Balance Sheet'!F5:F6) -> 1.7010374 | G31: ='Income Statement '!G5/SUM('Balance Sheet'!G5:G6) -> 1.9240296 | H31: ='Income Statement '!H5/SUM('Balance Sheet'!H5:H6) -> 1.914411 | I31: ='Income Statement '!I5/SUM('Balance Sheet'!I5:I6) -> 1.8742497 | J31: ='Income Statement '!J5/SUM('Balance Sheet'!J5:J6) -> 1.8122611 | ... L31: ='Income Statement '!L5/SUM('Balance Sheet'!L5:L6) -> 1.6546619 | N31: =AVERAGE(C31:L31) -> 1.7922052 | O31: =MEDIAN(C31:L31) -> 1.7781061
B33: Debtor Days | C33: =365/C27 -> 68.108368 | D33: =365/D27 -> 63.227837 | E33: =365/E27 -> 71.715006 | F33: =365/F27 -> 69.775262 | G33: =365/G27 -> 71.986622 | H33: =365/H27 -> 68.962619 | I33: =365/I27 -> 68.962619 | J33: =365/J27 -> 68.962619 | ... L33: =365/L27 -> 68.962619 | N33: =AVERAGE(C33:L33) -> 68.962619 | O33: =MEDIAN(C33:L33) -> 68.962619
B34: Payable Days | C34: =IFERROR(365/C28,0) -> 0 | D34: =IFERROR(365/D28,0) -> 0 | E34: =IFERROR(365/E28,0) -> 0 | F34: =IFERROR(365/F28,0) -> 0 | G34: =IFERROR(365/G28,0) -> 0 | H34: =IFERROR(365/H28,0) -> 0 | I34: =IFERROR(365/I28,0) -> 0 | J34: =IFERROR(365/J28,0) -> 0 | ... L34: =IFERROR(365/L28,0) -> 0 | N34: =AVERAGE(C34:L34) -> 0 | O34: =MEDIAN(C34:L34) -> 0
B35: Inventory Days | C35: =IFERROR(365/C29,0) -> 0 | D35: =IFERROR(365/D29,0) -> 0 | E35: =IFERROR(365/E29,0) -> 0 | F35: =IFERROR(365/F29,0) -> 0 | G35: =IFERROR(365/G29,0) -> 0 | H35: =IFERROR(365/H29,0) -> 0 | I35: =IFERROR(365/I29,0) -> 0 | J35: =IFERROR(365/J29,0) -> 0 | ... L35: =IFERROR(365/L29,0) -> 0 | N35: =AVERAGE(C35:L35) -> 0 | O35: =MEDIAN(C35:L35) -> 0
B36: Cash Conversion Cycle (in days) | C36: =IFERROR(SUM(C33,C35)-C34,0) -> 68.108368 | D36: =IFERROR(SUM(D33,D35)-D34,0) -> 63.227837 | E36: =IFERROR(SUM(E33,E35)-E34,0) -> 71.715006 | F36: =IFERROR(SUM(F33,F35)-F34,0) -> 69.775262 | G36: =IFERROR(SUM(G33,G35)-G34,0) -> 71.986622 | H36: =IFERROR(SUM(H33,H35)-H34,0) -> 68.962619 | I36: =IFERROR(SUM(I33,I35)-I34,0) -> 68.962619 | J36: =IFERROR(SUM(J33,J35)-J34,0) -> 68.962619 | ... L36: =IFERROR(SUM(L33,L35)-L34,0) -> 68.962619 | N36: =AVERAGE(C36:L36) -> 68.962619 | O36: =MEDIAN(C36:L36) -> 68.962619
B38: CFO/Sales | C38: ='Cash Flow '!C13/'Income Statement '!C5 -> 0.36484409 | D38: ='Cash Flow '!D13/'Income Statement '!D5 -> 0.14773757 | E38: ='Cash Flow '!E13/'Income Statement '!E5 -> 0.13210776 | F38: ='Cash Flow '!F13/'Income Statement '!F5 -> 0.14195963 | G38: ='Cash Flow '!G13/'Income Statement '!G5 -> 0.19627204 | H38: ='Cash Flow '!H13/'Income Statement '!H5 -> 0.1445721 | I38: ='Cash Flow '!I13/'Income Statement '!I5 -> 0.16309176 | J38: ='Cash Flow '!J13/'Income Statement '!J5 -> 0.16319432 | ... L38: ='Cash Flow '!L13/'Income Statement '!L5 -> 0.16337324 | N38: =AVERAGE(C38:L38) -> 0.17804404 | O38: =MEDIAN(C38:L38) -> 0.16314304
B39: CFO/Total Assets | C39: ='Cash Flow '!C13/'Balance Sheet'!C20 -> 0.38019687 | D39: ='Cash Flow '!D13/'Balance Sheet'!D20 -> 0.17402645 | E39: ='Cash Flow '!E13/'Balance Sheet'!E20 -> 0.14925011 | F39: ='Cash Flow '!F13/'Balance Sheet'!F20 -> 0.15655469 | G39: ='Cash Flow '!G13/'Balance Sheet'!G20 -> 0.2272633 | H39: ='Cash Flow '!H13/'Balance Sheet'!H20 -> 0.17056099 | I39: ='Cash Flow '!I13/'Balance Sheet'!I20 -> 0.19081481 | J39: ='Cash Flow '!J13/'Balance Sheet'!J20 -> 0.18774914 | ... L39: ='Cash Flow '!L13/'Balance Sheet'!L20 -> 0.17850465 | N39: =AVERAGE(C39:L39) -> 0.1998436 | O39: =MEDIAN(C39:L39) -> 0.18100982
B40: CFO/Total debt | C40: ='Cash Flow '!C13/'Balance Sheet'!C7 -> 8.1074169 | D40: ='Cash Flow '!D13/'Balance Sheet'!D7 -> 2.6127244 | E40: ='Cash Flow '!E13/'Balance Sheet'!E7 -> 2.4286398 | F40: ='Cash Flow '!F13/'Balance Sheet'!F7 -> 2.8124468 | G40: ='Cash Flow '!G13/'Balance Sheet'!G7 -> 3.8212729 | H40: ='Cash Flow '!H13/'Balance Sheet'!H7 -> 3.0851493 | I40: ='Cash Flow '!I13/'Balance Sheet'!I7 -> 3.8147472 | J40: ='Cash Flow '!J13/'Balance Sheet'!J7 -> 4.1838955 | ... L40: ='Cash Flow '!L13/'Balance Sheet'!L7 -> 5.0320025 | N40: =AVERAGE(C40:L40) -> 4.0486807 | O40: =MEDIAN(C40:L40) -> 3.81801

Sheet Cash Flow   
B2: ="Cash Flow Statement-"&'Data Sheet >'!B1 -> Cash Flow Statement-INFOSYS LTD
B3: Year | C3: ='Data Sheet >'!G16 -> 44651 | D3: ='Data Sheet >'!H16 -> 45016 | E3: ='Data Sheet >'!I16 -> 45382 | F3: ='Data Sheet >'!J16 -> 45747 | G3: ='Data Sheet >'!K16 -> 46112 | H3: =G3+365 -> 46477 | I3: =H3+365 -> 46842 | J3: =I3+365 -> 47207 | K3: =J3+365 -> 47572 | L3: =K3+365 -> 47937
B5: Operating Activities
B6: Profit from operations | C6: =IFERROR('Cash Flow Data'!J4,0) -> 65900 | D6: =IFERROR('Cash Flow Data'!K4,0) -> 30908 | E6: =IFERROR('Cash Flow Data'!L4,0) -> 22237 | F6: =IFERROR('Cash Flow Data'!M4,0) -> 23929 | G6: =IFERROR('Cash Flow Data'!N4,0) -> 34219 | H6: ='Income Statement '!H35+'Income Statement '!H20 -> 34532.425 | I6: ='Income Statement '!I35+'Income Statement '!I20 -> 37874.409 | J6: ='Income Statement '!J35+'Income Statement '!J20 -> 41537.489 | K6: ='Income Statement '!K35+'Income Statement '!K20 -> 45552.517 | L6: ='Income Statement '!L35+'Income Statement '!L20 -> 49953.306
B7: Receivables | C7: =IFERROR('Cash Flow Data'!J5,0) -> 0 | D7: =IFERROR('Cash Flow Data'!K5,0) -> 0 | E7: =IFERROR('Cash Flow Data'!L5,0) -> 0 | F7: =IFERROR('Cash Flow Data'!M5,0) -> 0 | G7: =IFERROR('Cash Flow Data'!N5,0) -> 0 | H7: ='Balance Sheet'!G15-'Balance Sheet'!H15 -> -1762.9535 | I7: ='Balance Sheet'!H15-'Balance Sheet'!I15 -> -3554.6493 | J7: ='Balance Sheet'!I15-'Balance Sheet'!J15 -> -3896.1783 | K7: ='Balance Sheet'!J15-'Balance Sheet'!K15 -> -4270.5212 | L7: ='Balance Sheet'!K15-'Balance Sheet'!L15 -> -4680.8308
B8: Inventory | C8: =IFERROR('Cash Flow Data'!J6,0) -> -16917 | D8: =IFERROR('Cash Flow Data'!K6,0) -> -4031 | E8: =IFERROR('Cash Flow Data'!L6,0) -> 5566 | F8: =IFERROR('Cash Flow Data'!M6,0) -> 4776 | G8: =IFERROR('Cash Flow Data'!N6,0) -> 1290 | H8: 0 | I8: =H8 -> 0 | J8: =I8 -> 0 | K8: =J8 -> 0 | L8: =K8 -> 0
B9: Payables | C9: =IFERROR('Cash Flow Data'!J7,0) -> 0 | D9: =IFERROR('Cash Flow Data'!K7,0) -> 0 | E9: =IFERROR('Cash Flow Data'!L7,0) -> 0 | F9: =IFERROR('Cash Flow Data'!M7,0) -> 0 | G9: =IFERROR('Cash Flow Data'!N7,0) -> 0 | H9: =G9 -> 0 | I9: =H9 -> 0 | J9: =I9 -> 0 | K9: =J9 -> 0 | L9: =K9 -> 0
B10: Other WC items | C10: =IFERROR('Cash Flow Data'!J8,0) -> 7299 | D10: =IFERROR('Cash Flow Data'!K8,0) -> 325 | E10: =IFERROR('Cash Flow Data'!L8,0) -> -2182 | F10: =IFERROR('Cash Flow Data'!M8,0) -> -2569 | G10: =IFERROR('Cash Flow Data'!N8,0) -> 4152 | H10: =('Balance Sheet'!H8-'Balance Sheet'!G8)-('Balance Sheet'!H13-'Balance Sheet'!G13) -> -4460.1414 | I10: =('Balance Sheet'!I8-'Balance Sheet'!H8)-('Balance Sheet'!I13-'Balance Sheet'!H13) -> 684.36079 | J10: =('Balance Sheet'!J8-'Balance Sheet'!I8)-('Balance Sheet'!J13-'Balance Sheet'!I13) -> 750.11384 | K10: =('Balance Sheet'!K8-'Balance Sheet'!J8)-('Balance Sheet'!K13-'Balance Sheet'!J13) -> 822.18442 | L10: =('Balance Sheet'!L8-'Balance Sheet'!K8)-('Balance Sheet'!L13-'Balance Sheet'!K13) -> 901.1795
B11: Working capital changes | C11: =IFERROR('Cash Flow Data'!J9,0) -> -9618 | D11: =IFERROR('Cash Flow Data'!K9,0) -> -3706 | E11: =IFERROR('Cash Flow Data'!L9,0) -> 3384 | F11: =IFERROR('Cash Flow Data'!M9,0) -> 2207 | G11: =IFERROR('Cash Flow Data'!N9,0) -> 5442 | H11: =SUM(H7:H10) -> -6223.0949 | I11: =SUM(I7:I10) -> -2870.2885 | J11: =SUM(J7:J10) -> -3146.0645 | K11: =SUM(K7:K10) -> -3448.3368 | L11: =SUM(L7:L10) -> -3779.6513
B12: Direct taxes | C12: =IFERROR('Cash Flow Data'!J10,0) -> -11902 | D12: =IFERROR('Cash Flow Data'!K10,0) -> -5519 | E12: =IFERROR('Cash Flow Data'!L10,0) -> -5320 | F12: =IFERROR('Cash Flow Data'!M10,0) -> -2998 | G12: =IFERROR('Cash Flow Data'!N10,0) -> -4597 | H12: 0 | I12: =H12 -> 0 | J12: =I12 -> 0 | K12: =J12 -> 0 | L12: =K12 -> 0
B13: Cash form Operating Activities | C13: =SUM(C6,C11,C12) -> 44380 | D13: =SUM(D6,D11,D12) -> 21683 | E13: =SUM(E6,E11,E12) -> 20301 | F13: =SUM(F6,F11,F12) -> 23138 | G13: =SUM(G6,G11,G12) -> 35064 | H13: =SUM(H6,H11,H12) -> 28309.33 | I13: =SUM(I6,I11,I12) -> 35004.12 | J13: =SUM(J6,J11,J12) -> 38391.425 | ... L13: =SUM(L6,L11,L12) -> 46173.655
B15: Investing Activities
B16: Fixed assets purchased | C16: =IFERROR('Cash Flow Data'!J12,0) -> -10522 | D16: =IFERROR('Cash Flow Data'!K12,0) -> -14142 | E16: =IFERROR('Cash Flow Data'!L12,0) -> -18207 | F16: =IFERROR('Cash Flow Data'!M12,0) -> -15671 | G16: =IFERROR('Cash Flow Data'!N12,0) -> -14559 | H16: =-'Dep Capex'!H10 -> -13525.907 | I16: =-'Dep Capex'!I10 -> -12566.12 | J16: =-'Dep Capex'!J10 -> -11674.44 | K16: =-'Dep Capex'!K10 -> -10846.032 | L16: =-'Dep Capex'!L10 -> -10076.408
B17: Fixed assets sold | C17: =IFERROR('Cash Flow Data'!J13,0) -> 569 | D17: =IFERROR('Cash Flow Data'!K13,0) -> 328 | E17: =IFERROR('Cash Flow Data'!L13,0) -> 475 | F17: =IFERROR('Cash Flow Data'!M13,0) -> 1264 | G17: =IFERROR('Cash Flow Data'!N13,0) -> 1401 | H17: 0 | I17: =H17 -> 0 | J17: =I17 -> 0 | K17: =J17 -> 0 | L17: =K17 -> 0
B18: Investments purchased | C18: =IFERROR('Cash Flow Data'!J14,0) -> -1153 | D18: =IFERROR('Cash Flow Data'!K14,0) -> -326 | E18: =IFERROR('Cash Flow Data'!L14,0) -> -4 | F18: =IFERROR('Cash Flow Data'!M14,0) -> -393 | G18: =IFERROR('Cash Flow Data'!N14,0) -> -553 | H18: ='Balance Sheet'!G12-'Balance Sheet'!H12 -> -6588.8914 | I18: ='Balance Sheet'!H12-'Balance Sheet'!I12 -> -2735.2773 | J18: ='Balance Sheet'!I12-'Balance Sheet'!J12 -> -2998.0814 | K18: ='Balance Sheet'!J12-'Balance Sheet'!K12 -> -3286.1356 | L18: ='Balance Sheet'!K12-'Balance Sheet'!L12 -> -3601.8659
B19: Investments sold | C19: =IFERROR('Cash Flow Data'!J15,0) -> 63 | D19: =IFERROR('Cash Flow Data'!K15,0) -> 5191 | E19: =IFERROR('Cash Flow Data'!L15,0) -> 3171 | F19: =IFERROR('Cash Flow Data'!M15,0) -> 554 | G19: =IFERROR('Cash Flow Data'!N15,0) -> 20 | H19: 0 | I19: =H19 -> 0 | J19: =I19 -> 0 | K19: =J19 -> 0 | L19: =K19 -> 0
B20: Interest received | C20: =IFERROR('Cash Flow Data'!J16,0) -> 137 | D20: =IFERROR('Cash Flow Data'!K16,0) -> 248 | E20: =IFERROR('Cash Flow Data'!L16,0) -> 333 | F20: =IFERROR('Cash Flow Data'!M16,0) -> 616 | G20: =IFERROR('Cash Flow Data'!N16,0) -> 650 | H20: 0 | I20: =H20 -> 0 | J20: =I20 -> 0 | K20: =J20 -> 0 | L20: =K20 -> 0
B21: Dividends received | C21: =IFERROR('Cash Flow Data'!J17,0) -> 162 | D21: =IFERROR('Cash Flow Data'!K17,0) -> 317 | E21: =IFERROR('Cash Flow Data'!L17,0) -> 336 | F21: =IFERROR('Cash Flow Data'!M17,0) -> 294 | G21: =IFERROR('Cash Flow Data'!N17,0) -> 408 | H21: 0 | I21: =H21 -> 0 | J21: =I21 -> 0 | K21: =J21 -> 0 | L21: =K21 -> 0
B22: Redemp n Canc of Shares | C22: =IFERROR('Cash Flow Data'!J18,0) -> 1208 | D22: =IFERROR('Cash Flow Data'!K18,0) -> 166 | E22: =IFERROR('Cash Flow Data'!L18,0) -> 123 | F22: =IFERROR('Cash Flow Data'!M18,0) -> 28 | G22: =IFERROR('Cash Flow Data'!N18,0) -> 611 | H22: 0 | I22: =H22 -> 0 | J22: =I22 -> 0 | K22: =J22 -> 0 | L22: =K22 -> 0
B23: Acquisition of companies | C23: =IFERROR('Cash Flow Data'!J19,0) -> -53 | D23: =IFERROR('Cash Flow Data'!K19,0) -> -10569 | E23: =IFERROR('Cash Flow Data'!L19,0) -> 0 | F23: =IFERROR('Cash Flow Data'!M19,0) -> -6 | G23: =IFERROR('Cash Flow Data'!N19,0) -> -2846 | H23: 0 | I23: =H23 -> 0 | J23: =I23 -> 0 | K23: =J23 -> 0 | L23: =K23 -> 0
B24: Inter corporate deposits | C24: =IFERROR('Cash Flow Data'!J20,0) -> 0 | D24: =IFERROR('Cash Flow Data'!K20,0) -> 0 | E24: =IFERROR('Cash Flow Data'!L20,0) -> 0 | F24: =IFERROR('Cash Flow Data'!M20,0) -> 0 | G24: =IFERROR('Cash Flow Data'!N20,0) -> 0 | H24: 0 | I24: =H24 -> 0 | J24: =I24 -> 0 | K24: =J24 -> 0 | L24: =K24 -> 0
B25: Other investing items | C25: =IFERROR('Cash Flow Data'!J21,0) -> -1315 | D25: =IFERROR('Cash Flow Data'!K21,0) -> 609 | E25: =IFERROR('Cash Flow Data'!L21,0) -> -481 | F25: =IFERROR('Cash Flow Data'!M21,0) -> -298 | G25: =IFERROR('Cash Flow Data'!N21,0) -> 472 | H25: ='Balance Sheet'!G11-'Balance Sheet'!H11 -> -70.347607 | I25: ='Balance Sheet'!H11-'Balance Sheet'!I11 -> -57.296788 | J25: ='Balance Sheet'!I11-'Balance Sheet'!J11 -> -62.801836 | K25: ='Balance Sheet'!J11-'Balance Sheet'!K11 -> -68.835806 | L25: ='Balance Sheet'!K11-'Balance Sheet'!L11 -> -75.449517
B26: Cash form Investing Activities | C26: =SUM(C16:C25) -> -10904 | D26: =SUM(D16:D25) -> -18178 | E26: =SUM(E16:E25) -> -14254 | F26: =SUM(F16:F25) -> -13612 | G26: =SUM(G16:G25) -> -14396 | H26: =SUM(H16:H25) -> -20185.146 | I26: =SUM(I16:I25) -> -15358.694 | J26: =SUM(J16:J25) -> -14735.323 | ... L26: =SUM(L16:L25) -> -13753.723
B28: Financing Activities
B29: Proceeds from shares | C29: =IFERROR('Cash Flow Data'!J23,0) -> 326 | D29: =IFERROR('Cash Flow Data'!K23,0) -> 1 | E29: =IFERROR('Cash Flow Data'!L23,0) -> 0 | F29: =IFERROR('Cash Flow Data'!M23,0) -> 0 | G29: =IFERROR('Cash Flow Data'!N23,0) -> 0 | H29: 0 | I29: =H29 -> 0 | J29: =I29 -> 0 | K29: =J29 -> 0 | L29: =K29 -> 0
B30: Proceeds from borrowings | C30: =IFERROR('Cash Flow Data'!J24,0) -> 12439 | D30: =IFERROR('Cash Flow Data'!K24,0) -> 16769 | E30: =IFERROR('Cash Flow Data'!L24,0) -> 14120 | F30: =IFERROR('Cash Flow Data'!M24,0) -> 23893 | G30: =IFERROR('Cash Flow Data'!N24,0) -> 15954 | H30: 0 | I30: =H30 -> 0 | J30: =I30 -> 0 | K30: =J30 -> 0 | L30: =K30 -> 0
B31: Repayment of borrowings | C31: =IFERROR('Cash Flow Data'!J25,0) -> -26360 | D31: =IFERROR('Cash Flow Data'!K25,0) -> -10226 | E31: =IFERROR('Cash Flow Data'!L25,0) -> -11908 | F31: =IFERROR('Cash Flow Data'!M25,0) -> -17627 | G31: =IFERROR('Cash Flow Data'!N25,0) -> -23916 | H31: 0 | I31: =H31 -> 0 | J31: =I31 -> 0 | K31: =J31 -> 0 | L31: =K31 -> 0
B32: Interest paid fin | C32: =IFERROR('Cash Flow Data'!J26,0) -> -4687 | D32: =IFERROR('Cash Flow Data'!K26,0) -> -6120 | E32: =IFERROR('Cash Flow Data'!L26,0) -> -8145 | F32: =IFERROR('Cash Flow Data'!M26,0) -> -8119 | G32: =IFERROR('Cash Flow Data'!N26,0) -> -8066 | H32: 0 | I32: =H32 -> 0 | J32: =I32 -> 0 | K32: =J32 -> 0 | L32: =K32 -> 0
B33: Dividends paid | C33: =IFERROR('Cash Flow Data'!J27,0) -> -3020 | D33: =IFERROR('Cash Flow Data'!K27,0) -> -6293 | E33: =IFERROR('Cash Flow Data'!L27,0) -> -4429 | F33: =IFERROR('Cash Flow Data'!M27,0) -> -4490 | G33: =IFERROR('Cash Flow Data'!N27,0) -> -4490 | H33: =-'Data Sheet >'!$K$31 -> -19430.4 | I33: =-'Data Sheet >'!$K$31 -> -19430.4 | J33: =-'Data Sheet >'!$K$31 -> -19430.4 | K33: =-'Data Sheet >'!$K$31 -> -19430.4 | L33: =-'Data Sheet >'!$K$31 -> -19430.4
B34: Financial liabilities | C34: =IFERROR('Cash Flow Data'!J28,0) -> -1310 | D34: =IFERROR('Cash Flow Data'!K28,0) -> -1114 | E34: =IFERROR('Cash Flow Data'!L28,0) -> -1140 | F34: =IFERROR('Cash Flow Data'!M28,0) -> -971 | G34: =IFERROR('Cash Flow Data'!N28,0) -> -1162 | H34: 0 | I34: =H34 -> 0 | J34: =I34 -> 0 | K34: =J34 -> 0 | L34: =K34 -> 0
B35: Other financing items | C35: =IFERROR('Cash Flow Data'!J29,0) -> -789 | D35: =IFERROR('Cash Flow Data'!K29,0) -> 2 | E35: =IFERROR('Cash Flow Data'!L29,0) -> 404 | F35: =IFERROR('Cash Flow Data'!M29,0) -> 312 | G35: =IFERROR('Cash Flow Data'!N29,0) -> 293 | H35: 0 | I35: =H35 -> 0 | J35: =I35 -> 0 | K35: =J35 -> 0 | L35: =K35 -> 0
B36: Cash form Financing Activities | C36: =SUM(C29:C35) -> -23401 | D36: =SUM(D29:D35) -> -6981 | E36: =SUM(E29:E35) -> -11098 | F36: =SUM(F29:F35) -> -7002 | G36: =SUM(G29:G35) -> -21387 | H36: =SUM(H29:H35) -> -19430.4 | I36: =SUM(I29:I35) -> -19430.4 | J36: =SUM(J29:J35) -> -19430.4 | ... L36: =SUM(L29:L35) -> -19430.4
B38: Net Cash Flow | C38: =SUM(C13,C26,C36) -> 10075 | D38: =SUM(D13,D26,D36) -> -3476 | E38: =SUM(E13,E26,E36) -> -5051 | F38: =SUM(F13,F26,F36) -> 2524 | G38: =SUM(G13,G26,G36) -> -719 | H38: =SUM(H13,H26,H36) -> -11306.216 | I38: =SUM(I13,I26,I36) -> 215.02581 | J38: =SUM(J13,J26,J36) -> 4225.7017 | ... L38: =SUM(L13,L26,L36) -> 12989.532

Sheet Balance Sheet
B2: ="Balance Sheet-"&'Data Sheet >'!B1 -> Balance Sheet-INFOSYS LTD
B3: Year | C3: ='Data Sheet >'!G16 -> 44651 | D3: ='Data Sheet >'!H16 -> 45016 | E3: ='Data Sheet >'!I16 -> 45382 | F3: ='Data Sheet >'!J16 -> 45747 | G3: ='Data Sheet >'!K16 -> 46112 | H3: =G3+365 -> 46477 | I3: =H3+365 -> 46842 | J3: =I3+365 -> 47207 | K3: =J3+365 -> 47572 | L3: =K3+365 -> 47937
B5: Equity Share Capital | C5: =IFERROR('Data Sheet >'!G57,0) -> 2098 | D5: =IFERROR('Data Sheet >'!H57,0) -> 2069 | E5: =IFERROR('Data Sheet >'!I57,0) -> 2071 | F5: =IFERROR('Data Sheet >'!J57,0) -> 2073 | G5: =IFERROR('Data Sheet >'!K57,0) -> 2024 | H5: =G5 -> 2024 | I5: =H5 -> 2024 | J5: =I5 -> 2024 | K5: =J5 -> 2024 | L5: =K5 -> 2024
B6: Reserves | C6: =IFERROR('Data Sheet >'!G58,0) -> 73252 | D6: =IFERROR('Data Sheet >'!H58,0) -> 73338 | E6: =IFERROR('Data Sheet >'!I58,0) -> 86045 | F6: =IFERROR('Data Sheet >'!J58,0) -> 93745 | G6: =IFERROR('Data Sheet >'!K58,0) -> 90828 | H6: ='Warking '!H6 -> 100260.51 | I6: ='Warking '!I6 -> 112490.29 | J6: ='Warking '!J6 -> 127786.09 | K6: ='Warking '!K6 -> 146442.48 | L6: ='Warking '!L6 -> 168782.37
B7: Borrowings | C7: =IFERROR('Data Sheet >'!G59,0) -> 5474 | D7: =IFERROR('Data Sheet >'!H59,0) -> 8299 | E7: =IFERROR('Data Sheet >'!I59,0) -> 8359 | F7: =IFERROR('Data Sheet >'!J59,0) -> 8227 | G7: =IFERROR('Data Sheet >'!K59,0) -> 9176 | H7: =G7 -> 9176 | I7: =H7 -> 9176 | J7: =I7 -> 9176 | K7: =J7 -> 9176 | L7: =K7 -> 9176
B8: Other Liabilities | C8: =IFERROR('Data Sheet >'!G60,0) -> 35905 | D8: =IFERROR('Data Sheet >'!H60,0) -> 40890 | E8: =IFERROR('Data Sheet >'!I60,0) -> 39545 | F8: =IFERROR('Data Sheet >'!J60,0) -> 43750 | G8: =IFERROR('Data Sheet >'!K60,0) -> 52260 | H8: ='Warking '!H8 -> 54517.235 | I8: ='Warking '!I8 -> 59755.225 | J8: ='Warking '!J8 -> 65496.478 | K8: ='Warking '!K8 -> 71789.347 | L8: ='Warking '!L8 -> 78686.833
B9: Total Liabilitis | C9: =SUM(C5:C8) -> 116729 | D9: =SUM(D5:D8) -> 124596 | E9: =SUM(E5:E8) -> 136020 | F9: =SUM(F5:F8) -> 147795 | G9: =SUM(G5:G8) -> 154288 | H9: =SUM(H5:H8) -> 165977.75 | I9: =SUM(I5:I8) -> 183445.51 | J9: =SUM(J5:J8) -> 204482.56 | ... L9: =SUM(L5:L8) -> 258669.2
B10: Net Block | C10: =IFERROR('Data Sheet >'!G62,0) -> 25800 | D10: =IFERROR('Data Sheet >'!H62,0) -> 29225 | E10: =IFERROR('Data Sheet >'!I62,0) -> 27622 | F10: =IFERROR('Data Sheet >'!J62,0) -> 30961 | G10: =IFERROR('Data Sheet >'!K62,0) -> 33770 | H10: ='Dep Capex'!H13 -> 41626.397 | I10: ='Dep Capex'!I13 -> 47978.284 | J10: ='Dep Capex'!J13 -> 52841.43 | K10: ='Dep Capex'!K13 -> 56221.742 | L10: ='Dep Capex'!L13 -> 58115.127
B11: Capital Work in Progress | C11: =IFERROR('Data Sheet >'!G63,0) -> 416 | D11: =IFERROR('Data Sheet >'!H63,0) -> 288 | E11: =IFERROR('Data Sheet >'!I63,0) -> 293 | F11: =IFERROR('Data Sheet >'!J63,0) -> 814 | G11: =IFERROR('Data Sheet >'!K63,0) -> 526 | H11: ='Warking '!H12 -> 596.34761 | I11: ='Warking '!I12 -> 653.6444 | J11: ='Warking '!J12 -> 716.44623 | K11: ='Warking '!K12 -> 785.28204 | L11: ='Warking '!L12 -> 860.73155
B12: Investments | C12: =IFERROR('Data Sheet >'!G64,0) -> 20324 | D12: =IFERROR('Data Sheet >'!H64,0) -> 19478 | E12: =IFERROR('Data Sheet >'!I64,0) -> 24623 | F12: =IFERROR('Data Sheet >'!J64,0) -> 23541 | G12: =IFERROR('Data Sheet >'!K64,0) -> 21880 | H12: ='Warking '!H16 -> 28468.891 | I12: ='Warking '!I16 -> 31204.169 | J12: ='Warking '!J16 -> 34202.25 | K12: ='Warking '!K16 -> 37488.386 | L12: ='Warking '!L16 -> 41090.251
B13: Other Assets | C13: =IFERROR('Data Sheet >'!G65-(SUM('Data Sheet >'!G67:G69)),0) -> 30019 | D13: =IFERROR('Data Sheet >'!H65-(SUM('Data Sheet >'!H67:H69)),0) -> 38008 | E13: =IFERROR('Data Sheet >'!I65-(SUM('Data Sheet >'!I67:I69)),0) -> 38503 | F13: =IFERROR('Data Sheet >'!J65-(SUM('Data Sheet >'!J67:J69)),0) -> 36866 | G13: =IFERROR('Data Sheet >'!K65-(SUM('Data Sheet >'!K67:K69)),0) -> 40677 | H13: ='Warking '!H20 -> 47394.377 | I13: ='Warking '!I20 -> 51948.005 | J13: ='Warking '!J20 -> 56939.144 | K13: ='Warking '!K20 -> 62409.83 | L13: ='Warking '!L20 -> 68406.136
B14: Total Non Current Assets | C14: =SUM(C10:C13) -> 76559 | D14: =SUM(D10:D13) -> 86999 | E14: =SUM(E10:E13) -> 91041 | F14: =SUM(F10:F13) -> 92182 | G14: =SUM(G10:G13) -> 96853 | H14: =SUM(H10:H13) -> 118086.01 | I14: =SUM(I10:I13) -> 131784.1 | J14: =SUM(J10:J13) -> 144699.27 | ... L14: =SUM(L10:L13) -> 168472.25
B15: Receivables | C15: =IFERROR('Data Sheet >'!G67,0) -> 22698 | D15: =IFERROR('Data Sheet >'!H67,0) -> 25424 | E15: =IFERROR('Data Sheet >'!I67,0) -> 30193 | F15: =IFERROR('Data Sheet >'!J67,0) -> 31158 | G15: =IFERROR('Data Sheet >'!K67,0) -> 35234 | H15: ='Warking '!H24 -> 36996.954 | I15: ='Warking '!I24 -> 40551.603 | J15: ='Warking '!J24 -> 44447.781 | K15: ='Warking '!K24 -> 48718.302 | L15: ='Warking '!L24 -> 53399.133
B16: Inventory | C16: =IFERROR('Data Sheet >'!G68,0) -> 0 | D16: =IFERROR('Data Sheet >'!H68,0) -> 0 | E16: =IFERROR('Data Sheet >'!I68,0) -> 0 | F16: =IFERROR('Data Sheet >'!J68,0) -> 0 | G16: =IFERROR('Data Sheet >'!K68,0) -> 0 | H16: =G16 -> 0 | I16: =H16 -> 0 | J16: =I16 -> 0 | K16: =J16 -> 0 | L16: =K16 -> 0
B17: Cash & Bank | C17: =IFERROR('Data Sheet >'!G69,0) -> 17472 | D17: =IFERROR('Data Sheet >'!H69,0) -> 12173 | E17: =IFERROR('Data Sheet >'!I69,0) -> 14786 | F17: =IFERROR('Data Sheet >'!J69,0) -> 24455 | G17: =IFERROR('Data Sheet >'!K69,0) -> 22201 | H17: ='Warking '!H30 -> 10894.784 | I17: ='Warking '!I30 -> 11109.81 | J17: ='Warking '!J30 -> 15335.512 | K17: ='Warking '!K30 -> 23808.288 | L17: ='Warking '!L30 -> 36797.82
B18: Total Current Assets | C18: =SUM(C15:C17) -> 40170 | D18: =SUM(D15:D17) -> 37597 | E18: =SUM(E15:E17) -> 44979 | F18: =SUM(F15:F17) -> 55613 | G18: =SUM(G15:G17) -> 57435 | H18: =SUM(H15:H17) -> 47891.738 | I18: =SUM(I15:I17) -> 51661.413 | J18: =SUM(J15:J17) -> 59783.293 | ... L18: =SUM(L15:L17) -> 90196.953
B20: Total Assets | C20: =C14+C18 -> 116729 | D20: =D14+D18 -> 124596 | E20: =E14+E18 -> 136020 | F20: =F14+F18 -> 147795 | G20: =G14+G18 -> 154288 | H20: =H14+H18 -> 165977.75 | I20: =I14+I18 -> 183445.51 | J20: =J14+J18 -> 204482.56 | ... L20: =L14+L18 -> 258669.2
B22: Check | C22: =C9=C20 -> TRUE | D22: =D9=D20 -> TRUE | E22: =E9=E20 -> TRUE | F22: =F9=F20 -> TRUE | G22: =G9=G20 -> TRUE | H22: =H9=H20 -> TRUE | I22: =I9=I20 -> TRUE | J22: =J9=J20 -> TRUE | ... L22: =L9=L20 -> TRUE

Sheet Income Statement 
B2: ="Income Statement-"&'Data Sheet >'!B1 -> Income Statement-INFOSYS LTD
B3: Year | C3: ='Data Sheet >'!G16 -> 44651 | D3: ='Data Sheet >'!H16 -> 45016 | E3: ='Data Sheet >'!I16 -> 45382 | F3: ='Data Sheet >'!J16 -> 45747 | G3: ='Data Sheet >'!K16 -> 46112 | H3: =G3+365 -> 46477 | I3: =H3+365 -> 46842 | J3: =I3+365 -> 47207 | K3: =J3+365 -> 47572 | L3: =K3+365 -> 47937
B5: Sales | C5: =IFERROR('Data Sheet >'!G17,0) -> 121641 | D5: =IFERROR('Data Sheet >'!H17,0) -> 146767 | E5: =IFERROR('Data Sheet >'!I17,0) -> 153670 | F5: =IFERROR('Data Sheet >'!J17,0) -> 162990 | G5: =IFERROR('Data Sheet >'!K17,0) -> 178650 | H5: =G5*(1+G6) -> 195814.61 | I5: =H5*(1+H6) -> 214628.38 | J5: =I5*(1+I6) -> 235249.77 | K5: =J5*(1+J6) -> 257852.45 | L5: =K5*(1+K6) -> 282626.79
B6: Sales Growth | D6: =D5/C5-1 -> 0.20655864 | E6: =E5/D5-1 -> 0.047033734 | F6: =F5/E5-1 -> 0.060649444 | G6: =G5/F5-1 -> 0.096079514 | H6: =H5/G5-1 -> 0.096079514 | I6: =I5/H5-1 -> 0.096079514 | J6: =J5/I5-1 -> 0.096079514 | K6: =K5/J5-1 -> 0.096079514 | L6: =L5/K5-1 -> 0.096079514
B8: COGS | C8: =IFERROR(SUM('Data Sheet >'!G20,'Data Sheet >'!G21),0) -> 20822 | D8: =IFERROR(SUM('Data Sheet >'!H20,'Data Sheet >'!H21),0) -> 26506 | E8: =IFERROR(SUM('Data Sheet >'!I20,'Data Sheet >'!I21),0) -> 27394 | F8: =IFERROR(SUM('Data Sheet >'!J20,'Data Sheet >'!J21),0) -> 30617 | G8: =IFERROR(SUM('Data Sheet >'!K20,'Data Sheet >'!K21),0) -> 33145 | H8: =H5*H9 -> 35380.424 | I8: =I5*I9 -> 38779.758 | J8: =J5*J9 -> 42505.699 | K8: =K5*K9 -> 46589.625 | L8: =L5*L9 -> 51065.934
B9: COGS % Sales | C9: =C8/C5 -> 0.17117584 | D9: =D8/D5 -> 0.18059918 | E9: =E8/E5 -> 0.17826511 | F9: =F8/F5 -> 0.18784588 | G9: =G8/G5 -> 0.18553037 | H9: =AVERAGE($C$9:$G$9) -> 0.18068328 | I9: =AVERAGE($C$9:$G$9) -> 0.18068328 | J9: =AVERAGE($C$9:$G$9) -> 0.18068328 | K9: =AVERAGE($C$9:$G$9) -> 0.18068328 | L9: =AVERAGE($C$9:$G$9) -> 0.18068328
B11: Gross Profit | C11: =C5-C8 -> 100819 | D11: =D5-D8 -> 120261 | E11: =E5-E8 -> 126276 | F11: =F5-F8 -> 132373 | G11: =G5-G8 -> 145505 | H11: =H5-H8 -> 160434.18 | I11: =I5-I8 -> 175848.62 | J11: =J5-J8 -> 192744.07 | ... L11: =L5-L8 -> 231560.85
B12: Gross Margin | C12: =C11/C5 -> 0.82882416 | D12: =D11/D5 -> 0.81940082 | E12: =E11/E5 -> 0.82173489 | F12: =F11/F5 -> 0.81215412 | G12: =G11/G5 -> 0.81446963 | H12: =H11/H5 -> 0.81931672 | I12: =I11/I5 -> 0.81931672 | J12: =J11/J5 -> 0.81931672 | ... L12: =L11/L5 -> 0.81931672
B14: Selling & Other Expenses | C14: =IFERROR(SUM('Data Sheet >'!G22:G24),0) -> 69328 | D14: =IFERROR(SUM('Data Sheet >'!H22:H24),0) -> 85131 | E14: =IFERROR(SUM('Data Sheet >'!I22:I24),0) -> 89851 | F14: =IFERROR(SUM('Data Sheet >'!J22:J24),0) -> 93137 | G14: =IFERROR(SUM('Data Sheet >'!K22:K24),0) -> 103225 | H14: =H5*(G14/G5) -> 113142.81 | I14: =I5*(H14/H5) -> 124013.51 | J14: =J5*(I14/I5) -> 135928.67 | K14: =K5*(J14/J5) -> 148988.63 | L14: =L5*(K14/K5) -> 163303.39
B15: S & G % Sales | C15: =C14/C5 -> 0.56993941 | D15: =D14/D5 -> 0.58004184 | E15: =E14/E5 -> 0.58470098 | F15: =F14/F5 -> 0.57142769 | G15: =G14/G5 -> 0.57780577 | H15: =H14/H5 -> 0.57780577 | I15: =I14/I5 -> 0.57780577 | J15: =J14/J5 -> 0.57780577 | ... L15: =L14/L5 -> 0.57780577
B17: EBITDA | C17: =C11-C14 -> 31491 | D17: =D11-D14 -> 35130 | E17: =E11-E14 -> 36425 | F17: =F11-F14 -> 39236 | G17: =G11-G14 -> 42280 | H17: =H11-H14 -> 47291.373 | I17: =I11-I14 -> 51835.105 | J17: =J11-J14 -> 56815.397 | ... L17: =L11-L14 -> 68257.467
B18: EBITDA % Sales | C18: =C17/C5 -> 0.25888475 | D18: =D17/D5 -> 0.23935898 | E18: =E17/E5 -> 0.2370339 | F18: =F17/F5 -> 0.24072642 | G18: =G17/G5 -> 0.23666387 | H18: =H17/H5 -> 0.24151096 | I18: =I17/I5 -> 0.24151096 | J18: =J17/J5 -> 0.24151096 | ... L18: =L17/L5 -> 0.24151096
B20: Depreciation | C20: =IFERROR('Data Sheet >'!G26,0) -> 3476 | D20: =IFERROR('Data Sheet >'!H26,0) -> 4225 | E20: =IFERROR('Data Sheet >'!I26,0) -> 4678 | F20: =IFERROR('Data Sheet >'!J26,0) -> 4812 | G20: =IFERROR('Data Sheet >'!K26,0) -> 4902 | H20: =H5*H21 -> 5669.5097 | I20: =I5*I21 -> 6214.2334 | J20: =J5*J21 -> 6811.2939 | K20: =K5*K21 -> 7465.7197 | L20: =L5*L21 -> 8183.0225
B21: Depreciation % Sales | C21: =C20/C5 -> 0.028575891 | D21: =D20/D5 -> 0.028787125 | E21: =E20/E5 -> 0.030441856 | F21: =F20/F5 -> 0.029523284 | G21: =G20/G5 -> 0.027439127 | H21: =AVERAGE(C21:G21) -> 0.028953457 | I21: =H21 -> 0.028953457 | J21: =I21 -> 0.028953457 | K21: =J21 -> 0.028953457 | L21: =K21 -> 0.028953457
B23: EBIT | C23: =C17-C20 -> 28015 | D23: =D17-D20 -> 30905 | E23: =E17-E20 -> 31747 | F23: =F17-F20 -> 34424 | G23: =G17-G20 -> 37378 | H23: =H17-H20 -> 41621.863 | I23: =I17-I20 -> 45620.872 | J23: =J17-J20 -> 50004.103 | ... L23: =L17-L20 -> 60074.444
B24: EBIT % of Sale | C24: =C23/C5 -> 0.23030886 | D24: =D23/D5 -> 0.21057186 | E24: =E23/E5 -> 0.20659205 | F24: =F23/F5 -> 0.21120314 | G24: =G23/G5 -> 0.20922474 | H24: =H23/H5 -> 0.2125575 | I24: =I23/I5 -> 0.2125575 | J24: =J23/J5 -> 0.2125575 | ... L24: =L23/L5 -> 0.2125575
B26: Interest | C26: =IFERROR('Data Sheet >'!G27,0) -> 200 | D26: =IFERROR('Data Sheet >'!H27,0) -> 284 | E26: =IFERROR('Data Sheet >'!I27,0) -> 470 | F26: =IFERROR('Data Sheet >'!J27,0) -> 416 | G26: =IFERROR('Data Sheet >'!K27,0) -> 416 | H26: =AVERAGE('Data Sheet >'!G59:K59)*4.54% -> 358.9778 | I26: =H26 -> 358.9778 | J26: =I26 -> 358.9778 | K26: =J26 -> 358.9778 | L26: =K26 -> 358.9778
B27: Interest of Sale | C27: =C26/C5 -> 0.0016441825 | D27: =D26/D5 -> 0.0019350399 | E27: =E26/E5 -> 0.003058502 | F27: =F26/F5 -> 0.0025523038 | G27: =G26/G5 -> 0.0023285754 | H27: =H26/H5 -> 0.0018332534 | I27: =I26/I5 -> 0.0016725552 | J27: =J26/J5 -> 0.0015259433 | ... L27: =L26/L5 -> 0.0012701478
B29: EBT | C29: =C23-C26 -> 27815 | D29: =D23-D26 -> 30621 | E29: =E23-E26 -> 31277 | F29: =F23-F26 -> 34008 | G29: =G23-G26 -> 36962 | H29: =H23-H26 -> 41262.886 | I29: =I23-I26 -> 45261.894 | J29: =J23-J26 -> 49645.125 | ... L29: =L23-L26 -> 59715.467
B30: EBT % of sale | C30: =C29/C5 -> 0.22866468 | D30: =D29/D5 -> 0.20863682 | E30: =E29/E5 -> 0.20353355 | F30: =F29/F5 -> 0.20865084 | G30: =G29/G5 -> 0.20689617 | H30: =H29/H5 -> 0.21072425 | I30: =I29/I5 -> 0.21088495 | J30: =J29/J5 -> 0.21103156 | ... L30: =L29/L5 -> 0.21128735
B32: Tax | C32: =IFERROR('Data Sheet >'!G29,0) -> 7964 | D32: =IFERROR('Data Sheet >'!H29,0) -> 9214 | E32: =IFERROR('Data Sheet >'!I29,0) -> 9740 | F32: =IFERROR('Data Sheet >'!J29,0) -> 10858 | G32: =IFERROR('Data Sheet >'!K29,0) -> 10521 | H32: =H29*H33 -> 12399.971 | I32: =I29*I33 -> 13601.719 | J32: =J29*J33 -> 14918.93 | K32: =K29*K33 -> 16362.698 | L32: =L29*L33 -> 17945.183
B33: Effective Tax Rate | C33: =C32/C29 -> 0.28632033 | D33: =D32/D29 -> 0.30090461 | E33: =E32/E29 -> 0.31141094 | F33: =F32/F29 -> 0.31927782 | G33: =G32/G29 -> 0.28464369 | H33: =AVERAGE(C33:G33) -> 0.30051148 | I33: =H33 -> 0.30051148 | J33: =I33 -> 0.30051148 | K33: =J33 -> 0.30051148 | L33: =K33 -> 0.30051148
B35: Net Profit | C35: =C29-C32 -> 19851 | D35: =D29-D32 -> 21407 | E35: =E29-E32 -> 21537 | F35: =F29-F32 -> 23150 | G35: =G29-G32 -> 26441 | H35: =H29-H32 -> 28862.915 | I35: =I29-I32 -> 31660.175 | J35: =J29-J32 -> 34726.195 | ... L35: =L29-L32 -> 41770.284
B36: Net Profit Margin | C36: =C35/C5 -> 0.16319333 | D36: =D35/D5 -> 0.14585704 | E36: =E35/E5 -> 0.14015097 | F36: =F35/F5 -> 0.14203325 | G36: =G35/G5 -> 0.14800448 | H36: =H35/H5 -> 0.14739919 | I36: =I35/I5 -> 0.1475116 | J36: =J35/J5 -> 0.14761415 | ... L36: =L35/L5 -> 0.14779308
B38: No. of Equity Share | C38: =IFERROR('Data Sheet >'!G93,0) -> 420.67 | D38: =IFERROR('Data Sheet >'!H93,0) -> 414.86 | E38: =IFERROR('Data Sheet >'!I93,0) -> 415.09 | F38: =IFERROR('Data Sheet >'!J93,0) -> 415.33 | G38: =IFERROR('Data Sheet >'!K93,0) -> 405.56 | H38: =G38 -> 405.56 | I38: =H38 -> 405.56 | J38: =I38 -> 405.56 | K38: =J38 -> 405.56 | L38: =K38 -> 405.56
B40: Earning Per Share | C40: =C35/C38 -> 47.189008 | D40: =D35/D38 -> 51.60054 | E40: =E35/E38 -> 51.885133 | F40: =F35/F38 -> 55.73881 | G40: =G35/G38 -> 65.196272 | H40: =H35/H38 -> 71.168051 | I40: =I35/I38 -> 78.06533 | J40: =J35/J38 -> 85.625297 | ... L40: =L35/L38 -> 102.99409
B41: EPS Growth | D41: =D40/C40-1 -> 0.093486431 | E41: =E40/D40-1 -> 0.0055153183 | F41: =F40/E40-1 -> 0.074273236 | G41: =G40/F40-1 -> 0.16967463 | H41: =H40/G40-1 -> 0.091596948 | I41: =I40/H40-1 -> 0.096915384 | J41: =J40/I40-1 -> 0.096841533 | K41: =K40/J40-1 -> 0.096774253 | L41: =L40/K40-1 -> 0.096712953
B43: Dividend Per Share | C43: =IFERROR('Data Sheet >'!G31/'Income Statement '!C38,0) -> 30.92115 | D43: =IFERROR('Data Sheet >'!H31/'Income Statement '!D38,0) -> 33.913127 | E43: =IFERROR('Data Sheet >'!I31/'Income Statement '!E38,0) -> 45.901371 | F43: =IFERROR('Data Sheet >'!J31/'Income Statement '!F38,0) -> 42.924422 | G43: =IFERROR('Data Sheet >'!$K$31/'Income Statement '!G38,0) -> 47.91005 | H43: =IFERROR('Data Sheet >'!$K$31/'Income Statement '!H38,0) -> 47.91005 | I43: =IFERROR('Data Sheet >'!$K$31/'Income Statement '!I38,0) -> 47.91005 | J43: =IFERROR('Data Sheet >'!$K$31/'Income Statement '!J38,0) -> 47.91005 | K43: =IFERROR('Data Sheet >'!$K$31/'Income Statement '!K38,0) -> 47.91005 | L43: =IFERROR('Data Sheet >'!$K$31/'Income Statement '!L38,0) -> 47.91005
B44: Divivend Payout Ratio | C44: =C43/C40 -> 0.6552617 | D44: =D43/D40 -> 0.65722427 | E44: =E43/E40 -> 0.88467289 | F44: =F43/F40 -> 0.77009935 | G44: =G43/G40 -> 0.73485874 | H44: =H43/H40 -> 0.67319604 | I44: =I43/I40 -> 0.61371738 | J44: =J43/J40 -> 0.5595315 | ... L44: =L43/L40 -> 0.46517281
B46: Retain Earning | C46: =C40-C43 -> 16.267858 | D46: =D40-D43 -> 17.687413 | E46: =E40-E43 -> 5.9837626 | F46: =F40-F43 -> 12.814389 | G46: =G40-G43 -> 17.286222 | H46: =H40-H43 -> 23.258001 | I46: =I40-I43 -> 30.15528 | J46: =J40-J43 -> 37.715246 | ... L46: =L40-L43 -> 55.084041

Sheet Dep Capex
B2: Year | C2: ='Income Statement '!C3 -> 44651 | D2: ='Income Statement '!D3 -> 45016 | E2: ='Income Statement '!E3 -> 45382 | F2: ='Income Statement '!F3 -> 45747 | G2: ='Income Statement '!G3 -> 46112 | H2: ='Income Statement '!H3 -> 46477 | I2: ='Income Statement '!I3 -> 46842 | J2: ='Income Statement '!J3 -> 47207 | ... L2: ='Income Statement '!L3 -> 47937
B4: Revenue | C4: ='Income Statement '!C5 -> 121641 | D4: ='Income Statement '!D5 -> 146767 | E4: ='Income Statement '!E5 -> 153670 | F4: ='Income Statement '!F5 -> 162990 | G4: ='Income Statement '!G5 -> 178650 | H4: ='Income Statement '!H5 -> 195814.61 | I4: ='Income Statement '!I5 -> 214628.38 | J4: ='Income Statement '!J5 -> 235249.77 | ... L4: ='Income Statement '!L5 -> 282626.79
B6: Depreciation | C6: ='Income Statement '!C20 -> 3476 | D6: ='Income Statement '!D20 -> 4225 | E6: ='Income Statement '!E20 -> 4678 | F6: ='Income Statement '!F20 -> 4812 | G6: ='Income Statement '!G20 -> 4902 | H6: ='Income Statement '!H20 -> 5669.5097 | I6: ='Income Statement '!I20 -> 6214.2334 | J6: ='Income Statement '!J20 -> 6811.2939 | ... L6: ='Income Statement '!L20 -> 8183.0225
B7: Depreciation as % of Revenue | C7: ='Income Statement '!C21 -> 0.028575891 | D7: ='Income Statement '!D21 -> 0.028787125 | E7: ='Income Statement '!E21 -> 0.030441856 | F7: ='Income Statement '!F21 -> 0.029523284 | G7: ='Income Statement '!G21 -> 0.027439127 | H7: ='Income Statement '!H21 -> 0.028953457 | I7: ='Income Statement '!I21 -> 0.028953457 | J7: ='Income Statement '!J21 -> 0.028953457 | ... L7: ='Income Statement '!L21 -> 0.028953457
B9: Net Block | H9: ='Balance Sheet'!G10 -> 33770 | I9: =H13 -> 41626.397 | J9: =I13 -> 47978.284 | K9: =J13 -> 52841.43 | L9: =K13 -> 56221.742
B10: Capital Expenditure | C10: =-'Cash Flow Data'!J12 -> 10522 | D10: =-'Cash Flow Data'!K12 -> 14142 | E10: =-'Cash Flow Data'!L12 -> 18207 | F10: =-'Cash Flow Data'!M12 -> 15671 | G10: =-'Cash Flow Data'!N12 -> 14559 | H10: =G10*(1+G11) -> 13525.907 | I10: =H10*(1+H11) -> 12566.12 | J10: =I10*(1+I11) -> 11674.44 | K10: =J10*(1+J11) -> 10846.032 | L10: =K10*(1+K11) -> 10076.408
B11: Capital Expenditure growth | D11: ='Cash Flow Data'!K12/'Cash Flow Data'!J12-1 -> 0.34404106 | E11: ='Cash Flow Data'!L12/'Cash Flow Data'!K12-1 -> 0.28744166 | F11: ='Cash Flow Data'!M12/'Cash Flow Data'!L12-1 -> -0.13928709 | G11: ='Cash Flow Data'!N12/'Cash Flow Data'!M12-1 -> -0.070959096 | H11: =H10/G10-1 -> -0.070959096 | I11: =I10/H10-1 -> -0.070959096 | J11: =J10/I10-1 -> -0.070959096 | K11: =K10/J10-1 -> -0.070959096 | L11: =L10/K10-1 -> -0.070959096
B12: Depreciation | C12: =C6 -> 3476 | D12: =D6 -> 4225 | E12: =E6 -> 4678 | F12: =F6 -> 4812 | G12: =G6 -> 4902 | H12: =H6 -> 5669.5097 | I12: =I6 -> 6214.2334 | J12: =J6 -> 6811.2939 | ... L12: =L6 -> 8183.0225
B13: Net BLOCK | H13: =H9+H10-H12 -> 41626.397 | I13: =I9+I10-I12 -> 47978.284 | J13: =J9+J10-J12 -> 52841.43 | K13: =K9+K10-K12 -> 56221.742 | L13: =L9+L10-L12 -> 58115.127

Sheet Warking 
B2: Year | C2: ='Income Statement '!C3 -> 44651 | D2: ='Income Statement '!D3 -> 45016 | E2: ='Income Statement '!E3 -> 45382 | F2: ='Income Statement '!F3 -> 45747 | G2: ='Income Statement '!G3 -> 46112 | H2: ='Income Statement '!H3 -> 46477 | I2: ='Income Statement '!I3 -> 46842 | J2: ='Income Statement '!J3 -> 47207 | ... L2: ='Income Statement '!L3 -> 47937
B4: ='Income Statement '!B5 -> Sales | C4: ='Income Statement '!C5 -> 121641 | D4: ='Income Statement '!D5 -> 146767 | E4: ='Income Statement '!E5 -> 153670 | F4: ='Income Statement '!F5 -> 162990 | G4: ='Income Statement '!G5 -> 178650 | H4: ='Income Statement '!H5 -> 195814.61 | I4: ='Income Statement '!I5 -> 214628.38 | ... L4: ='Income Statement '!L5 -> 282626.79
B6: Reserves | C6: ='Balance Sheet'!C6 -> 73252 | D6: ='Balance Sheet'!D6 -> 73338 | E6: ='Balance Sheet'!E6 -> 86045 | F6: ='Balance Sheet'!F6 -> 93745 | G6: ='Balance Sheet'!G6 -> 90828 | H6: =G6+'Income Statement '!H35-'Data Sheet >'!$K$31 -> 100260.51 | I6: =H6+'Income Statement '!I35-'Data Sheet >'!$K$31 -> 112490.29 | J6: =I6+'Income Statement '!J35-'Data Sheet >'!$K$31 -> 127786.09 | K6: =J6+'Income Statement '!K35-'Data Sheet >'!$K$31 -> 146442.48 | L6: =K6+'Income Statement '!L35-'Data Sheet >'!$K$31 -> 168782.37
B8: Other Liabilities | C8: ='Balance Sheet'!C8 -> 35905 | D8: ='Balance Sheet'!D8 -> 40890 | E8: ='Balance Sheet'!E8 -> 39545 | F8: ='Balance Sheet'!F8 -> 43750 | G8: ='Balance Sheet'!G8 -> 52260 | H8: =H4*$G$10 -> 54517.235 | I8: =I4*$G$10 -> 59755.225 | J8: =J4*$G$10 -> 65496.478 | K8: =K4*$G$10 -> 71789.347 | L8: =L4*$G$10 -> 78686.833
B9: Other Liabilities % of Revenue | C9: =C8/C4 -> 0.29517186 | D9: =D8/D4 -> 0.27860486 | E9: =E8/E4 -> 0.25733715 | F9: =F8/F4 -> 0.26842138 | G9: =G8/G4 -> 0.29252729 | H9: =H8/H4 -> 0.27841251 | I9: =I8/I4 -> 0.27841251 | J9: =J8/J4 -> 0.27841251 | ... L9: =L8/L4 -> 0.27841251
B10: Other Liabilities % of Revenue Average | G10: =AVERAGE(C9:G9) -> 0.27841251
B12: Capital Work in Progress | C12: ='Balance Sheet'!C11 -> 416 | D12: ='Balance Sheet'!D11 -> 288 | E12: ='Balance Sheet'!E11 -> 293 | F12: ='Balance Sheet'!F11 -> 814 | G12: ='Balance Sheet'!G11 -> 526 | H12: =H4*$G$14 -> 596.34761 | I12: =I4*$G$14 -> 653.6444 | J12: =J4*$G$14 -> 716.44623 | K12: =K4*$G$14 -> 785.28204 | L12: =L4*$G$14 -> 860.73155
B13: CWIP % Revenue | C13: =C12/C4 -> 0.0034198995 | D13: =D12/D4 -> 0.001962294 | E13: =E12/E4 -> 0.0019066832 | F13: =F12/F4 -> 0.0049941714 | G13: =G12/G4 -> 0.0029443045 | H13: =H12/H4 -> 0.0030454705 | I13: =I12/I4 -> 0.0030454705 | J13: =J12/J4 -> 0.0030454705 | ... L13: =L12/L4 -> 0.0030454705
B14: CWIP % Revenue Average | G14: =AVERAGE(C13:G13) -> 0.0030454705
B16: Investments | C16: ='Balance Sheet'!C12 -> 20324 | D16: ='Balance Sheet'!D12 -> 19478 | E16: ='Balance Sheet'!E12 -> 24623 | F16: ='Balance Sheet'!F12 -> 23541 | G16: ='Balance Sheet'!G12 -> 21880 | H16: =H4*$G$18 -> 28468.891 | I16: =I4*$G$18 -> 31204.169 | J16: =J4*$G$18 -> 34202.25 | K16: =K4*$G$18 -> 37488.386 | L16: =L4*$G$18 -> 41090.251
B17: Investments % Revenue | C17: =C16/C4 -> 0.16708182 | D17: =D16/D4 -> 0.13271376 | E17: =E16/E4 -> 0.16023297 | F17: =F16/F4 -> 0.14443217 | G17: =G16/G4 -> 0.12247411 | H17: =H16/H4 -> 0.14538697 | I17: =I16/I4 -> 0.14538697 | J17: =J16/J4 -> 0.14538697 | ... L17: =L16/L4 -> 0.14538697
B18: Investments % Revenue Average | G18: =AVERAGE(C17:G17) -> 0.14538697
B20: Other Assets | C20: ='Balance Sheet'!C13 -> 30019 | D20: ='Balance Sheet'!D13 -> 38008 | E20: ='Balance Sheet'!E13 -> 38503 | F20: ='Balance Sheet'!F13 -> 36866 | G20: ='Balance Sheet'!G13 -> 40677 | H20: =H4*$G$22 -> 47394.377 | I20: =I4*$G$22 -> 51948.005 | J20: =J4*$G$22 -> 56939.144 | K20: =K4*$G$22 -> 62409.83 | L20: =L4*$G$22 -> 68406.136
B21: Other Assets % Revenue | C21: =C20/C4 -> 0.24678357 | D21: =D20/D4 -> 0.2589683 | E21: =E20/E4 -> 0.25055639 | F21: =F20/F4 -> 0.22618566 | G21: =G20/G4 -> 0.22769102 | H21: =H20/H4 -> 0.24203698 | I21: =I20/I4 -> 0.24203698 | J21: =J20/J4 -> 0.24203698 | ... L21: =L20/L4 -> 0.24203698
B22: Other Assets % Revenue Average | G22: =AVERAGE(C21:G21) -> 0.24203698
B24: Receivables | C24: ='Balance Sheet'!C15 -> 22698 | D24: ='Balance Sheet'!D15 -> 25424 | E24: ='Balance Sheet'!E15 -> 30193 | F24: ='Balance Sheet'!F15 -> 31158 | G24: ='Balance Sheet'!G15 -> 35234 | H24: =(H4*$G$26)/365 -> 36996.954 | I24: =(I4*$G$26)/365 -> 40551.603 | J24: =(J4*$G$26)/365 -> 44447.781 | K24: =(K4*$G$26)/365 -> 48718.302 | L24: =(L4*$G$26)/365 -> 53399.133
B25: DSO | C25: =(C24/C4)*365 -> 68.108368 | D25: =(D24/D4)*365 -> 63.227837 | E25: =(E24/E4)*365 -> 71.715006 | F25: =(F24/F4)*365 -> 69.775262 | G25: =(G24/G4)*365 -> 71.986622 | H25: =(H24/H4)*365 -> 68.962619 | I25: =(I24/I4)*365 -> 68.962619 | J25: =(J24/J4)*365 -> 68.962619 | ... L25: =(L24/L4)*365 -> 68.962619
B26: DSO Average | G26: =AVERAGE(C25:G25) -> 68.962619
B28: Cash & Bank | H28: =G30 -> 22201 | I28: =H30 -> 10894.784 | J28: =I30 -> 11109.81 | K28: =J30 -> 15335.512 | L28: =K30 -> 23808.288
B29: Cash Flow | H29: ='Cash Flow '!H38 -> -11306.216 | I29: ='Cash Flow '!I38 -> 215.02581 | J29: ='Cash Flow '!J38 -> 4225.7017 | K29: ='Cash Flow '!K38 -> 8472.7763 | L29: ='Cash Flow '!L38 -> 12989.532
B30: Ending Cash | G30: ='Balance Sheet'!G17 -> 22201 | H30: =SUM(H28:H29) -> 10894.784 | I30: =SUM(I28:I29) -> 11109.81 | J30: =SUM(J28:J29) -> 15335.512 | K30: =SUM(K28:K29) -> 23808.288 | L30: =SUM(L28:L29) -> 36797.82

Sheet Assumption Drivers
B2: FINANCIAL MODEL
B4: FORECASTING ASSUMPTIONS & METHODOLOGY
B6: All figures are in ₹ Crore unless otherwise stated.
B7: 1. INCOME STATEMENT
B8: Revenue
B9: Previous Year Revenue × (1 + Growth Rate) → Forecast Revenue
B10: COGS
B11: Average Historical COGS Margin × Forecast Revenue → Forecast COGS
B12: Selling & Other Expenses
B13: Average Historical Expense-to-Revenue Ratio × Forecast Revenue → Forecast Expense
B14: Depreciation
B15: Average Historical Depreciation-to-Revenue Ratio × Forecast Revenue → Forecast Depreciation
... B74: Cash & Cash Equivalents is derived from the Cash Flow Statement and linked to the Balance Sheet, rather than being used as a balancing plug.

Sheet Data Sheet >
A1: INFOSYS LTD | B1: INFOSYS LTD | E1: =IF(B2<>B3, "A NEW VERSION OF THE WORKSHEET IS AVAILABLE", "")
A2: LATEST VERSION | B2: 2.1 | E2: PLEASE DO NOT MAKE ANY CHANGES TO THIS SHEET
A3: CURRENT VERSION | B3: 2.1
A5: META
A6: Number of shares | B6: =IF(B9>0, B9/B8, 0) -> 406.22571
A7: Face Value | B7: 5
A8: Current Price | B8: 1013.85
A9: Market Capitalization | B9: 411851.94
A15: PROFIT & LOSS
A16: Report Date | B16: 42825 | C16: 43190 | D16: 43555 | E16: 43921 | F16: 44286 | G16: 44651 | H16: 45016 | I16: 45382 | J16: 45747 | K16: 46112
A17: Sales | B17: 68484 | C17: 70522 | D17: 82675 | E17: 90791 | F17: 100472 | G17: 121641 | H17: 146767 | I17: 153670 | J17: 162990 | K17: 178650
A18: Raw Material Cost
A19: Change in Inventory
A20: Power and Fuel | B20: 228 | C20: 207 | D20: 221 | E20: 229 | F20: 143 | G20: 132 | H20: 176 | I20: 199 | J20: 222 | K20: 223
A21: Other Mfr. Exp | B21: 6712 | C21: 7286 | D21: 9902 | E21: 11086 | F21: 12800 | G21: 20690 | H21: 26330 | I21: 27195 | J21: 30395 | K21: 32922
A22: Employee Cost | B22: 37669 | C22: 38902 | D22: 45323 | E22: 50895 | F22: 55547 | G22: 63997 | H22: 78374 | I22: 82636 | J22: 85968 | K22: 95112
A23: Selling and admin | B23: 4584 | C23: 4585 | D23: 5553 | E23: 5375 | F23: 3194 | G23: 4305 | H23: 5300 | I23: 5705 | J23: 6039 | K23: 6784
A24: Other Expenses | B24: 687 | C24: 720 | D24: 1506 | E24: 939 | F24: 899 | G24: 1026 | H24: 1457 | I24: 1510 | J24: 1130 | K24: 1329
A25: Other Income | B25: 3050 | C25: 3311 | D25: 2882 | E25: 2803 | F25: 2201 | G25: 2295 | H25: 2701 | I25: 4711 | J25: 3600 | K25: 3033
A26: Depreciation | B26: 1703 | C26: 1863 | D26: 2011 | E26: 2893 | F26: 3267 | G26: 3476 | H26: 4225 | I26: 4678 | J26: 4812 | K26: 4902
A27: Interest | E27: 170 | F27: 195 | G27: 200 | H27: 284 | I27: 470 | J27: 416 | K27: 416
A28: Profit before tax | B28: 19951 | C28: 20270 | D28: 21041 | E28: 22007 | F28: 26628 | G28: 30110 | H28: 33322 | I28: 35988 | J28: 37608 | K28: 39995
A29: Tax | B29: 5598 | C29: 4241 | D29: 5631 | E29: 5368 | F29: 7205 | G29: 7964 | H29: 9214 | I29: 9740 | J29: 10858 | K29: 10521
A30: Net profit | B30: 14353 | C30: 16029 | D30: 15404 | E30: 16594 | F30: 19351 | G30: 22110 | H30: 24095 | I30: 26233 | J30: 26713 | K30: 29440
A31: Dividend Amount | B31: 5891.6 | C31: 9465.6 | D31: 9222.5 | E31: 7427 | F31: 11469.6 | G31: 13007.6 | H31: 14069.2 | I31: 19053.2 | J31: 17827.8 | K31: 19430.4
A40: Quarters
A41: Report Date | B41: 45382 | C41: 45473 | D41: 45565 | E41: 45657 | F41: 45747 | G41: 45838 | H41: 45930 | I41: 46022 | J41: 46112 | K41: 46203
A42: Sales | B42: 37923 | C42: 39315 | D42: 40986 | E42: 41764 | F42: 40925 | G42: 42279 | H42: 44490 | I42: 45479 | J42: 46402 | K42: 48211
A43: Expenses | B43: 29139 | C43: 29878 | D43: 31177 | E43: 31649 | F43: 31051 | G43: 32336 | H43: 33955 | I43: 34845 | J43: 35235 | K43: 36802
A44: Other Income | B44: 2729 | C44: 838 | D44: 712 | E44: 859 | F44: 1190 | G44: 1042 | H44: 982 | I44: -150 | J44: 1159 | K44: 984
A45: Depreciation | B45: 1163 | C45: 1149 | D45: 1160 | E45: 1203 | F45: 1299 | G45: 1140 | H45: 1182 | I45: 1155 | J45: 1424 | K45: 1246
A46: Interest | B46: 110 | C46: 105 | D46: 108 | E46: 101 | F46: 102 | G46: 105 | H46: 106 | I46: 100 | J46: 105 | K46: 119
A47: Profit before tax | B47: 10240 | C47: 9021 | D47: 9253 | E47: 9670 | F47: 9663 | G47: 9740 | H47: 10229 | I47: 9229 | J47: 10797 | K47: 11028
A48: Tax | B48: 2265 | C48: 2647 | D48: 2737 | E48: 2848 | F48: 2625 | G48: 2816 | H48: 2854 | I48: 2563 | J48: 2288 | K48: 3253
A49: Net profit | B49: 7969 | C49: 6368 | D49: 6506 | E49: 6806 | F49: 7033 | G49: 6921 | H49: 7364 | I49: 6654 | J49: 8501 | K49: 7769
A50: Operating Profit | B50: 8784 | C50: 9437 | D50: 9809 | E50: 10115 | F50: 9874 | G50: 9943 | H50: 10535 | I50: 10634 | J50: 11167 | K50: 11409
A55: BALANCE SHEET
A56: Report Date | B56: 42825 | C56: 43190 | D56: 43555 | E56: 43921 | F56: 44286 | G56: 44651 | H56: 45016 | I56: 45382 | J56: 45747 | K56: 46112
A57: Equity Share Capital | B57: 1144 | C57: 1088 | D57: 2170 | E57: 2122 | F57: 2124 | G57: 2098 | H57: 2069 | I57: 2071 | J57: 2073 | K57: 2024
A58: Reserves | B58: 67838 | C58: 63835 | D58: 62778 | E58: 63328 | F58: 74227 | G58: 73252 | H58: 73338 | I58: 86045 | J58: 93745 | K58: 90828
A59: Borrowings | E59: 4633 | F59: 5325 | G59: 5474 | H59: 8299 | I59: 8359 | J59: 8227 | K59: 9176
A60: Other Liabilities | B60: 14166 | C60: 14426 | D60: 19118 | E60: 21717 | F60: 25835 | G60: 35905 | H60: 40890 | I60: 39545 | J60: 43750 | K60: 52260
A61: Total | B61: 83148 | C61: 79349 | D61: 84066 | E61: 91800 | F61: 107511 | G61: 116729 | H61: 124596 | I61: 136020 | J61: 147795 | K61: 154288
A62: Net Block | B62: 14179 | C62: 12574 | D62: 15710 | E62: 23789 | F62: 25505 | G62: 25800 | H62: 29225 | I62: 27622 | J62: 30961 | K62: 33770
A63: Capital Work in Progress | B63: 1365 | C63: 1606 | D63: 1388 | E63: 954 | F63: 922 | G63: 416 | H63: 288 | I63: 293 | J63: 814 | K63: 526
A64: Investments | B64: 16423 | C64: 12163 | D64: 11261 | E64: 8792 | F64: 14205 | G64: 20324 | H64: 19478 | I64: 24623 | J64: 23541 | K64: 21880
A65: Other Assets | B65: 51181 | C65: 53006 | D65: 55707 | E65: 58265 | F65: 66879 | G65: 70189 | H65: 75605 | I65: 83482 | J65: 92479 | K65: 98112
A66: Total | B66: 83148 | C66: 79349 | D66: 84066 | E66: 91800 | F66: 107511 | G66: 116729 | H66: 124596 | I66: 136020 | J66: 147795 | K66: 154288
A67: Receivables | B67: 12322 | C67: 13142 | D67: 14827 | E67: 18487 | F67: 19294 | G67: 22698 | H67: 25424 | I67: 30193 | J67: 31158 | K67: 35234
A68: Inventory
A69: Cash & Bank | B69: 22625 | C69: 19818 | D69: 19568 | E69: 18649 | F69: 24714 | G69: 17472 | H69: 12173 | I69: 14786 | J69: 24455 | K69: 22201
A70: No. of Equity Shares | B70: 2285655150 | C70: 2173312301 | D70: 4335954462 | E70: 4240753210 | F70: 4245146114 | G70: 4193012929 | H70: 4136387925 | I70: 4139950635 | J70: 4143607528 | K70: 4046940812
A71: New Bonus Shares | D71: 2184191490
A72: Face value | B72: 5 | C72: 5 | D72: 5 | E72: 5 | F72: 5 | G72: 5 | H72: 5 | I72: 5 | J72: 5 | K72: 5
A80: CASH FLOW:
A81: Report Date | B81: 42825 | C81: 43190 | D81: 43555 | E81: 43921 | F81: 44286 | G81: 44651 | H81: 45016 | I81: 45382 | J81: 45747 | K81: 46112
A82: Cash from Operating Activity | B82: 11531 | C82: 13218 | D82: 14841 | E82: 17003 | F82: 23224 | G82: 23885 | H82: 22467 | I82: 25210 | J82: 35694 | K82: 33986
A83: Cash from Investing Activity | B83: -14664 | C83: 4533 | D83: -632 | E83: -331 | F83: -7373 | G83: -6485 | H83: -1071 | I83: -5093 | J83: -1864 | K83: 3546
A84: Cash from Financing Activity | B84: -6939 | C84: -20505 | D84: -14512 | E84: -17591 | F84: -9786 | G84: -24642 | H84: -26695 | I84: -17504 | J84: -24161 | K84: -39786
A85: Net Cash Flow | B85: -10072 | C85: -2754 | D85: -303 | E85: -919 | F85: 6065 | G85: -7242 | H85: -5299 | I85: 2613 | J85: 9669 | K85: -2254
A90: PRICE: | B90: 511.13 | C90: 565.9 | D90: 743.85 | E90: 641.5 | F90: 1368.05 | G90: 1906.85 | H90: 1427.95 | I90: 1498.05 | J90: 1570.65 | K90: 1250.6
A92: DERIVED:
A93: Adjusted Equity Shares in Cr | B93: 459.39 | C93: 436.82 | D93: 436.89 | E93: 425.9 | F93: 426.07 | G93: 420.67 | H93: 414.86 | I93: 415.09 | J93: 415.33 | K93: 405.56

Sheet Profit & Loss
A1: ='Data Sheet >'!B1 -> INFOSYS LTD | H1: =UPDATE | M1: SCREENER.IN
A3: Narration | B3: ='Data Sheet >'!B16 -> 42825 | C3: ='Data Sheet >'!C16 -> 43190 | D3: ='Data Sheet >'!D16 -> 43555 | E3: ='Data Sheet >'!E16 -> 43921 | F3: ='Data Sheet >'!F16 -> 44286 | G3: ='Data Sheet >'!G16 -> 44651 | H3: ='Data Sheet >'!H16 -> 45016 | I3: ='Data Sheet >'!I16 -> 45382 | ... K3: ='Data Sheet >'!K16 -> 46112 | L3: Trailing | M3: Best Case | N3: Worst Case
A4: Sales | B4: ='Data Sheet >'!B17 -> 68484 | C4: ='Data Sheet >'!C17 -> 70522 | D4: ='Data Sheet >'!D17 -> 82675 | E4: ='Data Sheet >'!E17 -> 90791 | F4: ='Data Sheet >'!F17 -> 100472 | G4: ='Data Sheet >'!G17 -> 121641 | H4: ='Data Sheet >'!H17 -> 146767 | I4: ='Data Sheet >'!I17 -> 153670 | ... K4: ='Data Sheet >'!K17 -> 178650 | L4: =SUM(Quarters!H4:K4) -> 184582 | M4: =$K4+M23*K4 -> 195814.61 | N4: =$K4+N23*L4 -> 191150.27
A5: Expenses | B5: =SUM('Data Sheet >'!B18,'Data Sheet >'!B20:B24, -1*'Data Sheet >'!B19) -> 49880 | C5: =SUM('Data Sheet >'!C18,'Data Sheet >'!C20:C24, -1*'Data Sheet >'!C19) -> 51700 | D5: =SUM('Data Sheet >'!D18,'Data Sheet >'!D20:D24, -1*'Data Sheet >'!D19) -> 62505 | E5: =SUM('Data Sheet >'!E18,'Data Sheet >'!E20:E24, -1*'Data Sheet >'!E19) -> 68524 | F5: =SUM('Data Sheet >'!F18,'Data Sheet >'!F20:F24, -1*'Data Sheet >'!F19) -> 72583 | G5: =SUM('Data Sheet >'!G18,'Data Sheet >'!G20:G24, -1*'Data Sheet >'!G19) -> 90150 | H5: =SUM('Data Sheet >'!H18,'Data Sheet >'!H20:H24, -1*'Data Sheet >'!H19) -> 111637 | I5: =SUM('Data Sheet >'!I18,'Data Sheet >'!I20:I24, -1*'Data Sheet >'!I19) -> 117245 | ... K5: =SUM('Data Sheet >'!K18,'Data Sheet >'!K20:K24, -1*'Data Sheet >'!K19) -> 136370 | L5: =SUM(Quarters!H5:K5) -> 140837 | M5: =M4-M6 -> 149188.11 | N5: =N4-N6 -> 145848.62
A6: Operating Profit | B6: =B4-B5 -> 18604 | C6: =C4-C5 -> 18822 | D6: =D4-D5 -> 20170 | E6: =E4-E5 -> 22267 | F6: =F4-F5 -> 27889 | G6: =G4-G5 -> 31491 | H6: =H4-H5 -> 35130 | I6: =I4-I5 -> 36425 | ... K6: =K4-K5 -> 42280 | L6: =SUM(Quarters!H6:K6) -> 43745 | M6: =M4*M24 -> 46626.497 | N6: =N4*N24 -> 45301.646
A7: Other Income | B7: ='Data Sheet >'!B25 -> 3050 | C7: ='Data Sheet >'!C25 -> 3311 | D7: ='Data Sheet >'!D25 -> 2882 | E7: ='Data Sheet >'!E25 -> 2803 | F7: ='Data Sheet >'!F25 -> 2201 | G7: ='Data Sheet >'!G25 -> 2295 | H7: ='Data Sheet >'!H25 -> 2701 | I7: ='Data Sheet >'!I25 -> 4711 | ... K7: ='Data Sheet >'!K25 -> 3033 | L7: =SUM(Quarters!H7:K7) -> 2975 | M7: 0 | N7: 0
A8: Depreciation | B8: ='Data Sheet >'!B26 -> 1703 | C8: ='Data Sheet >'!C26 -> 1863 | D8: ='Data Sheet >'!D26 -> 2011 | E8: ='Data Sheet >'!E26 -> 2893 | F8: ='Data Sheet >'!F26 -> 3267 | G8: ='Data Sheet >'!G26 -> 3476 | H8: ='Data Sheet >'!H26 -> 4225 | I8: ='Data Sheet >'!I26 -> 4678 | ... K8: ='Data Sheet >'!K26 -> 4902 | L8: =SUM(Quarters!H8:K8) -> 5007 | M8: =+$L8 -> 5007 | N8: =+$L8 -> 5007
A9: Interest | B9: ='Data Sheet >'!B27 -> 0 | C9: ='Data Sheet >'!C27 -> 0 | D9: ='Data Sheet >'!D27 -> 0 | E9: ='Data Sheet >'!E27 -> 170 | F9: ='Data Sheet >'!F27 -> 195 | G9: ='Data Sheet >'!G27 -> 200 | H9: ='Data Sheet >'!H27 -> 284 | I9: ='Data Sheet >'!I27 -> 470 | ... K9: ='Data Sheet >'!K27 -> 416 | L9: =SUM(Quarters!H9:K9) -> 430 | M9: =+$L9 -> 430 | N9: =+$L9 -> 430
A10: Profit before tax | B10: ='Data Sheet >'!B28 -> 19951 | C10: ='Data Sheet >'!C28 -> 20270 | D10: ='Data Sheet >'!D28 -> 21041 | E10: ='Data Sheet >'!E28 -> 22007 | F10: ='Data Sheet >'!F28 -> 26628 | G10: ='Data Sheet >'!G28 -> 30110 | H10: ='Data Sheet >'!H28 -> 33322 | I10: ='Data Sheet >'!I28 -> 35988 | ... K10: ='Data Sheet >'!K28 -> 39995 | L10: =SUM(Quarters!H10:K10) -> 41283 | M10: =M6+M7-SUM(M8:M9) -> 41189.497 | N10: =N6+N7-SUM(N8:N9) -> 39864.646
A11: Tax | B11: ='Data Sheet >'!B29 -> 5598 | C11: ='Data Sheet >'!C29 -> 4241 | D11: ='Data Sheet >'!D29 -> 5631 | E11: ='Data Sheet >'!E29 -> 5368 | F11: ='Data Sheet >'!F29 -> 7205 | G11: ='Data Sheet >'!G29 -> 7964 | H11: ='Data Sheet >'!H29 -> 9214 | I11: ='Data Sheet >'!I29 -> 9740 | ... K11: ='Data Sheet >'!K29 -> 10521 | L11: =SUM(Quarters!H11:K11) -> 10958 | M11: =IF($L10>0,$L11/$L10,0) -> 0.26543614 | N11: =IF($L10>0,$L11/$L10,0) -> 0.26543614
A12: Net profit | B12: ='Data Sheet >'!B30 -> 14353 | C12: ='Data Sheet >'!C30 -> 16029 | D12: ='Data Sheet >'!D30 -> 15404 | E12: ='Data Sheet >'!E30 -> 16594 | F12: ='Data Sheet >'!F30 -> 19351 | G12: ='Data Sheet >'!G30 -> 22110 | H12: ='Data Sheet >'!H30 -> 24095 | I12: ='Data Sheet >'!I30 -> 26233 | ... K12: ='Data Sheet >'!K30 -> 29440 | L12: =SUM(Quarters!H12:K12) -> 30288 | M12: =M10-M11*M10 -> 30256.316 | N12: =N10-N11*N10 -> 29283.128
A13: EPS | B13: =IF('Data Sheet >'!B93>0,B12/'Data Sheet >'!B93,0) -> 31.243606 | C13: =IF('Data Sheet >'!C93>0,C12/'Data Sheet >'!C93,0) -> 36.694748 | D13: =IF('Data Sheet >'!D93>0,D12/'Data Sheet >'!D93,0) -> 35.258303 | E13: =IF('Data Sheet >'!E93>0,E12/'Data Sheet >'!E93,0) -> 38.962198 | F13: =IF('Data Sheet >'!F93>0,F12/'Data Sheet >'!F93,0) -> 45.41742 | G13: =IF('Data Sheet >'!G93>0,G12/'Data Sheet >'!G93,0) -> 52.559013 | H13: =IF('Data Sheet >'!H93>0,H12/'Data Sheet >'!H93,0) -> 58.079834 | I13: =IF('Data Sheet >'!I93>0,I12/'Data Sheet >'!I93,0) -> 63.198343 | ... K13: =IF('Data Sheet >'!K93>0,K12/'Data Sheet >'!K93,0) -> 72.590985 | L13: =IF('Data Sheet >'!$B6>0,'Profit & Loss'!L12/'Data Sheet >'!$B6,0) -> 74.559534 | M13: =IF('Data Sheet >'!$B6>0,'Profit & Loss'!M12/'Data Sheet >'!$B6,0) -> 74.481539 | N13: =IF('Data Sheet >'!$B6>0,'Profit & Loss'!N12/'Data Sheet >'!$B6,0) -> 72.085856
A14: Price to earning | B14: =IF(B15>0,B15/B13,"") -> 16.359507 | C14: =IF(C15>0,C15/C13,"") -> 15.421825 | D14: =IF(D15>0,D15/D13,"") -> 21.097158 | E14: =IF(E15>0,E15/E13,"") -> 16.464677 | F14: =IF(F15>0,F15/F13,"") -> 30.121702 | G14: =IF(G15>0,G15/G13,"") -> 36.280171 | H14: =IF(H15>0,H15/H13,"") -> 24.585986 | I14: =IF(I15>0,I15/I13,"") -> 23.703944 | ... K14: =IF(K15>0,K15/K13,"") -> 17.228035 | L14: =IF(L13>0,L15/L13,0) -> 13.597859 | M14: =M25 -> 19.737521 | N14: =N25 -> 13.597859
A15: Price | B15: ='Data Sheet >'!B90 -> 511.13 | C15: ='Data Sheet >'!C90 -> 565.9 | D15: ='Data Sheet >'!D90 -> 743.85 | E15: ='Data Sheet >'!E90 -> 641.5 | F15: ='Data Sheet >'!F90 -> 1368.05 | G15: ='Data Sheet >'!G90 -> 1906.85 | H15: ='Data Sheet >'!H90 -> 1427.95 | I15: ='Data Sheet >'!I90 -> 1498.05 | ... K15: ='Data Sheet >'!K90 -> 1250.6 | L15: ='Data Sheet >'!B8 -> 1013.85 | M15: =M13*M14 -> 1470.0809 | N15: =N13*N14 -> 980.21328
A17: RATIOS:
A18: Dividend Payout | B18: =IF('Data Sheet >'!B30>0, 'Data Sheet >'!B31/'Data Sheet >'!B30, 0) -> 0.41047865 | C18: =IF('Data Sheet >'!C30>0, 'Data Sheet >'!C31/'Data Sheet >'!C30, 0) -> 0.59052966 | D18: =IF('Data Sheet >'!D30>0, 'Data Sheet >'!D31/'Data Sheet >'!D30, 0) -> 0.59870813 | E18: =IF('Data Sheet >'!E30>0, 'Data Sheet >'!E31/'Data Sheet >'!E30, 0) -> 0.44757141 | F18: =IF('Data Sheet >'!F30>0, 'Data Sheet >'!F31/'Data Sheet >'!F30, 0) -> 0.59271355 | G18: =IF('Data Sheet >'!G30>0, 'Data Sheet >'!G31/'Data Sheet >'!G30, 0) -> 0.58831298 | H18: =IF('Data Sheet >'!H30>0, 'Data Sheet >'!H31/'Data Sheet >'!H30, 0) -> 0.58390537 | I18: =IF('Data Sheet >'!I30>0, 'Data Sheet >'!I31/'Data Sheet >'!I30, 0) -> 0.72630656 | ... K18: =IF('Data Sheet >'!K30>0, 'Data Sheet >'!K31/'Data Sheet >'!K30, 0) -> 0.66
A19: OPM | B19: =IF(B6>0,B6/B4,0) -> 0.27165469 | C19: =IF(C6>0,C6/C4,0) -> 0.26689544 | D19: =IF(D6>0,D6/D4,0) -> 0.24396734 | E19: =IF(E6>0,E6/E4,0) -> 0.24525559 | F19: =IF(F6>0,F6/F4,0) -> 0.27757982 | G19: =IF(G6>0,G6/G4,0) -> 0.25888475 | H19: =IF(H6>0,H6/H4,0) -> 0.23935898 | I19: =IF(I6>0,I6/I4,0) -> 0.2370339 | ... L19: =IF(L6>0,L6/L4,0) -> 0.23699494
G22: TRENDS: | H22: 10 YEARS | I22: 7 YEARS | J22: 5 YEARS | K22: 3 YEARS | L22: RECENT | M22: BEST | N22: WORST
G23: Sales Growth | H23: =IF(B4=0,"",POWER($K4/B4,1/9)-1) -> 0.11241852 | I23: =IF(D4=0,"",POWER($K4/D4,1/7)-1) -> 0.11635961 | J23: =IF(F4=0,"",POWER($K4/F4,1/5)-1) -> 0.12199674 | K23: =IF(H4=0,"",POWER($K4/H4, 1/3)-1) -> 0.067722024 | L23: =IF(ISERROR(MAX(IF(J4=0,"",(K4-J4)/J4),IF(K4=0,"",(L4-K4)/K4))),"",MAX(IF(J4=0,"",(K4-J4)/J4),IF(K4=0,"",(L4-K4)/K4))) -> 0.096079514 | M23: =MAX(K23:L23) -> 0.096079514 | N23: =MIN(H23:L23) -> 0.067722024
G24: OPM | H24: =IF(SUM(B4:$K$4)=0,"",SUMPRODUCT(B19:$K$19,B4:$K$4)/SUM(B4:$K$4)) -> 0.24842648 | I24: =IF(SUM(E4:$K$4)=0,"",SUMPRODUCT(E19:$K$19,E4:$K$4)/SUM(E4:$K$4)) -> 0.2457829 | J24: =IF(SUM(G4:$K$4)=0,"",SUMPRODUCT(G19:$K$19,G4:$K$4)/SUM(G4:$K$4)) -> 0.2416625 | K24: =IF(SUM(I4:$K$4)=0, "", SUMPRODUCT(I19:$K$19,I4:$K$4)/SUM(I4:$K$4)) -> 0.23811552 | L24: =L19 -> 0.23699494 | M24: =MAX(K24:L24) -> 0.23811552 | N24: =MIN(H24:L24) -> 0.23699494
G25: Price to Earning | H25: =IF(ISERROR(AVERAGEIF(B14:$L14,">0")),"",AVERAGEIF(B14:$L14,">0")) -> 21.752828 | I25: =IF(ISERROR(AVERAGEIF(E14:$L14,">0")),"",AVERAGEIF(E14:$L14,">0")) -> 23.300328 | J25: =IF(ISERROR(AVERAGEIF(G14:$L14,">0")),"",AVERAGEIF(G14:$L14,">0")) -> 23.302707 | K25: =IF(ISERROR(AVERAGEIF(I14:$L14,">0")),"",AVERAGEIF(I14:$L14,">0")) -> 19.737521 | L25: =L14 -> 13.597859 | M25: =MAX(K25:L25) -> 19.737521 | N25: =MIN(H25:L25) -> 13.597859
A28: Dividend | B28: =B13*B18 -> 12.824833 | C28: =C13*C18 -> 21.669337 | D28: =D13*D18 -> 21.109433 | E28: =E13*E18 -> 17.438366 | F28: =F13*F18 -> 26.91952 | G28: =G13*G18 -> 30.92115 | H28: =H13*H18 -> 33.913127 | I28: =I13*I18 -> 45.901371 | ... K28: =K13*K18 -> 47.91005
A29: Dividend Growth | C29: =C28/B28-1 -> 0.68963897 | D29: =D28/C28-1 -> -0.02583858 | E29: =E28/D28-1 -> -0.17390646 | F29: =F28/E28-1 -> 0.54369512 | G29: =G28/F28-1 -> 0.14865158 | H29: =H28/G28-1 -> 0.096761529 | I29: =I28/H28-1 -> 0.35349861 | J29: =J28/I28-1 -> -0.064855345 | K29: =K28/J28-1 -> 0.116149
A31: Market Capitalization | B31: ='Data Sheet >'!B93*'Data Sheet >'!B90 -> 234808.01 | C31: ='Data Sheet >'!C93*'Data Sheet >'!C90 -> 247196.44 | D31: ='Data Sheet >'!D93*'Data Sheet >'!D90 -> 324980.63 | E31: ='Data Sheet >'!E93*'Data Sheet >'!E90 -> 273214.85 | F31: ='Data Sheet >'!F93*'Data Sheet >'!F90 -> 582885.06 | G31: ='Data Sheet >'!G93*'Data Sheet >'!G90 -> 802154.59 | H31: ='Data Sheet >'!H93*'Data Sheet >'!H90 -> 592399.34 | I31: ='Data Sheet >'!I93*'Data Sheet >'!I90 -> 621825.57 | ... K31: ='Data Sheet >'!K93*'Data Sheet >'!K90 -> 507193.34
A32: Debt | B32: ='Data Sheet >'!B59 -> 0 | C32: ='Data Sheet >'!C59 -> 0 | D32: ='Data Sheet >'!D59 -> 0 | E32: ='Data Sheet >'!E59 -> 4633 | F32: ='Data Sheet >'!F59 -> 5325 | G32: ='Data Sheet >'!G59 -> 5474 | H32: ='Data Sheet >'!H59 -> 8299 | I32: ='Data Sheet >'!I59 -> 8359 | ... K32: ='Data Sheet >'!K59 -> 9176
A33: Cash | B33: ='Data Sheet >'!B69 -> 22625 | C33: ='Data Sheet >'!C69 -> 19818 | D33: ='Data Sheet >'!D69 -> 19568 | E33: ='Data Sheet >'!E69 -> 18649 | F33: ='Data Sheet >'!F69 -> 24714 | G33: ='Data Sheet >'!G69 -> 17472 | H33: ='Data Sheet >'!H69 -> 12173 | I33: ='Data Sheet >'!I69 -> 14786 | ... K33: ='Data Sheet >'!K69 -> 22201
A34: EV | B34: =B31+B32-B33 -> 212183.01 | C34: =C31+C32-C33 -> 227378.44 | D34: =D31+D32-D33 -> 305412.63 | E34: =E31+E32-E33 -> 259198.85 | F34: =F31+F32-F33 -> 563496.06 | G34: =G31+G32-G33 -> 790156.59 | H34: =H31+H32-H33 -> 588525.34 | I34: =I31+I32-I33 -> 615398.57 | ... K34: =K31+K32-K33 -> 494168.34
A35: EV/EBITDA | B35: =B34/B6 -> 11.405236 | C35: =C34/C6 -> 12.080461 | D35: =D34/D6 -> 15.141925 | E35: =E34/E6 -> 11.640493 | F35: =F34/F6 -> 20.204958 | G35: =G34/G6 -> 25.091505 | H35: =H34/H6 -> 16.752785 | I35: =I34/I6 -> 16.894951 | ... K35: =K34/K6 -> 11.687993
A36: EV/Sales | B36: =B34/B4 -> 3.0982859 | C36: =C34/C4 -> 3.2242199 | D36: =D34/D4 -> 3.6941352 | E36: =E34/E4 -> 2.8548959 | F36: =F34/F4 -> 5.6084886 | G36: =G34/G4 -> 6.4958081 | H36: =H34/H4 -> 4.0099296 | I36: =I34/I4 -> 4.0046761 | ... K36: =K34/K4 -> 2.7661256
A37: P/B | B37: =B31/'His Balance Sheet'!B26 -> 3.4039026 | C37: =C31/'His Balance Sheet'!C26 -> 3.8075326 | D37: =D31/'His Balance Sheet'!D26 -> 5.0037049 | E37: =E31/'His Balance Sheet'!E26 -> 4.1744057 | F37: =F31/'His Balance Sheet'!F26 -> 7.634282 | G37: =G31/'His Balance Sheet'!G26 -> 10.645715 | H37: =H31/'His Balance Sheet'!H26 -> 7.8560258 | I37: =I31/'His Balance Sheet'!I26 -> 7.0568974 | ... K37: =K31/'His Balance Sheet'!K26 -> 5.4623846

Sheet Cash Flow Data
C2: 42064 | D2: 42430 | E2: 42795 | F2: 43160 | G2: 43525 | H2: 43891 | I2: 44256 | J2: 44621 | K2: 44986 | L2: 45352 | M2: 45717 | N2: 46082
B3: Cash from Operating Activity - | C3: 11880 | D3: 11455 | E3: 10824 | F3: 8023 | G3: 25336 | H3: 20169 | I3: 44327 | J3: 44381 | K3: 21683 | L3: 20301 | M3: 23138 | N3: 35064
B4: Profit from operations | C4: 13955 | D4: 6824 | E4: 17581 | F4: 20187 | G4: 27840 | H4: 18078 | I4: 28540 | J4: 65900 | K4: 30908 | L4: 22237 | M4: 23929 | N4: 34219
B5: Receivables | C5: 1442 | D5: 0 | E5: 0 | F5: 0 | G5: 0 | H5: 0 | I5: 0 | J5: 0 | K5: 0 | L5: 0 | M5: 0 | N5: 0
B6: Inventory | C6: -485 | D6: 5618 | E6: -8243 | F6: -1595 | G6: -1069 | H6: 1562 | I6: 46 | J6: -16917 | K6: -4031 | L6: 5566 | M6: 4776 | N6: 1290
B7: Payables | C7: -605 | D7: 0 | E7: 0 | F7: 0 | G7: 0 | H7: 0 | I7: 0 | J7: 0 | K7: 0 | L7: 0 | M7: 0 | N7: 0
B8: Other WC items | C8: 0 | D8: 548 | E8: 3329 | F8: -7680 | G8: 3659 | H8: 2634 | I8: 16446 | J8: 7299 | K8: 325 | L8: -2182 | M8: -2569 | N8: 4152
B9: Working capital changes | C9: 351 | D9: 6166 | E9: -4914 | F9: -9276 | G9: 2591 | H9: 4196 | I9: 16491 | J9: -9618 | K9: -3706 | L9: 3384 | M9: 2207 | N9: 5442
B10: Direct taxes | C10: -2427 | D10: -1534 | E10: -1843 | F10: -2888 | G10: -5094 | H10: -2106 | I10: -704 | J10: -11902 | K10: -5519 | L10: -5320 | M10: -2998 | N10: -4597
B11: Cash from Investing Activity - | C11: -9021 | D11: -8794 | E11: -9490 | F11: -11730 | G11: -29176 | H11: -14012 | I11: -9437 | J11: -10905 | K11: -18179 | L11: -14253 | M11: -13611 | N11: -14397
B12: Fixed assets purchased | C12: -13492 | D12: -10163 | E12: -7716 | F12: -7478 | G12: -9091 | H12: -10398 | I12: -6979 | J12: -10522 | K12: -14142 | L12: -18207 | M12: -15671 | N12: -14559
B13: Fixed assets sold | C13: 1444 | D13: 231 | E13: 289 | F13: 179 | G13: 467 | H13: 386 | I13: 445 | J13: 569 | K13: 328 | L13: 475 | M13: 1264 | N13: 1401
B14: Investments purchased | C14: 1531 | D14: -3796 | E14: -861 | F14: -8641 | G14: -490 | H14: -828 | I14: -3631 | J14: -1153 | K14: -326 | L14: -4 | M14: -393 | N14: -553
... B32: CFO/OP | C32: 4.2 | D32: -20.78 | E32: 0.96 | F32: 0.51 | G32: 1.04 | H32: 1.28 | I32: 1.48 | J32: 0.89 | K32: 0.84 | L32: 1.15 | M32: 1.03 | N32: 1.15

Sheet Quarters
A1: ='Profit & Loss'!A1 -> INFOSYS LTD | E1: =UPDATE | J1: SCREENER.IN
A3: Narration | B3: ='Data Sheet >'!B41 -> 45382 | C3: ='Data Sheet >'!C41 -> 45473 | D3: ='Data Sheet >'!D41 -> 45565 | E3: ='Data Sheet >'!E41 -> 45657 | F3: ='Data Sheet >'!F41 -> 45747 | G3: ='Data Sheet >'!G41 -> 45838 | H3: ='Data Sheet >'!H41 -> 45930 | I3: ='Data Sheet >'!I41 -> 46022 | ... K3: ='Data Sheet >'!K41 -> 46203
A4: Sales | B4: ='Data Sheet >'!B42 -> 37923 | C4: ='Data Sheet >'!C42 -> 39315 | D4: ='Data Sheet >'!D42 -> 40986 | E4: ='Data Sheet >'!E42 -> 41764 | F4: ='Data Sheet >'!F42 -> 40925 | G4: ='Data Sheet >'!G42 -> 42279 | H4: ='Data Sheet >'!H42 -> 44490 | I4: ='Data Sheet >'!I42 -> 45479 | ... K4: ='Data Sheet >'!K42 -> 48211
A5: Expenses | B5: ='Data Sheet >'!B43 -> 29139 | C5: ='Data Sheet >'!C43 -> 29878 | D5: ='Data Sheet >'!D43 -> 31177 | E5: ='Data Sheet >'!E43 -> 31649 | F5: ='Data Sheet >'!F43 -> 31051 | G5: ='Data Sheet >'!G43 -> 32336 | H5: ='Data Sheet >'!H43 -> 33955 | I5: ='Data Sheet >'!I43 -> 34845 | ... K5: ='Data Sheet >'!K43 -> 36802
A6: Operating Profit | B6: ='Data Sheet >'!B50 -> 8784 | C6: ='Data Sheet >'!C50 -> 9437 | D6: ='Data Sheet >'!D50 -> 9809 | E6: ='Data Sheet >'!E50 -> 10115 | F6: ='Data Sheet >'!F50 -> 9874 | G6: ='Data Sheet >'!G50 -> 9943 | H6: ='Data Sheet >'!H50 -> 10535 | I6: ='Data Sheet >'!I50 -> 10634 | ... K6: ='Data Sheet >'!K50 -> 11409
A7: Other Income | B7: ='Data Sheet >'!B44 -> 2729 | C7: ='Data Sheet >'!C44 -> 838 | D7: ='Data Sheet >'!D44 -> 712 | E7: ='Data Sheet >'!E44 -> 859 | F7: ='Data Sheet >'!F44 -> 1190 | G7: ='Data Sheet >'!G44 -> 1042 | H7: ='Data Sheet >'!H44 -> 982 | I7: ='Data Sheet >'!I44 -> -150 | ... K7: ='Data Sheet >'!K44 -> 984
A8: Depreciation | B8: ='Data Sheet >'!B45 -> 1163 | C8: ='Data Sheet >'!C45 -> 1149 | D8: ='Data Sheet >'!D45 -> 1160 | E8: ='Data Sheet >'!E45 -> 1203 | F8: ='Data Sheet >'!F45 -> 1299 | G8: ='Data Sheet >'!G45 -> 1140 | H8: ='Data Sheet >'!H45 -> 1182 | I8: ='Data Sheet >'!I45 -> 1155 | ... K8: ='Data Sheet >'!K45 -> 1246
A9: Interest | B9: ='Data Sheet >'!B46 -> 110 | C9: ='Data Sheet >'!C46 -> 105 | D9: ='Data Sheet >'!D46 -> 108 | E9: ='Data Sheet >'!E46 -> 101 | F9: ='Data Sheet >'!F46 -> 102 | G9: ='Data Sheet >'!G46 -> 105 | H9: ='Data Sheet >'!H46 -> 106 | I9: ='Data Sheet >'!I46 -> 100 | ... K9: ='Data Sheet >'!K46 -> 119
A10: Profit before tax | B10: ='Data Sheet >'!B47 -> 10240 | C10: ='Data Sheet >'!C47 -> 9021 | D10: ='Data Sheet >'!D47 -> 9253 | E10: ='Data Sheet >'!E47 -> 9670 | F10: ='Data Sheet >'!F47 -> 9663 | G10: ='Data Sheet >'!G47 -> 9740 | H10: ='Data Sheet >'!H47 -> 10229 | I10: ='Data Sheet >'!I47 -> 9229 | ... K10: ='Data Sheet >'!K47 -> 11028
A11: Tax | B11: ='Data Sheet >'!B48 -> 2265 | C11: ='Data Sheet >'!C48 -> 2647 | D11: ='Data Sheet >'!D48 -> 2737 | E11: ='Data Sheet >'!E48 -> 2848 | F11: ='Data Sheet >'!F48 -> 2625 | G11: ='Data Sheet >'!G48 -> 2816 | H11: ='Data Sheet >'!H48 -> 2854 | I11: ='Data Sheet >'!I48 -> 2563 | ... K11: ='Data Sheet >'!K48 -> 3253
A12: Net profit | B12: ='Data Sheet >'!B49 -> 7969 | C12: ='Data Sheet >'!C49 -> 6368 | D12: ='Data Sheet >'!D49 -> 6506 | E12: ='Data Sheet >'!E49 -> 6806 | F12: ='Data Sheet >'!F49 -> 7033 | G12: ='Data Sheet >'!G49 -> 6921 | H12: ='Data Sheet >'!H49 -> 7364 | I12: ='Data Sheet >'!I49 -> 6654 | ... K12: ='Data Sheet >'!K49 -> 7769
A14: OPM | B14: =IF(B4>0,B6/B4,"") -> 0.23162724 | C14: =IF(C4>0,C6/C4,"") -> 0.24003561 | D14: =IF(D4>0,D6/D4,"") -> 0.23932562 | E14: =IF(E4>0,E6/E4,"") -> 0.24219423 | F14: =IF(F4>0,F6/F4,"") -> 0.24127062 | G14: =IF(G4>0,G6/G4,"") -> 0.23517586 | H14: =IF(H4>0,H6/H4,"") -> 0.23679479 | I14: =IF(I4>0,I6/I4,"") -> 0.2338222 | ... K14: =IF(K4>0,K6/K4,"") -> 0.23664724

Sheet His Balance Sheet
A1: ='Profit & Loss'!A1 -> INFOSYS LTD | E1: =UPDATE | J1: SCREENER.IN
A3: Narration | B3: ='Data Sheet >'!B56 -> 42825 | C3: ='Data Sheet >'!C56 -> 43190 | D3: ='Data Sheet >'!D56 -> 43555 | E3: ='Data Sheet >'!E56 -> 43921 | F3: ='Data Sheet >'!F56 -> 44286 | G3: ='Data Sheet >'!G56 -> 44651 | H3: ='Data Sheet >'!H56 -> 45016 | I3: ='Data Sheet >'!I56 -> 45382 | ... K3: ='Data Sheet >'!K56 -> 46112
A4: Equity Share Capital | B4: ='Data Sheet >'!B57 -> 1144 | C4: ='Data Sheet >'!C57 -> 1088 | D4: ='Data Sheet >'!D57 -> 2170 | E4: ='Data Sheet >'!E57 -> 2122 | F4: ='Data Sheet >'!F57 -> 2124 | G4: ='Data Sheet >'!G57 -> 2098 | H4: ='Data Sheet >'!H57 -> 2069 | I4: ='Data Sheet >'!I57 -> 2071 | ... K4: ='Data Sheet >'!K57 -> 2024
A5: Reserves | B5: ='Data Sheet >'!B58 -> 67838 | C5: ='Data Sheet >'!C58 -> 63835 | D5: ='Data Sheet >'!D58 -> 62778 | E5: ='Data Sheet >'!E58 -> 63328 | F5: ='Data Sheet >'!F58 -> 74227 | G5: ='Data Sheet >'!G58 -> 73252 | H5: ='Data Sheet >'!H58 -> 73338 | I5: ='Data Sheet >'!I58 -> 86045 | ... K5: ='Data Sheet >'!K58 -> 90828
A6: Borrowings | B6: ='Data Sheet >'!B59 -> 0 | C6: ='Data Sheet >'!C59 -> 0 | D6: ='Data Sheet >'!D59 -> 0 | E6: ='Data Sheet >'!E59 -> 4633 | F6: ='Data Sheet >'!F59 -> 5325 | G6: ='Data Sheet >'!G59 -> 5474 | H6: ='Data Sheet >'!H59 -> 8299 | I6: ='Data Sheet >'!I59 -> 8359 | ... K6: ='Data Sheet >'!K59 -> 9176
A7: Other Liabilities | B7: ='Data Sheet >'!B60 -> 14166 | C7: ='Data Sheet >'!C60 -> 14426 | D7: ='Data Sheet >'!D60 -> 19118 | E7: ='Data Sheet >'!E60 -> 21717 | F7: ='Data Sheet >'!F60 -> 25835 | G7: ='Data Sheet >'!G60 -> 35905 | H7: ='Data Sheet >'!H60 -> 40890 | I7: ='Data Sheet >'!I60 -> 39545 | ... K7: ='Data Sheet >'!K60 -> 52260
A8: Total | B8: ='Data Sheet >'!B61 -> 83148 | C8: ='Data Sheet >'!C61 -> 79349 | D8: ='Data Sheet >'!D61 -> 84066 | E8: ='Data Sheet >'!E61 -> 91800 | F8: ='Data Sheet >'!F61 -> 107511 | G8: ='Data Sheet >'!G61 -> 116729 | H8: ='Data Sheet >'!H61 -> 124596 | I8: ='Data Sheet >'!I61 -> 136020 | ... K8: ='Data Sheet >'!K61 -> 154288
A10: Net Block | B10: ='Data Sheet >'!B62 -> 14179 | C10: ='Data Sheet >'!C62 -> 12574 | D10: ='Data Sheet >'!D62 -> 15710 | E10: ='Data Sheet >'!E62 -> 23789 | F10: ='Data Sheet >'!F62 -> 25505 | G10: ='Data Sheet >'!G62 -> 25800 | H10: ='Data Sheet >'!H62 -> 29225 | I10: ='Data Sheet >'!I62 -> 27622 | ... K10: ='Data Sheet >'!K62 -> 33770
A11: Capital Work in Progress | B11: ='Data Sheet >'!B63 -> 1365 | C11: ='Data Sheet >'!C63 -> 1606 | D11: ='Data Sheet >'!D63 -> 1388 | E11: ='Data Sheet >'!E63 -> 954 | F11: ='Data Sheet >'!F63 -> 922 | G11: ='Data Sheet >'!G63 -> 416 | H11: ='Data Sheet >'!H63 -> 288 | I11: ='Data Sheet >'!I63 -> 293 | ... K11: ='Data Sheet >'!K63 -> 526
A12: Investments | B12: ='Data Sheet >'!B64 -> 16423 | C12: ='Data Sheet >'!C64 -> 12163 | D12: ='Data Sheet >'!D64 -> 11261 | E12: ='Data Sheet >'!E64 -> 8792 | F12: ='Data Sheet >'!F64 -> 14205 | G12: ='Data Sheet >'!G64 -> 20324 | H12: ='Data Sheet >'!H64 -> 19478 | I12: ='Data Sheet >'!I64 -> 24623 | ... K12: ='Data Sheet >'!K64 -> 21880
A13: Other Assets | B13: ='Data Sheet >'!B65 -> 51181 | C13: ='Data Sheet >'!C65 -> 53006 | D13: ='Data Sheet >'!D65 -> 55707 | E13: ='Data Sheet >'!E65 -> 58265 | F13: ='Data Sheet >'!F65 -> 66879 | G13: ='Data Sheet >'!G65 -> 70189 | H13: ='Data Sheet >'!H65 -> 75605 | I13: ='Data Sheet >'!I65 -> 83482 | ... K13: ='Data Sheet >'!K65 -> 98112
A14: Total | B14: ='Data Sheet >'!B66 -> 83148 | C14: ='Data Sheet >'!C66 -> 79349 | D14: ='Data Sheet >'!D66 -> 84066 | E14: ='Data Sheet >'!E66 -> 91800 | F14: ='Data Sheet >'!F66 -> 107511 | G14: ='Data Sheet >'!G66 -> 116729 | H14: ='Data Sheet >'!H66 -> 124596 | I14: ='Data Sheet >'!I66 -> 136020 | ... K14: ='Data Sheet >'!K66 -> 154288
A16: Working Capital | B16: =B13-B7 -> 37015 | C16: =C13-C7 -> 38580 | D16: =D13-D7 -> 36589 | E16: =E13-E7 -> 36548 | F16: =F13-F7 -> 41044 | G16: =G13-G7 -> 34284 | H16: =H13-H7 -> 34715 | I16: =I13-I7 -> 43937 | ... K16: =K13-K7 -> 45852
A17: Debtors | B17: ='Data Sheet >'!B67 -> 12322 | C17: ='Data Sheet >'!C67 -> 13142 | D17: ='Data Sheet >'!D67 -> 14827 | E17: ='Data Sheet >'!E67 -> 18487 | F17: ='Data Sheet >'!F67 -> 19294 | G17: ='Data Sheet >'!G67 -> 22698 | H17: ='Data Sheet >'!H67 -> 25424 | I17: ='Data Sheet >'!I67 -> 30193 | ... K17: ='Data Sheet >'!K67 -> 35234
A18: Inventory | B18: ='Data Sheet >'!B68 -> 0 | C18: ='Data Sheet >'!C68 -> 0 | D18: ='Data Sheet >'!D68 -> 0 | E18: ='Data Sheet >'!E68 -> 0 | F18: ='Data Sheet >'!F68 -> 0 | G18: ='Data Sheet >'!G68 -> 0 | H18: ='Data Sheet >'!H68 -> 0 | I18: ='Data Sheet >'!I68 -> 0 | ... K18: ='Data Sheet >'!K68 -> 0
A20: Debtor Days | B20: =IF('Profit & Loss'!B4>0,'His Balance Sheet'!B17/('Profit & Loss'!B4/365),0) -> 65.672712 | C20: =IF('Profit & Loss'!C4>0,'His Balance Sheet'!C17/('Profit & Loss'!C4/365),0) -> 68.018916 | D20: =IF('Profit & Loss'!D4>0,'His Balance Sheet'!D17/('Profit & Loss'!D4/365),0) -> 65.459389 | E20: =IF('Profit & Loss'!E4>0,'His Balance Sheet'!E17/('Profit & Loss'!E4/365),0) -> 74.321849 | F20: =IF('Profit & Loss'!F4>0,'His Balance Sheet'!F17/('Profit & Loss'!F4/365),0) -> 70.092265 | G20: =IF('Profit & Loss'!G4>0,'His Balance Sheet'!G17/('Profit & Loss'!G4/365),0) -> 68.108368 | H20: =IF('Profit & Loss'!H4>0,'His Balance Sheet'!H17/('Profit & Loss'!H4/365),0) -> 63.227837 | I20: =IF('Profit & Loss'!I4>0,'His Balance Sheet'!I17/('Profit & Loss'!I4/365),0) -> 71.715006 | ... K20: =IF('Profit & Loss'!K4>0,'His Balance Sheet'!K17/('Profit & Loss'!K4/365),0) -> 71.986622
A21: Inventory Turnover | B21: =IF('His Balance Sheet'!B18>0,'Profit & Loss'!B4/'His Balance Sheet'!B18,0) -> 0 | C21: =IF('His Balance Sheet'!C18>0,'Profit & Loss'!C4/'His Balance Sheet'!C18,0) -> 0 | D21: =IF('His Balance Sheet'!D18>0,'Profit & Loss'!D4/'His Balance Sheet'!D18,0) -> 0 | E21: =IF('His Balance Sheet'!E18>0,'Profit & Loss'!E4/'His Balance Sheet'!E18,0) -> 0 | F21: =IF('His Balance Sheet'!F18>0,'Profit & Loss'!F4/'His Balance Sheet'!F18,0) -> 0 | G21: =IF('His Balance Sheet'!G18>0,'Profit & Loss'!G4/'His Balance Sheet'!G18,0) -> 0 | H21: =IF('His Balance Sheet'!H18>0,'Profit & Loss'!H4/'His Balance Sheet'!H18,0) -> 0 | I21: =IF('His Balance Sheet'!I18>0,'Profit & Loss'!I4/'His Balance Sheet'!I18,0) -> 0 | ... K21: =IF('His Balance Sheet'!K18>0,'Profit & Loss'!K4/'His Balance Sheet'!K18,0) -> 0
A23: Return on Equity | B23: =IF(SUM('His Balance Sheet'!B4:B5)>0,'Profit & Loss'!B12/SUM('His Balance Sheet'!B4:B5),"") -> 0.20806877 | C23: =IF(SUM('His Balance Sheet'!C4:C5)>0,'Profit & Loss'!C12/SUM('His Balance Sheet'!C4:C5),"") -> 0.24689247 | D23: =IF(SUM('His Balance Sheet'!D4:D5)>0,'Profit & Loss'!D12/SUM('His Balance Sheet'!D4:D5),"") -> 0.23717435 | E23: =IF(SUM('His Balance Sheet'!E4:E5)>0,'Profit & Loss'!E12/SUM('His Balance Sheet'!E4:E5),"") -> 0.25353705 | F23: =IF(SUM('His Balance Sheet'!F4:F5)>0,'Profit & Loss'!F12/SUM('His Balance Sheet'!F4:F5),"") -> 0.25344789 | G23: =IF(SUM('His Balance Sheet'!G4:G5)>0,'Profit & Loss'!G12/SUM('His Balance Sheet'!G4:G5),"") -> 0.29343066 | H23: =IF(SUM('His Balance Sheet'!H4:H5)>0,'Profit & Loss'!H12/SUM('His Balance Sheet'!H4:H5),"") -> 0.31953267 | I23: =IF(SUM('His Balance Sheet'!I4:I5)>0,'Profit & Loss'!I12/SUM('His Balance Sheet'!I4:I5),"") -> 0.29770984 | ... K23: =IF(SUM('His Balance Sheet'!K4:K5)>0,'Profit & Loss'!K12/SUM('His Balance Sheet'!K4:K5),"") -> 0.31706371
A24: Return on Capital Emp | C24: =IF((B4+B5+B6+C4+C5+C6)>0,('Profit & Loss'!C10+'Profit & Loss'!C9)*2/(B4+B5+B6+C4+C5+C6),"") -> 0.30275195 | D24: =IF((C4+C5+C6+D4+D5+D6)>0,('Profit & Loss'!D10+'Profit & Loss'!D9)*2/(C4+C5+C6+D4+D5+D6),"") -> 0.32402923 | E24: =IF((D4+D5+D6+E4+E5+E6)>0,('Profit & Loss'!E10+'Profit & Loss'!E9)*2/(D4+D5+D6+E4+E5+E6),"") -> 0.32847272 | F24: =IF((E4+E5+E6+F4+F5+F6)>0,('Profit & Loss'!F10+'Profit & Loss'!F9)*2/(E4+E5+E6+F4+F5+F6),"") -> 0.35349469 | G24: =IF((F4+F5+F6+G4+G5+G6)>0,('Profit & Loss'!G10+'Profit & Loss'!G9)*2/(F4+F5+F6+G4+G5+G6),"") -> 0.37304615 | H24: =IF((G4+G5+G6+H4+H5+H6)>0,('Profit & Loss'!H10+'Profit & Loss'!H9)*2/(G4+G5+G6+H4+H5+H6),"") -> 0.40850909 | I24: =IF((H4+H5+H6+I4+I5+I6)>0,('Profit & Loss'!I10+'Profit & Loss'!I9)*2/(H4+H5+H6+I4+I5+I6),"") -> 0.40468196 | J24: =IF((I4+I5+I6+J4+J5+J6)>0,('Profit & Loss'!J10+'Profit & Loss'!J9)*2/(I4+I5+I6+J4+J5+J6),"") -> 0.37925394 | K24: =IF((J4+J5+J6+K4+K5+K6)>0,('Profit & Loss'!K10+'Profit & Loss'!K9)*2/(J4+J5+J6+K4+K5+K6),"") -> 0.39220082
A26: Book Value | B26: =B4+B5 -> 68982 | C26: =C4+C5 -> 64923 | D26: =D4+D5 -> 64948 | E26: =E4+E5 -> 65450 | F26: =F4+F5 -> 76351 | G26: =G4+G5 -> 75350 | H26: =H4+H5 -> 75407 | I26: =I4+I5 -> 88116 | ... K26: =K4+K5 -> 92852

Sheet Cash Flow
A1: ='His Balance Sheet'!A1 -> INFOSYS LTD | E1: =UPDATE | J1: SCREENER.IN
A3: Narration | B3: ='Data Sheet >'!B81 -> 42825 | C3: ='Data Sheet >'!C81 -> 43190 | D3: ='Data Sheet >'!D81 -> 43555 | E3: ='Data Sheet >'!E81 -> 43921 | F3: ='Data Sheet >'!F81 -> 44286 | G3: ='Data Sheet >'!G81 -> 44651 | H3: ='Data Sheet >'!H81 -> 45016 | I3: ='Data Sheet >'!I81 -> 45382 | ... K3: ='Data Sheet >'!K81 -> 46112
A4: Cash from Operating Activity | B4: ='Data Sheet >'!B82 -> 11531 | C4: ='Data Sheet >'!C82 -> 13218 | D4: ='Data Sheet >'!D82 -> 14841 | E4: ='Data Sheet >'!E82 -> 17003 | F4: ='Data Sheet >'!F82 -> 23224 | G4: ='Data Sheet >'!G82 -> 23885 | H4: ='Data Sheet >'!H82 -> 22467 | I4: ='Data Sheet >'!I82 -> 25210 | ... K4: ='Data Sheet >'!K82 -> 33986
A5: Cash from Investing Activity | B5: ='Data Sheet >'!B83 -> -14664 | C5: ='Data Sheet >'!C83 -> 4533 | D5: ='Data Sheet >'!D83 -> -632 | E5: ='Data Sheet >'!E83 -> -331 | F5: ='Data Sheet >'!F83 -> -7373 | G5: ='Data Sheet >'!G83 -> -6485 | H5: ='Data Sheet >'!H83 -> -1071 | I5: ='Data Sheet >'!I83 -> -5093 | ... K5: ='Data Sheet >'!K83 -> 3546
A6: Cash from Financing Activity | B6: ='Data Sheet >'!B84 -> -6939 | C6: ='Data Sheet >'!C84 -> -20505 | D6: ='Data Sheet >'!D84 -> -14512 | E6: ='Data Sheet >'!E84 -> -17591 | F6: ='Data Sheet >'!F84 -> -9786 | G6: ='Data Sheet >'!G84 -> -24642 | H6: ='Data Sheet >'!H84 -> -26695 | I6: ='Data Sheet >'!I84 -> -17504 | ... K6: ='Data Sheet >'!K84 -> -39786
A7: Net Cash Flow | B7: ='Data Sheet >'!B85 -> -10072 | C7: ='Data Sheet >'!C85 -> -2754 | D7: ='Data Sheet >'!D85 -> -303 | E7: ='Data Sheet >'!E85 -> -919 | F7: ='Data Sheet >'!F85 -> 6065 | G7: ='Data Sheet >'!G85 -> -7242 | H7: ='Data Sheet >'!H85 -> -5299 | I7: ='Data Sheet >'!I85 -> 2613 | ... K7: ='Data Sheet >'!K85 -> -2254
